Workbook

Sheet Winery Departments
A1: Winery | B1: Job Function / Department | C1: Count | E1: Winery | F1: LinkedIn Members | G1: Displayed Function Count Sum | H1: Displayed Sum / Members | I1: Note
A2: Purcari Wineries | B2: Operations | C2: 24 | E2: Purcari Wineries | F2: 103 | G2: =SUMIF('Winery Departments'!$A:$A,E2,'Winery Departments'!$C:$C) -> 72 | H2: =G2/F2 -> 0.69902913 | I2: =IF(G2>F2,"Department categories overlap","Displayed categories do not exceed total") -> Displayed categories do not exceed total
A3: Purcari Wineries | B3: Marketing | C3: 20 | E3: Cramele Recas | F3: 71 | G3: =SUMIF('Winery Departments'!$A:$A,E3,'Winery Departments'!$C:$C) -> 62 | H3: 0.87323944 | I3: Displayed categories do not exceed total
A4: Purcari Wineries | B4: Sales | C4: 14 | E4: Jidvei | F4: 116 | G4: =SUMIF('Winery Departments'!$A:$A,E4,'Winery Departments'!$C:$C) -> 73 | H4: 0.62931034 | I4: Displayed categories do not exceed total
A5: Purcari Wineries | B5: Accounting | C5: 7 | E5: Cramele Cotnari | F5: 23 | G5: =SUMIF('Winery Departments'!$A:$A,E5,'Winery Departments'!$C:$C) -> 21 | H5: 0.91304348 | I5: Displayed categories do not exceed total
A6: Purcari Wineries | B6: Human Resources | C6: 7 | E6: Beciul Domnesc | F6: 115 | G6: =SUMIF('Winery Departments'!$A:$A,E6,'Winery Departments'!$C:$C) -> 76 | H6: 0.66086957 | I6: Displayed categories do not exceed total
A7: Cramele Recas | B7: Sales | C7: 34 | E7: Crama Ceptura | F7: 9 | G7: =SUMIF('Winery Departments'!$A:$A,E7,'Winery Departments'!$C:$C) -> 8 | H7: 0.88888889 | I7: Displayed categories do not exceed total
A8: Cramele Recas | B8: Operations | C8: 16 | E8: Domeniile Averesti | F8: 10 | G8: =SUMIF('Winery Departments'!$A:$A,E8,'Winery Departments'!$C:$C) -> 11 | H8: 1.1 | I8: Department categories overlap
A9: Cramele Recas | B9: Business Development | C9: 5 | E9: Budureasca | F9: 39 | G9: =SUMIF('Winery Departments'!$A:$A,E9,'Winery Departments'!$C:$C) -> 32 | H9: 0.82051282 | I9: Displayed categories do not exceed total
A10: Cramele Recas | B10: Engineering | C10: 4 | E10: Tohani Romania | F10: 10 | G10: =SUMIF('Winery Departments'!$A:$A,E10,'Winery Departments'!$C:$C) -> 10 | H10: 1 | I10: Displayed categories do not exceed total
A11: Cramele Recas | B11: Marketing | C11: 3 | E11: Murfatlar | F11: 14 | G11: =SUMIF('Winery Departments'!$A:$A,E11,'Winery Departments'!$C:$C) -> 11 | H11: 0.78571429 | I11: Displayed categories do not exceed total
A12: Jidvei | B12: Sales | C12: 25 | E12: Davino Winery | F12: 9 | G12: =SUMIF('Winery Departments'!$A:$A,E12,'Winery Departments'!$C:$C) -> 11 | H12: 1.2222222 | I12: Department categories overlap
A13: Jidvei | B13: Operations | C13: 17 | E13: Domeniile Ostrov | F13: 10 | G13: =SUMIF('Winery Departments'!$A:$A,E13,'Winery Departments'!$C:$C) -> 9 | H13: 0.9 | I13: Displayed categories do not exceed total
A14: Jidvei | B14: Engineering | C14: 14 | E14: Casa de Vinuri Cotnari SA | F14: 17 | G14: =SUMIF('Winery Departments'!$A:$A,E14,'Winery Departments'!$C:$C) -> 16 | H14: 0.94117647 | I14: Displayed categories do not exceed total
... A16: Jidvei | B16: Administrative | C16: 8 | E16: Via Viticola | F16: 45 | G16: =SUMIF('Winery Departments'!$A:$A,E16,'Winery Departments'!$C:$C) -> 34 | H16: 0.75555556 | I16: Marketing company of Vintruvian Estates
A17: Cramele Cotnari | B17: Sales | C17: 15 | E17: Crama Gîrboiu | G17: =SUMIF('Winery Departments'!$A:$A,E17,'Winery Departments'!$C:$C) -> 0 | H17: =IFERROR(G17/F17,"") | I17: No LinkedIn capture available; BestJobs employer profile lists 6 alumni (checked 2026-08-21)
A18: Cramele Cotnari | B18: Marketing | C18: 3 | E18: Domeniile Vânju Mare | G18: =SUMIF('Winery Departments'!$A:$A,E18,'Winery Departments'!$C:$C) -> 0 | H18: =IFERROR(G18/F18,"") | I18: No LinkedIn capture available; BestJobs employer profile exists, alumni count not published (checked 2026-08-21)
A19: Cramele Cotnari | B19: Operations | C19: 1 | E19: Licorna WineHouse | G19: =SUMIF('Winery Departments'!$A:$A,E19,'Winery Departments'!$C:$C) -> 0 | H19: =IFERROR(G19/F19,"") | I19: No LinkedIn capture available; BestJobs employer profile lists 1 alumnus (checked 2026-08-21)
A20: Cramele Cotnari | B20: Program and Project Management | C20: 1 | E20: Gitana Winery | G20: =SUMIF('Winery Departments'!$A:$A,E20,'Winery Departments'!$C:$C) -> 0 | H20: =IFERROR(G20/F20,"") | I20: Moldovan producer — outside the Romanian LinkedIn capture. Four staff are named on the winery's own People page (checked 2026-08-21)
A21: Cramele Cotnari | B21: Research | C21: 1 | E21: Domeniile Sâmburești | G21: =SUMIF('Winery Departments'!$A:$A,E21,'Winery Departments'!$C:$C) -> 0 | H21: =IFERROR(G21/F21,"") | I21: No LinkedIn capture available; BestJobs employer profile lists 2 alumni (checked 2026-08-21)
A22: Beciul Domnesc | B22: Sales | C22: 34 | E22: Crama Rasova | G22: =SUMIF('Winery Departments'!$A:$A,E22,'Winery Departments'!$C:$C) -> 0 | H22: =IFERROR(G22/F22,"") | I22: No LinkedIn capture available; BestJobs employer profile lists 4 alumni (checked 2026-08-21)
A23: Beciul Domnesc | B23: Operations | C23: 14 | E23: Liliac Winery | G23: =SUMIF('Winery Departments'!$A:$A,E23,'Winery Departments'!$C:$C) -> 0 | H23: =IFERROR(G23/F23,"") | I23: No LinkedIn capture available; BestJobs employer profile for amb Wine Company lists 15 alumni (checked 2026-08-21)
A24: Beciul Domnesc | B24: Business Development | C24: 12 | E24: Crama Oprișor | G24: =SUMIF('Winery Departments'!$A:$A,E24,'Winery Departments'!$C:$C) -> 0 | H24: =IFERROR(G24/F24,"") | I24: No LinkedIn capture available; the winery publishes a full team page naming 14 staff, and a BestJobs employer profile exists (checked 2026-08-21)
A25: Beciul Domnesc | B25: Finance | C25: 9 | E25: Domeniile Săhăteni | G25: =SUMIF('Winery Departments'!$A:$A,E25,'Winery Departments'!$C:$C) -> 0 | H25: =IFERROR(G25/F25,"") | I25: No LinkedIn capture available; BestJobs employer profile lists 11 alumni (checked 2026-08-21)
A26: Beciul Domnesc | B26: Engineering | C26: 7 | E26: Crama 1000 de Chipuri | G26: =SUMIF('Winery Departments'!$A:$A,E26,'Winery Departments'!$C:$C) -> 0 | H26: =IFERROR(G26/F26,"") | I26: No LinkedIn capture available; BestJobs employer profile lists 2 alumni (checked 2026-08-21)
A27: Crama Ceptura | B27: Sales | C27: 5 | E27: Casa de Vinuri Negrini | G27: =SUMIF('Winery Departments'!$A:$A,E27,'Winery Departments'!$C:$C) -> 0 | H27: =IFERROR(G27/F27,"") | I27: No LinkedIn capture available; BestJobs employer profile exists, alumni count not published (checked 2026-08-21)
A28: Crama Ceptura | B28: Accounting | C28: 1 | E28: Petro Vaselo | G28: =SUMIF('Winery Departments'!$A:$A,E28,'Winery Departments'!$C:$C) -> 0 | H28: =IFERROR(G28/F28,"") | I28: No LinkedIn capture available; a BestJobs employer profile exists but is empty (checked 2026-08-21)
... A31: Domeniile Averesti | B31: Sales | C31: 7 | E31: SERVE Ceptura | G31: =SUMIF('Winery Departments'!$A:$A,E31,'Winery Departments'!$C:$C) -> 0 | H31: =IFERROR(G31/F31,"") | I31: No LinkedIn capture available; BestJobs employer profile lists 8 alumni (checked 2026-08-21). Part of Purcari Wineries since May 2026
A32: Domeniile Averesti | B32: Marketing | C32: 2
A33: Domeniile Averesti | B33: Business Development | C33: 1
A34: Domeniile Averesti | B34: Engineering | C34: 1
A35: Budureasca | B35: Sales | C35: 14
A36: Budureasca | B36: Operations | C36: 7
A37: Budureasca | B37: Marketing | C37: 5
A38: Budureasca | B38: Accounting | C38: 3
A39: Budureasca | B39: Information Technology | C39: 3
A40: Tohani Romania | B40: Operations | C40: 4
A41: Tohani Romania | B41: Sales | C41: 2
A42: Tohani Romania | B42: Engineering | C42: 2
A43: Tohani Romania | B43: Finance | C43: 1
... A74: Via Viticola | B74: Engineering | C74: 4

Sheet Open Positions
A1: Winery | B1: Role / website finding | C1: Type | D1: Location | E1: Status | F1: Source / timing | G1: Details / application route | H1: Source URL
A2: Purcari Wineries | B2: Manager, Quality Management Systems | C2: Vacancy | D2: Chișinău; production-site travel | E2: Publicly advertised | F2: LinkedIn company post; ~2 weeks before 2026-08-18 | G2: ISO 9001/22000, audits, food safety and continuous improvement. Apply via hr@purcari.wine. | H2: https://www.linkedin.com/company/purcari-wineries-plc
A3: Purcari Wineries | B3: Project Development Manager (Financing & Investments) | C3: Vacancy | D3: Chișinău | E3: Publicly advertised | F3: LinkedIn company post; ~2 weeks before 2026-08-18 | G3: Financing, grants, investments and strategic project development. Apply via hr@purcari.wine. | H3: https://www.linkedin.com/company/purcari-wineries-plc
A4: Purcari Wineries | B4: Office Manager | C4: Vacancy | D4: Chișinău | E4: Recent posting; verify | F4: LinkedIn company post; ~2 months before 2026-08-18 | G4: Management-team support and daily office operations; the post may have closed. | H4: https://www.linkedin.com/company/purcari-wineries-plc
A5: Purcari Wineries | B5: Agronom | C5: Paid internship / early career | D5: Purcari, Moldova | E5: Listed; verify application window | F5: Official internship site checked 2026-08-18 | G5: Vineyard work planning, treatment/fertilization programs and team/resource coordination. | H5: https://internship.purcari.wine/
A6: Purcari Wineries | B6: IT Helpdesk | C6: Paid internship / early career | D6: Chișinău | E6: Listed; verify application window | F6: Official internship site checked 2026-08-18 | G6: Level-1 support, equipment availability, troubleshooting and application setup. | H6: https://internship.purcari.wine/
A7: Purcari Wineries | B7: HR Associate | C7: Paid internship / early career | D7: Chișinău | E7: Listed; verify application window | F7: Official internship site checked 2026-08-18 | G7: HR administration, personnel files, team-building support and HR projects. | H7: https://internship.purcari.wine/
A8: Purcari Wineries | B8: Trade Marketing Specialist | C8: Paid internship / early career | D8: Chișinău | E8: Listed; verify application window | F8: Official internship site checked 2026-08-18 | G8: Trade-marketing plans, promotional calendar, budgets and agency/vendor coordination. | H8: https://internship.purcari.wine/
A9: Purcari Wineries | B9: Guide — Château Purcari Tourist Complex | C9: Paid internship / early career | D9: Purcari, Ștefan Vodă | E9: Listed; verify application window | F9: Official internship site checked 2026-08-18 | G9: Visitor-facing role at the Château Purcari tourism complex. | H9: https://internship.purcari.wine/
A10: Jidvei | B10: Horticultural Engineer (COR 213230) | C10: Vacancy | D10: Jidvei / Cetatea de Baltă, Alba | E10: Recent posting; verify | F10: LinkedIn company post; ~3 months before 2026-08-18 | G10: Horticulture role advertised by the company; verify whether applications remain open. | H10: https://www.linkedin.com/company/jidvei
A11: Jidvei | B11: Brand Manager | C11: Vacancy | D11: Bucharest metropolitan area | E11: Recent posting; verify | F11: LinkedIn company post; ~5–6 months before 2026-08-18 | G11: Brand-management opening promoted twice; current acceptance status was not independently confirmed. | H11: https://www.linkedin.com/company/jidvei
A12: Jidvei | B12: Senior Event Manager | C12: Vacancy | D12: Bucharest metropolitan area | E12: Recent posting; verify | F12: LinkedIn company post; ~6 months before 2026-08-18 | G12: Event role aligned with Jidvei's large cultural and experiential calendar. | H12: https://www.linkedin.com/company/jidvei
... A62: SERVE Ceptura | B62: BestJobs employer profile (8 alumni) | C62: Job-board review | D62: Ceptura, Prahova | E62: Employer profile active; no open role visible at check | F62: BestJobs company profile checked 2026-08-21 | G62: No live listing was visible at check. Recruitment may move to the Purcari group route following the May 2026 acquisition. | H62: https://www.bestjobs.eu/company-profile/serve-ceptura

Sheet Campaign Evidence
A1: Winery | B1: Period | C1: Campaign / initiative | D1: Theme | E1: Channel / mechanic | F1: Pattern interpretation | G1: Source URL
A2: Jidvei | B2: 2026 | C2: Weinland Trails | D2: Experiential / tourism | E2: Running and cycling through vineyards, tastings, food and a charitable component | F2: A repeatable destination property linking wine with nature, community and active lifestyle. | G2: https://www.jidvei.ro/weinland-trails/
A3: Jidvei | B3: 2026 | C3: Spirit collection launch in Paris | D3: Product launch / prestige | E3: International reveal of the Spirit collection around the Paris cultural calendar | F3: Uses high-status international settings to premiumize new products. | G3: https://www.jidvei.ro/francezii-dedica-un-festival-culturii-romane-jidvei-aduce-un-omagiu-spiritului-romanesc-prin-lansarea-colectiei-spirit-in-premiera-la-paris/
A4: Jidvei | B4: 2025–2026 | C4: Strugurele de Aur | D4: Culture / heritage | E4: Recurring Romanian folklore festival supported and amplified by Jidvei | F4: Builds a durable association with Romanian music, dance and cultural heritage. | G4: https://www.jidvei.ro/festivalul-national-de-folclor-strugurele-de-aur-editia-xxi-3-7-septembrie-2025-blaj-si-jidvei/
A5: Jidvei | B5: 2024–2026 | C5: Romanian culture abroad | D5: Cultural diplomacy | E5: Brâncuși at Centre Pompidou, NASTY at Cannes and Paris Book Festival visibility | F5: Makes Romanian cultural prestige a recurring international communications platform. | G5: https://www.jidvei.ro/premiera-jidvei-este-vinul-oficial-al-vernisajului-celei-mai-ample-expozitii-brancusi-din-lume-organizata-la-centrul-pompidou-din-paris/
A6: Jidvei | B6: 2024 | C6: Romanian Olympic Team partnership | D6: Sports / national pride | E6: COSR partnership and Paris Olympics association | F6: Connects the brand to national representation, performance and major moments. | G6: https://www.jidvei.ro/jocurile-olimpice-de-la-paris-ne-au-adus-mai-aproape-de-sportivii-romani-printr-un-parteneriat-devenit-traditie-intre-asociatia-jidvei-viitor-prin-educatie-si-cosr/
A7: Jidvei | B7: Seasonal | C7: Must de la Jidvei | D7: Seasonal product | E7: Harvest-time must launch and availability communications | F7: Uses the harvest calendar to create urgency around a short-lived seasonal product. | G7: https://www.jidvei.ro/jidvei-da-startul-editiei-2024-a-campaniei-must-de-la-jidvei/
A8: Jidvei | B8: 2024 | C8: Eu sunt Jidvei. Născut în inima Transilvaniei | D8: Masterbrand / origin | E8: Corporate brand platform centered on Transylvanian provenance | F8: Provides a unifying identity platform across products, people and place. | G8: https://www.jidvei.ro/eu-sunt-jidvei-nascut-in-inima-transilvaniei-desavarsit-in-tara-vinului/
A9: Jidvei | B9: 2025–2026 | C9: Official-wine and cultural-event partnerships | D9: Events / hospitality | E9: IMPACT Bucharest official wine and RAPSODIILE concert at Castel Bethlen-Haller | F9: Turns hospitality and cultural events into premium brand experiences. | G9: https://www.jidvei.ro/grand-palais-gazduieste-literatura-romana-jidvei-o-insoteste-la-festivalul-de-carte-de-la-paris/
A10: Jidvei | B10: Feb. 2021 | C10: Mysterium extended into super-premium sparkling | D10: Product launch | E10: Traditional-method sparkling added to the existing Mysterium range | F10: Stretches an established premium name into a new category instead of creating one, which is the cheaper way to enter sparkling. | G10: https://www.jidvei.ro/de-azi-mysterium-inseamna-si-vinuri-spumante-super-premium-obtinute-prin-metoda-traditionala/
A11: Jidvei | B11: Mar. 2021 | C11: „Vin și Gust” | D11: Gastronomy partnership | E11: A project pairing the wine range with Romanian gastronomy, launched in the middle of the pandemic restaurant closures | F11: Starts a food-and-wine platform precisely when the on-trade was shut — the audience was at home and cooking. | G11: https://www.jidvei.ro/vin-si-gust-un-nou-proiect-jidvei-in-care-gastronomia-si-arta-vinului-isi-dau-mana/
A12: Jidvei | B12: Aug. 2021 | C12: „Must de la Jidvei”, seventh edition | D12: Seasonal promotion | E12: Annual harvest-season must campaign, run every year since; further editions recorded in 2023 and 2024 | F12: The only fixture in the calendar that repeats identically each autumn — a habit rather than a campaign. | G12: https://www.jidvei.ro/jidvei-da-startul-celei-de-a-saptea-editii-a-campaniei-must-de-la-jidvei/
... A266: SERVE Ceptura | B266: Feb.–Mar. 2026 | C266: Fetească Neagră content and „Making of SERVE wine” | D266: Content marketing | E266: A run of owned content on Fetească Neagră, the estate's story, a viticultural dictionary and a making-of series, published in the weeks before the Purcari deal was announced | F266: The house restates what it stands for immediately before ownership changes — the founding mission put on the record. | G266: https://www.serve.ro/

Sheet Campaign Timeline
A1: Winery | B1: Year | C1: Month | D1: Date | E1: Campaign / item | F1: Type | G1: Where it was found | H1: Source URL | J1: Coverage by winery | K1: Rows
A2: Beciul Domnesc | B2: 2023 | C2: 12 | D2: 2023-12-31 | E2: Comoara Pivniţei | F2: Brand communication | G2: Official winery news/blog | H2: https://www.beciuldomnesc.ro/list/producator/comoara-pivnitei?fc=7 | J2: Beciul Domnesc | K2: =COUNTIF($A$2:$A$511,J2) -> 3
A3: Beciul Domnesc | B3: 2023 | C3: 12 | D3: 2023-12-31 | E3: Povestea noastră | F3: Brand communication | G3: Official winery news/blog | H3: https://www.beciuldomnesc.ro/page/companie | J3: Budureasca | K3: =COUNTIF($A$2:$A$511,J3) -> 2
A4: Beciul Domnesc | B4: 2026 | E4: Beciul Domnesc lansează campania promoţională „Somelier de Grătar” împreună cu agenția Interactions | F4: Product launch | G4: IQads (Romanian marketing press); date estimated from the publisher's article sequence | H4: https://www.iqads.ro/articol/76345/beciul-domnesc-lanseaza-campania-promotionala-somelier-de-gratar-impreuna-cu | J4: Carastelec Winery | K4: =COUNTIF($A$2:$A$511,J4) -> 23
A5: Budureasca | B5: 2021 | C5: 04 | D5: 2021-04-21 | E5: Declaration on the Sustainable Development Strategy | F5: Brand communication | G5: Official winery news/blog | H5: https://budureascawines.com/declaration/ | J5: Casa de Vinuri Cotnari SA | K5: =COUNTIF($A$2:$A$511,J5) -> 0
A6: Budureasca | B6: 2026 | C6: 04 | D6: 2026-04-02 | E6: Prevenirea și reducerea risipei alimentare | F6: Promotion / contest | G6: Official winery news/blog | H6: https://budureascawines.com/ro/program-national-risipa-alimentara/ | J6: Casa de Vinuri Negrini | K6: =COUNTIF($A$2:$A$511,J6) -> 0
A7: Carastelec Winery | B7: 2021 | C7: 10 | D7: 2021-10-28 | E7: Carassia a câștigat la Londra un număr record de medalii! | F7: Awards / reputation | G7: Official winery news/blog | H7: https://www.carastelecwinery.com/ro/tripluaur-la-cswwc2021-2 | J7: Crama 1000 de Chipuri | K7: =COUNTIF($A$2:$A$511,J7) -> 0
A8: Carastelec Winery | B8: 2021 | C8: 10 | D8: 2021-10-28 | E8: Record number of medals for Carassia sparklings in London | F8: Awards / reputation | G8: Official winery news/blog | H8: https://www.carastelecwinery.com/en/triple-gold-cswwc2021-2 | J8: Crama Ceptura | K8: =COUNTIF($A$2:$A$511,J8) -> 1
A9: Carastelec Winery | B9: 2021 | C9: 10 | D9: 2021-10-28 | E9: Rekordszámú érmet szereztek a londoni Pezsgő Világbajnokságon a Carassia pezsgők | F9: Brand communication | G9: Official winery news/blog | H9: https://www.carastelecwinery.com/3arany_cswwc2021-2 | J9: Crama Gîrboiu | K9: =COUNTIF($A$2:$A$511,J9) -> 207
A10: Carastelec Winery | B10: 2021 | C10: 12 | D10: 2021-12-02 | E10: A Carassia Rosé a Pezsgő Világbajnokság egyik legrangosabb trófeáját és a Nemzeti bajnok címet is megszerezte | F10: Brand communication | G10: Official winery news/blog | H10: https://www.carastelecwinery.com/trofeak_cswwc2021 | J10: Crama Oprișor | K10: =COUNTIF($A$2:$A$511,J10) -> 0
A11: Carastelec Winery | B11: 2021 | C11: 12 | D11: 2021-12-02 | E11: Carassia Rosé Brut este anul acesta Campion Național și titular al Chairman`s Trophy. | F11: Awards / reputation | G11: Official winery news/blog | H11: https://www.carastelecwinery.com/ro/national-champion-cswwc2021 | J11: Crama Rasova | K11: =COUNTIF($A$2:$A$511,J11) -> 0
A12: Carastelec Winery | B12: 2021 | C12: 12 | D12: 2021-12-03 | E12: Carassia Rosé Brut won the Chairman’s Trophy and it is also the National Champion of Romania this year. | F12: Awards / reputation | G12: Official winery news/blog | H12: https://www.carastelecwinery.com/en/chairmans-trophy-national-champion-cswwc2021 | J12: Cramele Cotnari | K12: =COUNTIF($A$2:$A$511,J12) -> 0
A13: Carastelec Winery | B13: 2022 | C13: 09 | D13: 2022-09-16 | E13: O medalie de aur și două de argint la ediția din 2022 a Campionatului Mondial de Șampanii și Spumante din Londra | F13: Awards / reputation | G13: Official winery news/blog | H13: https://www.carastelecwinery.com/ro/cswwc2022-ro | J13: Cramele Recas | K13: =COUNTIF($A$2:$A$511,J13) -> 1
A14: Carastelec Winery | B14: 2022 | C14: 09 | D14: 2022-09-16 | E14: One gold and two silver medals at the Champagne and Sparkling Wine World Championship 2022 | F14: Awards / reputation | G14: Official winery news/blog | H14: https://www.carastelecwinery.com/en/cswwc2022-en-2 | J14: Davino Winery | K14: =COUNTIF($A$2:$A$511,J14) -> 0
A15: Carastelec Winery | B15: 2022 | C15: 09 | D15: 2022-09-16 | E15: Töretlenül folytatódik az éremgyűjtés – Egy arany, két ezüst a 2022-es Pezsgővilágbajnokságon. | F15: Brand communication | G15: Official winery news/blog | H15: https://www.carastelecwinery.com/cswwc2022-hu | J15: Domeniile Averesti | K15: =COUNTIF($A$2:$A$511,J15) -> 0
A16: Carastelec Winery | B16: 2022 | C16: 11 | D16: 2022-11-05 | E16: A new National Champion title for Carassia sparkling wines | F16: Brand communication | G16: Official winery news/blog | H16: https://www.carastelecwinery.com/en/cswwc2022-national-champion | J16: Domeniile Davidescu | K16: =COUNTIF($A$2:$A$511,J16) -> 34
... A29: Carastelec Winery | B29: 2025 | C29: 11 | D29: 2025-11-13 | E29: Carassia, medaliată constant la CSWWC | F29: Awards / reputation | G29: Official winery news/blog | H29: https://www.carastelecwinery.com/ro/carassia-medaliata-constant-la-cswwc | J29: Tohani Romania | K29: =COUNTIF($A$2:$A$511,J29) -> 1
A30: Crama Ceptura | B30: 2021 | E30: KUBIS semnează noua campanie TV pentru Crama Ceptura “Împreună, dincolo de granițe.” | F30: Promotion / contest | G30: IQads (Romanian marketing press); date estimated from the publisher's article sequence | H30: https://www.iqads.ro/articol/57608/kubis-semneaza-noua-campanie-tv-pentru-crama-ceptura-impreuna-dincolo-de-granite | J30: Via Viticola | K30: =COUNTIF($A$2:$A$511,J30) -> 0
A31: Crama Gîrboiu | B31: 2021 | C31: 01 | D31: 2021-01-03 | E31: Crama Girboiu – O retrospectivă a anului 2020 | F31: Brand communication | G31: Official winery news/blog | H31: https://cramagirboiu.ro/blog/crama-girboiu-o-retrospectiva-a-anului-2020/ | J31: Zarea | K31: =COUNTIF($A$2:$A$511,J31) -> 8
A32: Crama Gîrboiu | B32: 2021 | C32: 01 | D32: 2021-01-19 | E32: Dry January: Un Ianuarie fără alcool? | F32: Brand communication | G32: Official winery news/blog | H32: https://cramagirboiu.ro/blog/dry-january-un-ianuarie-fara-alcool/ | J32: Total | K32: =SUM(K2:K31) -> 510
A33: Crama Gîrboiu | B33: 2021 | C33: 01 | D33: 2021-01-05 | E33: Rezoluția ta pentru anul 2021 ar putea fi să bei vinuri mai bune | F33: Brand communication | G33: Official winery news/blog | H33: https://cramagirboiu.ro/blog/vinurile-bune-fac-parte-din-rezolutia-ta-pentru-anul-2021/
A34: Crama Gîrboiu | B34: 2021 | C34: 02 | D34: 2021-02-02 | E34: Recomandări de vinuri romantice pentru Ziua Îndrăgostiților | F34: Brand communication | G34: Official winery news/blog | H34: https://cramagirboiu.ro/blog/cele-mai-romantice-vinuri-pentru-ziua-indragostitilor/
A35: Crama Gîrboiu | B35: 2021 | C35: 02 | D35: 2021-02-16 | E35: Specialități Culinare – cu ce vin le asociem anul acesta? | F35: Brand communication | G35: Official winery news/blog | H35: https://cramagirboiu.ro/blog/cu-ce-specialitati-asociem-vinurile-anul-acesta/
A36: Crama Gîrboiu | B36: 2021 | C36: 03 | D36: 2021-03-31 | E36: Care este cea mai buna Feteasca Neagra? | F36: Brand communication | G36: Official winery news/blog | H36: https://cramagirboiu.ro/blog/feteasca-neagra-ambasador/
A37: Crama Gîrboiu | B37: 2021 | C37: 03 | D37: 2021-03-16 | E37: Despre vinuri bune și barrique | F37: Brand communication | G37: Official winery news/blog | H37: https://cramagirboiu.ro/blog/barrique-si-vinurile-bune-de-la-crama-girboiu/
A38: Crama Gîrboiu | B38: 2021 | C38: 03 | D38: 2021-03-01 | E38: Sărbătorește Ziua Femeii cu Vinul LIVIA | F38: Brand communication | G38: Official winery news/blog | H38: https://cramagirboiu.ro/blog/sarbatoreste-ziua-femeii-cu-vinul-livia-in-luna-martie/
A39: Crama Gîrboiu | B39: 2021 | C39: 04 | D39: 2021-04-05 | E39: Ce este metoda traditionala? | F39: Content marketing | G39: Official winery news/blog | H39: https://cramagirboiu.ro/blog/ce-este-metoda-traditionala/
A40: Crama Gîrboiu | B40: 2021 | C40: 04 | D40: 2021-04-06 | E40: Fumé: Tot ce trebuie să știi despre Vinul Fumé | F40: Brand communication | G40: Official winery news/blog | H40: https://cramagirboiu.ro/blog/fume-tot-ce-trebuie-sa-stii-despre-vinul-fume/
A41: Crama Gîrboiu | B41: 2021 | C41: 04 | D41: 2021-04-20 | E41: Masa de Paște și vinurile românești. Află care sunt cele mai recomandate alegeri. | F41: Brand communication | G41: Official winery news/blog | H41: https://cramagirboiu.ro/blog/ce-vinuri-bem-la-masa-de-paste/
A42: Crama Gîrboiu | B42: 2021 | C42: 05 | D42: 2021-05-15 | E42: Cele mai înalte distincții pentru Crama Gîrboiu la Mundus Vini 2021! | F42: Awards / reputation | G42: Official winery news/blog | H42: https://cramagirboiu.ro/blog/cele-mai-bune-vinuri-romanesti-2021/
A43: Crama Gîrboiu | B43: 2021 | C43: 05 | D43: 2021-05-11 | E43: De Constantin și Elena, sărbătorește-i pe cei dragi cu vinurile Constantin și Petite Helena | F43: Brand communication | G43: Official winery news/blog | H43: https://cramagirboiu.ro/blog/de-constantin-si-elena-sarbatoreste-i-pe-cei-dragi-cu-vinurile-constantin-si-petite-helena/
A44: Crama Gîrboiu | B44: 2021 | C44: 05 | D44: 2021-05-04 | E44: Tamaioasa Romaneasca, o editie speciala! | F44: Brand communication | G44: Official winery news/blog | H44: https://cramagirboiu.ro/blog/bacanta-tamaioasa-romaneasca-o-editie-speciala/
... A321: Jidvei | B321: 2022 | C321: 10 | D321: 2022-10-14 | E321: Owner’s Choice – 10 ani, 5 vinuri, peste 150 de medalii. Și nu ne oprim aici… | F321: Awards / reputation | G321: Official winery news/blog | H321: https://www.jidvei.ro/owners-choice-10-ani-5-vinuri-peste-150-de-medalii/
A322: Jidvei | B322: 2023 | E322: Noua gamă de vinuri, Iluziv by Jidvei, o premieră pe piața vinului din România | F322: Awards / reputation | G322: IQads (Romanian marketing press); date estimated from the publisher's article sequence | H322: https://www.iqads.ro/articol/64374/noua-gama-de-vinuri-iluziv-by-jidvei-o-premiera-pe-piata-vinului-din-romania
A323: Jidvei | B323: 2023 | C323: 01 | D323: 2023-01-13 | E323: Platforma Cocktails by Jidvei, o inițiativă unică în România | F323: Brand communication | G323: Official winery news/blog | H323: https://www.jidvei.ro/platforma-cocktails-by-jidvei-o-initiativa-unica-in-romania/
A324: Jidvei | B324: 2023 | C324: 03 | D324: 2023-03-27 | E324: D.O.C. Jidvei este un pas mai departe în arta vinului. Și nu ne oprim aici. | F324: Brand communication | G324: Official winery news/blog | H324: https://www.jidvei.ro/d-o-c-jidvei-este-un-pas-mai-departe-in-arta-vinului-si-nu-ne-oprim-aici/
A325: Jidvei | B325: 2023 | C325: 04 | D325: 2023-04-04 | E325: Traminer Roz CIB 2018, ecoul unui an viticol de excepție | F325: Brand communication | G325: Official winery news/blog | H325: https://www.jidvei.ro/traminer-roz-cib-2018-ecoul-unui-an-viticol-de-exceptie/
A326: Jidvei | B326: 2023 | C326: 04 | D326: 2023-04-25 | E326: Vino în Țara Vinului! | F326: Brand communication | G326: Official winery news/blog | H326: https://www.jidvei.ro/vino-in-tara-vinului/
A327: Jidvei | B327: 2023 | C327: 06 | D327: 2023-06-30 | E327: Noua gamă de vinuri, Iluziv by Jidvei, o premieră pe piața vinului din România | F327: Awards / reputation | G327: Official winery news/blog | H327: https://www.jidvei.ro/noua-gama-de-vinuri-iluziv-by-jidvei-o-premiera-pe-piata-vinului-din-romania/
A328: Jidvei | B328: 2023 | C328: 07 | D328: 2023-07-14 | E328: WeinRun – o provocare lansată de Jidvei iubitorilor de sport și natură | F328: Experiential / events | G328: Official winery news/blog | H328: https://www.jidvei.ro/weinrun-o-provocare-lansata-de-jidvei-iubitorilor-de-sport-si-natura/
A329: Jidvei | B329: 2023 | C329: 08 | D329: 2023-08-04 | E329: Jidvei dă startul unei noi ediții a campaniei „Must de la Jidvei” | F329: Promotion / contest | G329: Official winery news/blog | H329: https://www.jidvei.ro/jidvei-da-startul-unei-noi-editii-a-campaniei-must-de-la-jidvei/
A330: Jidvei | B330: 2023 | C330: 08 | D330: 2023-08-22 | E330: Sărbătoarea cântecului la ediția omagială a Festivalului Național de Folclor „Strugurele de Aur” – 2023 | F330: Awards / reputation | G330: Official winery news/blog | H330: https://www.jidvei.ro/sarbatoarea-cantecului-la-editia-omagiala-a-festivalului-national-de-folclor-strugurele-de-aur-2023/
A331: Jidvei | B331: 2023 | C331: 10 | D331: 2023-10-13 | E331: Noua gamă Pinot Noir marchează o premieră extraordinară între vinurile Jidvei | F331: Awards / reputation | G331: Official winery news/blog | H331: https://www.jidvei.ro/noua-gama-pinot-noir-marcheaza-o-premiera-extraordinara-intre-vinurile-jidvei/
A332: Jidvei | B332: 2024 | E332: Jidvei, singurul brand românesc de vinuri în Top 100 de producători premium din întreaga lume | F332: Awards / reputation | G332: IQads (Romanian marketing press); date estimated from the publisher's article sequence | H332: https://www.iqads.ro/articol/67065/jidvei-singurul-brand-romanesc-de-vinuri-in-top-100-de-producatori-premium-din
A333: Jidvei | B333: 2024 | E333: Vinul Jidvei, de la Centrul Pompidou la Festivalul de Film de la Cannes, susține arta românească la un eveniment cinematografic de pres | F333: Experiential / events | G333: IQads (Romanian marketing press); date estimated from the publisher's article sequence | H333: https://www.iqads.ro/articol/68298/vinul-jidvei-de-la-centrul-pompidou-la-festivalul-de-film-de-la-cannes-sustine
A334: Jidvei | B334: 2024 | C334: 02 | D334: 2024-02-29 | E334: Jidvei, cel mai premiat producător român la Mundus Vini Spring Tasting 2024 | F334: Awards / reputation | G334: Official winery news/blog | H334: https://www.jidvei.ro/jidvei-cel-mai-premiat-producator-roman-la-mundus-vini-spring-tasting-2024/
A335: Jidvei | B335: 2024 | C335: 02 | D335: 2024-02-14 | E335: Jidvei, singurul brand românesc de vinuri în Top 100 de producători premium din întreaga lume | F335: Awards / reputation | G335: Official winery news/blog | H335: https://www.jidvei.ro/jidvei-singurul-brand-romanesc-de-vinuri-in-top-100-de-producatori-premium-din-intreaga-lume/
A336: Jidvei | B336: 2024 | C336: 03 | D336: 2024-03-26 | E336: Jidvei alături de 2800 de vizitatori la vernisajul Brâncuși de la Paris. O premieră absolută | F336: Awards / reputation | G336: IQads (Romanian marketing press) | H336: https://www.iqads.ro/articol/67645/jidvei-alaturi-de-2800-de-vizitatori-la-vernisajul-c-brancusi-de-la-paris-o
A337: Jidvei | B337: 2024 | C337: 03 | D337: 2024-03-22 | E337: Jidvei, vinul oficial al vernisajului celei mai mari expoziții Brâncuși din lume, de la Paris | F337: Sponsorship / partnership | G337: Official winery news/blog | H337: https://www.jidvei.ro/jidvei-vinul-oficial-al-vernisajului-celei-mai-mari-expozitii-brancusi-din-lume-de-la-paris/
A338: Jidvei | B338: 2024 | C338: 04 | D338: 2024-04-08 | E338: Premieră. Jidvei este vinul oficial al vernisajului celei mai ample expoziții Brâncuși din lume, organizată la Centrul Pompidou din Paris | F338: Awards / reputation | G338: Official winery news/blog | H338: https://www.jidvei.ro/premiera-jidvei-este-vinul-oficial-al-vernisajului-celei-mai-ample-expozitii-brancusi-din-lume-organizata-la-centrul-pompidou-din-paris/
A339: Jidvei | B339: 2024 | C339: 05 | D339: 2024-05-17 | E339: Aniversare a Festivalului Național de Folclor „Strugurele de Aur” Ediția XX a Concursului de interpretare vocală și instrumentală | F339: Awards / reputation | G339: Official winery news/blog | H339: https://www.jidvei.ro/aniversare-a-festivalului-national-de-folclor-strugurele-de-aur-editia-xx-a-concursului-de-interpretare-vocala-si-instrumentala/
A340: Jidvei | B340: 2024 | C340: 05 | D340: 2024-05-31 | E340: Castelul Bethlen-Haller, desemnat de Top Hotel Awards „Cea mai bună destinație de turism viticol din România” | F340: Brand communication | G340: Official winery news/blog | H340: https://www.jidvei.ro/castelul-bethlen-haller-desemnat-de-top-hotel-awards-cea-mai-buna-destinatie-de-turism-viticol-din-romania/
A341: Jidvei | B341: 2024 | C341: 05 | D341: 2024-05-15 | E341: Descoperă Țara Vinului în alergare! Jidvei Weinland Trails 2024, un concurs caritabil cu rute inedit gândite printre vii | F341: Experiential / events | G341: Official winery news/blog | H341: https://www.jidvei.ro/descopera-tara-vinului-in-alergare-jidvei-weinland-trails-2024-un-concurs-caritabil-cu-rute-inedit-gandite-printre-vii/
A342: Jidvei | B342: 2024 | C342: 06 | D342: 2024-06-08 | E342: De la Centrul Pompidou la Festivalul de Film de la Cannes Jidvei susține arta românească la un eveniment cinematografic de prestigiu | F342: Experiential / events | G342: Official winery news/blog | H342: https://www.jidvei.ro/de-la-centrul-pompidou-la-festivalul-de-film-de-la-cannes-jidvei-sustine-arta-romaneasca-la-un-eveniment-cinematografic-de-prestigiu/
A343: Jidvei | B343: 2024 | C343: 06 | D343: 2024-06-10 | E343: Festivalul Național de Folclor „Strugurele de Aur” a desemnat tinerii interpreți admiși la cea de-a XX-a ediție a concursului | F343: Awards / reputation | G343: Official winery news/blog | H343: https://www.jidvei.ro/festivalul-national-de-folclor-strugurele-de-aur-a-desemnat-tinerii-interpreti-admisi-la-cea-de-a-xx-a-editie-a-concursului/
A344: Jidvei | B344: 2024 | C344: 07 | D344: 2024-07-26 | E344: Asociația „Jidvei – Viitor prin Educație” este, de 5 ani, sponsor COSR, iar Jidvei, vinul oficial al evenimentelor organizate la Casa României pe perioada Jocurilor Olimpice de la Paris | F344: Experiential / events | G344: Official winery news/blog | H344: https://www.jidvei.ro/asociatia-jidvei-viitor-prin-educatie-este-de-5-ani-sponsor-cosr-iar-jidvei-vinul-oficial-al-evenimentelor-organizate-la-casa-romaniei-pe-perioada-jocurilor-olimpice-de-la-pari/
A345: Jidvei | B345: 2024 | C345: 07 | D345: 2024-07-01 | E345: Premieră. Jidvei este vinul official al cele mai ample expoziții Brâncuși din lume, organizată la Centrul Pompidou din Paris | F345: Awards / reputation | G345: IQads (Romanian marketing press) | H345: https://www.iqads.ro/articol/67503/premiera-jidvei-este-vinul-official-al-cele-mai-ample-expozitii-brancusi-din
... A353: Jidvei | B353: 2024 | C353: 12 | D353: 2024-12-11 | E353: Lansăm Verjus Jidvei – primul produs românesc de acest tip, dedicat celor pasionați de gastronomie și de un stil de viață sănătos | F353: Product launch | G353: Official winery news/blog | H353: https://www.jidvei.ro/lansam-verjus-jidvei-primul-produs-romanesc-de-acest-tip-dedicat-celor-pasionati-de-gastronomie-si-de-un-stil-de-viata-sanatos/
A354: Jidvei | B354: 2025 | E354: Alexandra Tînjală: Cultura este modul prin care o comunitate alege să spună cine este. Noi alegem să spunem povestea Jidvei prin proiec | F354: CSR / sustainability | G354: IQads (Romanian marketing press); date estimated from the publisher's article sequence | H354: https://www.iqads.ro/articol/72413/alexandra-tinjala-cultura-este-modul-prin-care-o-comunitate-alege-sa-spuna-cine
A355: Jidvei | B355: 2025 | E355: Jidvei duce vinul românesc la Teatrul La Fenice din Veneția | F355: Brand communication | G355: IQads (Romanian marketing press); date estimated from the publisher's article sequence | H355: https://www.iqads.ro/articol/70531/jidvei-duce-vinul-romanesc-la-teatrul-la-fenice-din-venetia
A356: Jidvei | B356: 2025 | E356: Jidvei lansează Vinars XO, în premieră internațională, la Paris | F356: Awards / reputation | G356: IQads (Romanian marketing press); date estimated from the publisher's article sequence | H356: https://www.iqads.ro/articol/73291/jidvei-lanseaza-vinars-xo-in-premiera-internationala-la-paris
A357: Jidvei | B357: 2025 | E357: Michelle Obama la IMPACT București. JIDVEI, vinul oficial al celui mai important eveniment de business & tech din Europa de Sud-Est | F357: Experiential / events | G357: IQads (Romanian marketing press); date estimated from the publisher's article sequence | H357: https://www.iqads.ro/articol/73099/michelle-obama-la-impact-bucuresti-jidvei-vinul-oficial-al-celui-mai-important
A358: Jidvei | B358: 2025 | C358: 01 | D358: 2025-01-28 | E358: Jidvei obține statutul de DOP (Denumire de Origine Protejată), o recunoaștere a excelenței vinurilor sale | F358: Corporate / financial | G358: Official winery news/blog | H358: https://www.jidvei.ro/jidvei-obtine-statutul-de-dop-denumire-de-origine-protejata-o-recunoastere-a-excelentei-vinurilor-sale/
A359: Jidvei | B359: 2025 | C359: 03 | D359: 2025-03-07 | E359: Start înscrieri pentru cea mai frumoasă competiție de alergare din inima Transilvaniei, Jidvei Weinland Trails – Spring Running Edition | F359: Experiential / events | G359: Official winery news/blog | H359: https://www.jidvei.ro/start-inscrieri-pentru-cea-mai-frumoasa-competitie-de-alergare-din-inima-transilvaniei-jidvei-weinland-trails-spring-running-edition/
A360: Jidvei | B360: 2025 | C360: 05 | D360: 2025-05-15 | E360: Castelul Bethlen-Haller distins la TopHotel Awards 2025 | F360: Awards / reputation | G360: Official winery news/blog | H360: https://www.jidvei.ro/castelul-bethlen-haller-distins-la-tophotel-awards-2025/
A361: Jidvei | B361: 2025 | C361: 06 | D361: 2025-06-19 | E361: Concert extraordinar la Castelul Bethlen-Haller: Alexandru Tomescu și vioara Stradivarius în închiderea Turneului RAPSODIILE | F361: Experiential / events | G361: Official winery news/blog | H361: https://www.jidvei.ro/concert-extraordinar-la-castelul-bethlen-haller-alexandru-tomescu-si-vioara-stradivarius-in-inchiderea-turneului-rapsodiile/
A362: Jidvei | B362: 2025 | C362: 07 | D362: 2025-07-29 | E362: S-au deschis înscrierile pentru preselecția Festivalului Național de Folclor Strugurele de Aur 2025 | F362: Awards / reputation | G362: Official winery news/blog | H362: https://www.jidvei.ro/s-au-deschis-inscrierile-pentru-preselectia-festivalului-national-de-folclor-strugurele-de-aur-2025/
A363: Jidvei | B363: 2025 | C363: 08 | D363: 2025-08-18 | E363: Festivalul Național de Folclor „Strugurele de Aur”, ediția XXI 3 – 7 septembrie 2025 | Blaj și Jidvei | F363: Awards / reputation | G363: Official winery news/blog | H363: https://www.jidvei.ro/festivalul-national-de-folclor-strugurele-de-aur-editia-xxi-3-7-septembrie-2025-blaj-si-jidvei/
A364: Jidvei | B364: 2025 | C364: 09 | D364: 2025-09-25 | E364: Jidvei a lansat Vinars XO, în premieră internațională, la Paris | F364: Awards / reputation | G364: Official winery news/blog | H364: https://www.jidvei.ro/jidvei-a-lansat-vinars-xo-in-premiera-internationala-la-paris/
A365: Jidvei | B365: 2025 | C365: 09 | D365: 2025-09-23 | E365: Michelle Obama la IMPACT București. JIDVEI, vinul oficial al celui mai important eveniment de business & tech din Europa de Sud-Est. | F365: Experiential / events | G365: Official winery news/blog | H365: https://www.jidvei.ro/michelle-obama-la-impact-bucuresti-jidvei-vinul-oficial-al-celui-mai-important-eveniment-de-business-tech-din-europa-de-sud-est/
A366: Jidvei | B366: 2025 | C366: 10 | D366: 2025-10-30 | E366: Owner’s Choice Ana Fetească Regală, moștenirea generațiilor din inima Transilvaniei | F366: Experiential / events | G366: Official winery news/blog | H366: https://www.jidvei.ro/owners-choice-ana-feteasca-regala-mostenirea-generatiilor-din-inima-transilvaniei/
A367: Jidvei | B367: 2025 | C367: 12 | D367: 2025-12-01 | E367: Francezii dedică un festival culturii române. Jidvei aduce un omagiu spiritului românesc prin lansarea colecției “Spirit”, în premieră | F367: Awards / reputation | G367: IQads (Romanian marketing press) | H367: https://www.iqads.ro/articol/73953/francezii-dedica-un-festival-culturii-romane-jidvei-aduce-un-omagiu-spiritului
A368: Jidvei | B368: 2026 | E368: Jidvei revine la Festivalul de Film de la Cannes în calitate de vin oficial al României | F368: Experiential / events | G368: IQads (Romanian marketing press); date estimated from the publisher's article sequence | H368: https://www.iqads.ro/articol/75627/jidvei-revine-la-festivalul-de-film-de-la-cannes-in-calitate-de-vin-oficial-al
A369: Jidvei | B369: 2026 | C369: 01 | D369: 2026-01-25 | E369: Francezii dedică un festival culturii române. Jidvei aduce un omagiu spiritului românesc prin lansarea colecției „Spirit”, în premieră la Paris. | F369: Awards / reputation | G369: Official winery news/blog | H369: https://www.jidvei.ro/francezii-dedica-un-festival-culturii-romane-jidvei-aduce-un-omagiu-spiritului-romanesc-prin-lansarea-colectiei-spirit-in-premiera-la-paris/
A370: Jidvei | B370: 2026 | C370: 03 | D370: 2026-03-18 | E370: Am deschis înscrierile pentru Jidvei Weinland Trails 2026. Singurul maraton printre vii din România | F370: Experiential / events | G370: Official winery news/blog | H370: https://www.jidvei.ro/am-deschis-inscrierile-pentru-jidvei-weinland-trails-2026-singurul-maraton-printre-vii-din-romania/
A371: Jidvei | B371: 2026 | C371: 03 | D371: 2026-03-23 | E371: Festivalul Național de Folclor Strugurele de Aur, o nouă întâlnire cu tinerii care duc tradiția mai departe | F371: Awards / reputation | G371: Official winery news/blog | H371: https://www.jidvei.ro/festivalul-national-de-folclor-strugurele-de-aur-o-noua-intalnire-cu-tinerii-care-duc-traditia-mai-departe/
A372: Jidvei | B372: 2026 | C372: 04 | D372: 2026-04-19 | E372: Grand Palais a găzduit România. Jidvei a adus Transilvania la Festivalul de Carte de la Paris | F372: Experiential / events | G372: IQads (Romanian marketing press) | H372: https://www.iqads.ro/articol/75328/grand-palais-a-gazduit-romania-jidvei-a-adus-transilvania-la-festivalul-de-carte
A373: Jidvei | B373: 2026 | C373: 04 | D373: 2026-04-24 | E373: Grand Palais găzduiește literatura română. Jidvei o însoțește la Festivalul de Carte de la Paris. | F373: Experiential / events | G373: Official winery news/blog | H373: https://www.jidvei.ro/grand-palais-gazduieste-literatura-romana-jidvei-o-insoteste-la-festivalul-de-carte-de-la-paris/
A374: Jidvei | B374: 2026 | C374: 07 | D374: 2026-07-03 | E374: Sebastian Stan, într-un interviu rar în limba română la Cannes, pentru seria JIDVEI „Vin la povești” | F374: Brand communication | G374: IQads (Romanian marketing press) | H374: https://www.iqads.ro/articol/75910/sebastian-stan-intr-un-interviu-rar-in-limba-romana-la-cannes-pentru-seria
A375: Liliac Winery | B375: 2021 | E375: young.LILIAC, singurul vin care se transformă în fiecare an sub inspirația artiștilor contemporani din România | F375: Brand communication | G375: IQads (Romanian marketing press); date estimated from the publisher's article sequence | H375: https://www.iqads.ro/articol/57287/young-liliac-singurul-vin-care-se-transforma-in-fiecare-an-sub-inspiratia
A376: Murfatlar | B376: 2023 | C376: 08 | D376: 2023-08-29 | E376: Lacrima lui Ovidiu | F376: Brand communication | G376: Official winery news/blog | H376: https://murfatlar-vinul.ro/index.php/lacrima-lui-ovidiu/
A377: Murfatlar | B377: 2023 | C377: 11 | D377: 2023-11-17 | E377: Jumătate vin, jumătate viață | F377: Brand communication | G377: Official winery news/blog | H377: https://murfatlar-vinul.ro/jumatate-vin-jumatate-viata/
A378: Murfatlar | B378: 2024 | C378: 09 | D378: 2024-09-26 | E378: Lacrima lui Ovidiu 12 | F378: Brand communication | G378: Official winery news/blog | H378: https://murfatlar-vinul.ro/lacrima-lui-ovidiu-12/
A379: Murfatlar | B379: 2024 | C379: 12 | D379: 2024-12-03 | E379: Moștenire pentru viitor | F379: Brand communication | G379: Official winery news/blog | H379: https://murfatlar-vinul.ro/mostenire-pentru-viitor/
A380: Murfatlar | B380: 2025 | C380: 02 | D380: 2025-02-09 | E380: Aperitiv Mamaia | F380: Brand communication | G380: Official winery news/blog | H380: https://murfatlar-vinul.ro/aperitiv-mamaia/
A381: Murfatlar | B381: 2025 | C381: 02 | D381: 2025-02-09 | E381: Vermut Mamaia | F381: Brand communication | G381: Official winery news/blog | H381: https://murfatlar-vinul.ro/vermut-mamaia/
A382: Murfatlar | B382: 2026 | C382: 07 | D382: 2026-07-20 | E382: Aerosoli Prosecco | F382: Brand communication | G382: Official winery news/blog | H382: https://murfatlar-vinul.ro/aerosoli-prosecco/
A383: Purcari Wineries | B383: 2022 | E383: "Noi, nu! Niciodată", o campanie manifest semnată Purcari pentru încurajarea românilor de pretutindeni în perioada dificilă pe care o t | F383: Promotion / contest | G383: IQads (Romanian marketing press); date estimated from the publisher's article sequence | H383: https://www.iqads.ro/articol/62189/noi-nu-niciodata-o-campanie-manifest-semnata-purcari-pentru-incurajarea
A384: Purcari Wineries | B384: 2023 | C384: 03 | D384: 2023-03-07 | E384: Château Purcari își menține titlul de cel mai bun producător din Moldova la Mundus Vini Spring Tasting 2023 | F384: Awards / reputation | G384: Official winery news/blog | H384: https://purcariwineries.com/chateau-purcari-isi-mentine-titlul-de-cel-mai-bun-producator-din-moldova-la-mundus-vini-spring-tasting-2023/
A385: Purcari Wineries | B385: 2023 | C385: 06 | D385: 2023-06-29 | E385: Nocturne Night Run 2023 | F385: Experiential / events | G385: Official winery news/blog | H385: https://purcariwineries.com/nocturne-run-night-2023/
A386: Purcari Wineries | B386: 2023 | C386: 06 | D386: 2023-06-14 | E386: Rezultate de Aur pentru Château Purcari la Decanter World Wine Awards | F386: Awards / reputation | G386: Official winery news/blog | H386: https://purcariwineries.com/rezultate-de-aur-pentru-chateau-purcari-la-decanter-world-wine-awards/
A387: Purcari Wineries | B387: 2023 | C387: 07 | D387: 2023-07-20 | E387: Diez.md: Cum se creează un vin bun? Am fost în laboratoarele Purcari să aflăm cum e să faci o carieră în industria vinului în Moldova | F387: Content marketing | G387: Official winery news/blog | H387: https://purcariwineries.com/diez-md-cum-se-creeaza-un-vin-bun-am-fost-in-laboratoarele-purcari-sa-aflam-cum-e-sa-faci-o-cariera-in-industria-vinului-in-moldova/
A388: Purcari Wineries | B388: 2023 | C388: 08 | D388: 2023-08-24 | E388: Publicarea Rezultatelor Financiare pentru Semestru I, 2023 | F388: Brand communication | G388: Official winery news/blog | H388: https://purcariwineries.com/publicarea-rezultatelor-financiare-pentru-semestru-i-2023/
A389: Purcari Wineries | B389: 2023 | C389: 09 | D389: 2023-09-21 | E389: Château Purcari la Balul Generozității (ediția a 10-a) | F389: Brand communication | G389: Official winery news/blog | H389: https://purcariwineries.com/chateau-purcari-la-balul-generozitatii-editia-a-10-a/
A390: Purcari Wineries | B390: 2023 | C390: 09 | D390: 2023-09-22 | E390: Festivalul Vinului Moldovei din București | F390: Experiential / events | G390: Official winery news/blog | H390: https://purcariwineries.com/festivalul-vinului-moldovei-din-bucuresti/
A391: Purcari Wineries | B391: 2023 | C391: 09 | D391: 2023-09-15 | E391: Informare referitoare la comentarii media | F391: Brand communication | G391: Official winery news/blog | H391: https://purcariwineries.com/informare-referitoare-la-comentarii-media/
A392: Purcari Wineries | B392: 2023 | C392: 09 | D392: 2023-09-29 | E392: Teambuilding în Podgoria Onești | F392: Brand communication | G392: Official winery news/blog | H392: https://purcariwineries.com/teambuilding-in-podgoria-onesti/
A393: Purcari Wineries | B393: 2023 | C393: 09 | D393: 2023-09-29 | E393: Vizita Înaltului Reprezentant al Uniunii Europene pentru Afaceri Externe și Politica de Securitate, Josep Borrell, la Château Purcari | F393: Brand communication | G393: Official winery news/blog | H393: https://purcariwineries.com/vizita-inaltului-reprezentant-al-uniunii-europene-pentru-afaceri-externe-si-politica-de-securitate-josep-borrell-la-chateau-purcari/
A394: Purcari Wineries | B394: 2023 | C394: 09 | D394: 2023-09-15 | E394: Ziarul Financiar: Deschiderea de astăzi la Bursă. Eugeniu Baltag, Purcari: Am avut o primă jumătate de an foarte puternică. Creşterea din S1 vine în proporţie de două treimi din volume, iar restul din majorările de preţ | F394: CSR / sustainability | G394: Official winery news/blog | H394: https://purcariwineries.com/ziarul-financiar-deschiderea-de-astazi-la-bursa-eugeniu-baltag-purcari-am-avut-o-prima-jumatate-de-an-foarte-puternica-cresterea-din-s1-vine-in-proportie-de-doua-treimi-din-volume-iar-restul-din/
A395: Purcari Wineries | B395: 2023 | C395: 10 | D395: 2023-10-04 | E395: Alexandru Filip devine Director General adjunct al Grupului de Vinării Purcari | F395: Corporate / financial | G395: Official winery news/blog | H395: https://purcariwineries.com/purcari-il-numeste-pe-alexandru-filip-in-functie-de-director-general-adjunct/
...

Sheet CEO Research
A1: Winery | B1: CEO / senior leader | C1: Public title | D1: Background | E1: Education — Bachelor / Master / PhD | F1: Career domains | G1: Core discipline | H1: CEO source | I1: Confidence / notes
A2: Jidvei | B2: Claudiu Necșulescu | C2: President / owner; CEO title not confirmed | D2: Engineer who moved from state machinery into trading, agriculture and the post-privatization rebuilding of Jidvei. | E2: Bachelor/equivalent: Road Vehicles / Automotive Engineering, Transilvania University of Brașov (1987). Master: not found. PhD: not found. | F2: Mechanical and automotive engineering; machinery; trade/export; agriculture; viticulture; ownership and strategy. | G2: Engineering | H2: https://www.zf.ro/who-s-who/claudiu-necsulescu-10387336 | I2: High confidence on the leader; CEO title is not publicly confirmed.
A3: Beciul Domnesc | B3: Gianina-Virginia Rusu | C3: CEO since Nov. 2023 | D3: Joined as an economist, progressed through controlling and about 18 years as CFO, then became CEO; also holds accounting, audit and tax credentials. | E3: Bachelor: Accounting and Computer Science, George Bacovia University (1998–2002). Master: not found. PhD: not found. Professional: CECCAR, CAFR, CCF. | F3: Accounting; controlling; finance/CFO; audit; tax; corporate leadership. | G3: Finance / Economics | H3: https://ro.linkedin.com/in/gianina-virginia-rusu-70736640 | I3: High confidence on CEO and career progression.
A4: Purcari Wineries | B4: Victor Bostan | C4: Founder and CEO (returned 16 Dec. 2025) | D4: Founder of the modern group with more than 35 years in wine; returned as CEO after the 2025 ownership and governance transition. | E4: Bachelor/equivalent: Wine Technology, Technical University of Moldova. Master: not found. PhD: not found. | F4: Winemaking; viticulture; wine technology; entrepreneurship; corporate strategy and governance. | G4: Wine Engineer | H4: https://purcariwineries.com/en/investors/ | I4: High confidence; current leadership confirmed by public-company sources.
A5: Cramele Recas | B5: Gheorghe Iova | C5: Co-founder / director; senior operating leader | D5: Started as a farm head at IAS Recaș, became director, helped lead privatization and growth, and also taught at the Banat agricultural university. | E5: Bachelor/equivalent: Horticulture, University of Agricultural Sciences, Cluj-Napoca; top of class (1983). Master: not found. PhD: not found. | F5: Horticulture; vineyard/farm operations; winemaking; teaching/academia; management; privatization; export. | G5: Agronomy / Horticulture | H5: https://ghidulbanatului.ro/povestea-cramelor-recas-unul-dintre-cei-mai-mari-producatori-de-vinuri-din-romania_9065.html | I5: Medium confidence on the CEO-style title; leadership is shared among founding families.
A6: Via Viticola | B6: Marius Iliev | C6: General Manager / founder-level leader | D6: Former University of Illinois Chicago academic who taught differential equations; returned to Romania and became an entrepreneur, investor and winery turnaround leader. | E6: Exact bachelor/master/PhD degrees not publicly stated in reviewed sources. Advanced mathematics training is implied by his former university teaching, but not labeled as a degree. | F6: Mathematics and academia; entrepreneurship; investment/turnaround; wine; viticulture; portfolio strategy. | G6: Academia | H6: https://www.desprevin.ro/interviu-marius-iliev-ceo-via-viticola-sarica-niculitel | I6: Medium-high confidence; the exact education level is intentionally not inferred.
A7: Budureasca | B7: Olga Miloiu | C7: CEO / General Manager since 2012 | D7: Career spans European funds, import/distribution, beverage management, sales, marketing, hospitality and general management. | E7: Bachelor/licence: International Economic Relations, ASE Bucharest (1999–2003), valedictorian. Bachelor/licence: Engineering & Management in Agricultural Tourism, Bioterra University (1996–2000). Master: not found. PhD: not found. | F7: European funds; import/distribution; beverages; sales; marketing; finance/control; hospitality; general management. | G7: Finance / Economics | H7: https://ro.linkedin.com/in/olga-miloiu-ba75537b | I7: High confidence on CEO and education.
A8: Zarea | B8: Emil Popescu | C8: President / owner | D8: Long-standing owner and president; detailed earlier career history is not publicly disclosed in reviewed sources. | E8: University POLITEHNICA of Bucharest attended/listed. Degree level and field not specified. Master: not found. PhD: not found. | F8: Ownership; beverage/FMCG; corporate strategy; acquisitions; portfolio and brand management. Engineering is possible from the university context but not asserted. | G8: Engineering | H8: https://ro.linkedin.com/in/emil-popescu-758a086 | I8: High confidence on leadership; public biographical detail is limited.
A9: Cramele Cotnari | B9: Răzvan Serghiuță | C9: Director General since Dec. 2018 | D9: Advanced from Commercial Director to Director General after a long career in the wine industry. | E9: Doctoral studies: Economics, Alexandru Ioan Cuza University of Iași. Bachelor: not publicly specified. Master: not publicly specified. | F9: Sales/commercial; general management; economics; wine/FMCG. | G9: Marketing / Sales | H9: https://ro.linkedin.com/in/razvan-serghiuta-aa985710b | I9: High confidence on the current Director General.
A10: Casa de Vinuri Cotnari SA | B10: Victor Deleanu | C10: President / Director General | D10: Second-generation leader; worked in vineyard operations and winemaking before leading the premium, dry-wine and HoReCa-focused company. | E10: Bachelor: Law, Alexandru Ioan Cuza University of Iași. Additional study: Horticulture (reported as year 2 in 2015; completion not confirmed). Master: not found. PhD: not found. | F10: Law; vineyard operations; winemaking; ownership; general management; premium wine; HoReCa strategy; family business. | G10: Law | H10: https://www.crameromania.ro/oameni/interviu-victor-deleanu-cel-mai-tanar-director-general-al-unei-crame-din-romania-crame-288.html | I10: High confidence on leadership and education; horticulture completion is not claimed.
A11: Murfatlar | B11: Cosmin Popescu | C11: Managing Partner | D11: Joined Murfatlar around 2000 and progressed through wine-sector operational and executive management into the managing-partner role. | E11: Bachelor/equivalent: Finance, Banking and Stock Exchanges. Master: not found. PhD: not found. | F11: Finance; wine production and operations; executive management; brand/export strategy; oenology judging. | G11: Finance / Economics | H11: https://www.iwcb.ro/speakers/cosmin-popescu/ | I11: Medium-high confidence on the managing-partner role and education.
A12: Domeniile Averesti | B12: Rareș Florea | C12: Country Manager; previously publicly titled CEO | D12: Commercial leader with about 18 years across financial services, production, retail and e-commerce; responsible for Romanian commercial strategy and international expansion. | E12: Bachelor/equivalent: Public Administration, University of Bucharest. Master: not found. PhD: not found. | F12: Banking and financial services; production; retail; e-commerce; commercial strategy; export; general management. | G12: Finance / Economics | H12: https://www.businessmagazin.ro/analize/agricultura/rares-florea-country-manager-domeniile-averesti-domeniul-vinului-22459506 | I12: High confidence on current operating leadership and background.
... A70: Vintruvian | B70: Marius Iliev | C70: General Manager / founder-level leader | D70: Vintruvian Estates is the group behind Via Viticola, already researched in this workbook, and the buyer of Villa Zorilor and the Prince Matei brand from Vinarte in 2019; leadership and background are recorded on the Via Viticola row. | E70: See the Via Viticola row. | F70: See the Via Viticola row. | G70: Academia | H70: https://www.vintruvianestates.com/ | I70: Cross-reference, not a separate company: listed name is the group behind Via Viticola. Its four commercial staff are filed under Via Viticola and are not double-counted here.
A72: Core discipline — one standardized value per leader: the profession they trained in or built their career on before wine, so the column can be filtered and counted. Where someone holds more than one, the documented education decides; where the education is not documented, the dominant career domain does. Permitted values: Wine Engineer · Agronomy / Horticulture · Engineering · Finance / Economics · Marketing / Sales · Law · Medicine · Academia · Entrepreneur / Owner · General Management · Not established. "Entrepreneur / Owner" means a self-made proprietor with no single prior profession on the record — it is a finding, not a gap. "Not established" means no leader was identified, or none of their background is public — that is a gap. "Wine Engineer" is reserved for documented oenology or wine-technology training; running a winery is not by itself enough. The unstandardized detail stays in the Background, Education and Career domains columns; this column never replaces them.

Sheet Commercial People
A1: Winery | B1: Person | C1: Function | D1: Current role | E1: Type | F1: Seniority | G1: Source URL | I1: Roster KPI | J1: People
A2: Purcari Wineries / Crama Ceptura | B2: Oana Patricia Drăgușin | C2: Marketing | D2: Country Marketing Manager | E2: Marketing Leadership | F2: Leadership | G2: https://ro.linkedin.com/in/oana-patricia-dr%C4%83gu%C8%99in | I2: Marketing | J2: =COUNTIF($C$2:$C$101,"Marketing") -> 34
A3: Purcari Wineries / Crama Ceptura | B3: Diana Urecheanu | C3: Marketing | D3: Trade Marketing Manager | E3: Trade Marketing | F3: Manager | G3: https://ro.linkedin.com/in/dianaurecheanu | I3: Sales | J3: =COUNTIF($C$2:$C$101,"Sales") -> 66
A4: Crama Ceptura | B4: Cătălin Velicu | C4: Sales | D4: Regional Sales Manager | E4: Regional / Area Sales | F4: Manager | G4: https://ro.linkedin.com/in/catalin-velicu-051259b9 | I4: Total | J4: =SUM(J2:J3) -> 100
A5: Purcari Wineries | B5: Veronica Moșneag | C5: Marketing | D5: Senior Marketing Manager | E5: Marketing Leadership | F5: Leadership | G5: https://vioser.md/functia-director-marketing/
A6: Purcari Wineries | B6: Adelina Palancica | C6: Marketing | D6: Brand Development Manager | E6: Brand / Product | F6: Manager | G6: https://theorg.com/org/purcari-wineries-group/teams/marketing-management | I6: Marketing type | J6: People | L6: Sales type | M6: People
A7: Purcari Wineries | B7: Anton Tofan | C7: Marketing | D7: International Brand Manager | E7: International Marketing | F7: Manager | G7: https://theorg.com/org/purcari-wineries-group/teams/marketing-management | I7: Marketing Leadership | J7: =COUNTIFS($C$2:$C$101,"Marketing",$E$2:$E$101,I7) -> 12 | L7: Commercial Leadership | M7: =COUNTIFS($C$2:$C$101,"Sales",$E$2:$E$101,L7) -> 10
A8: Purcari Wineries | B8: Maria Bezede | C8: Marketing | D8: International Marketing Manager | E8: International Marketing | F8: Manager | G8: https://md.linkedin.com/in/maria-bezede-962241215 | I8: Brand / Product | J8: =COUNTIFS($C$2:$C$101,"Marketing",$E$2:$E$101,I8) -> 9 | L8: National Sales | M8: =COUNTIFS($C$2:$C$101,"Sales",$E$2:$E$101,L8) -> 6
A9: Purcari Wineries | B9: Anton Pavlovskiy | C9: Marketing | D9: Trade Marketing Manager | E9: Trade Marketing | F9: Manager | G9: https://theorg.com/org/purcari-wineries-group/teams/marketing-operations | I9: Trade Marketing | J9: =COUNTIFS($C$2:$C$101,"Marketing",$E$2:$E$101,I9) -> 5 | L9: Regional / Area Sales | M9: =COUNTIFS($C$2:$C$101,"Sales",$E$2:$E$101,L9) -> 25
A10: Purcari Wineries | B10: Bradu Valeria | C10: Marketing | D10: Assistant Trade Marketing Manager | E10: Trade Marketing | F10: Manager | G10: https://theorg.com/org/purcari-wineries-group/teams/marketing-operations | I10: Digital / Social | J10: =COUNTIFS($C$2:$C$101,"Marketing",$E$2:$E$101,I10) -> 2 | L10: Key Accounts / Modern Trade | M10: =COUNTIFS($C$2:$C$101,"Sales",$E$2:$E$101,L10) -> 7
A11: Purcari Wineries | B11: Victoria Costovici | C11: Marketing | D11: Digital Marketing Manager | E11: Digital / Social | F11: Manager | G11: https://md.linkedin.com/in/victoria-costovici-274744213 | I11: PR / Communications | J11: =COUNTIFS($C$2:$C$101,"Marketing",$E$2:$E$101,I11) -> 2 | L11: HoReCa / On-Trade | M11: =COUNTIFS($C$2:$C$101,"Sales",$E$2:$E$101,L11) -> 4
A12: Purcari Wineries | B12: Julia Eyrich | C12: Marketing | D12: Digital Marketing Manager | E12: Digital / Social | F12: Manager | G12: https://theorg.com/org/purcari-wineries-group/teams/marketing-operations | I12: Content / Creative | J12: =COUNTIFS($C$2:$C$101,"Marketing",$E$2:$E$101,I12) -> 2 | L12: Export / International | M12: =COUNTIFS($C$2:$C$101,"Sales",$E$2:$E$101,L12) -> 5
A13: Purcari Wineries | B13: Alexandra Patrut | C13: Marketing | D13: Brand Manager | E13: Brand / Product | F13: Manager | G13: https://ro.linkedin.com/pub/dir/%2B/Patrut/ro-0-Rom%C3%A2nia | I13: International Marketing | J13: =COUNTIFS($C$2:$C$101,"Marketing",$E$2:$E$101,I13) -> 2 | L13: Distribution / Traditional Trade | M13: =COUNTIFS($C$2:$C$101,"Sales",$E$2:$E$101,L13) -> 1
A14: Purcari Wineries | C14: Sales | D14: Regional Manager - MEA & Turkey | E14: Export / International | F14: Leadership | L14: E-commerce / DTC | M14: =COUNTIFS($C$2:$C$101,"Sales",$E$2:$E$101,L14) -> 2
A15: Purcari Wineries | B15: Burcu Ateşer | C15: Sales | D15: Regional Manager - Turkey & North Cyprus | E15: Export / International | F15: Manager | G15: https://theorg.com/org/purcari-wineries-group/teams/international-operations | L15: Business Development | M15: =COUNTIFS($C$2:$C$101,"Sales",$E$2:$E$101,L15) -> 1
A16: Purcari Wineries | B16: Horodinca Vlad Dumitru | C16: Sales | D16: Area Sales Manager | E16: Regional / Area Sales | F16: Manager | G16: https://theorg.com/org/purcari-wineries-group/teams/sales-department | L16: Sales Management | M16: =COUNTIFS($C$2:$C$101,"Sales",$E$2:$E$101,L16) -> 1
A17: Purcari Wineries | B17: Dumitru Cioban | C17: Sales | D17: Sales Specialist | E17: Sales Operations | F17: Specialist | G17: https://theorg.com/org/purcari-wineries-group/teams/sales-department | L17: Sales Operations | M17: =COUNTIFS($C$2:$C$101,"Sales",$E$2:$E$101,L17) -> 4
A18: Cramele Recaș | B18: Radu Dumitrescu | C18: Marketing | D18: Marketing Director | E18: Marketing Leadership | F18: Leadership | G18: https://ro.linkedin.com/in/radu-dumitrescu-110077b
A19: Cramele Recaș | B19: Ligia-Elena Stroe | C19: Marketing | D19: Brand Manager | E19: Brand / Product | F19: Manager | G19: https://ro.linkedin.com/in/ligia-stroe
A20: Cramele Recaș | B20: Ciprian Roșca | C20: Sales | D20: Commercial Director Romania | E20: Commercial Leadership | F20: Leadership | G20: https://ro.linkedin.com/in/ciprian-rosca-94483b1a
A21: Cramele Recaș | B21: Miltiade Pietroiu | C21: Sales | D21: National Sales Director | E21: National Sales | F21: Leadership | G21: https://ro.linkedin.com/in/miltiade-pietroiu-54438717
A22: Cramele Recaș | B22: Mihai-Traian Bodoc | C22: Sales | D22: National Key Account Manager | E22: Key Accounts / Modern Trade | F22: Manager | G22: https://ro.linkedin.com/in/mihai-traian-bodoc-9b79b478
A23: Cramele Recaș | B23: Octavian Macavei | C23: Sales | D23: Sales Manager | E23: Sales Management | F23: Manager | G23: https://ro.linkedin.com/in/octavian-macavei-3049a41a0
A24: Cramele Recaș | B24: Viorica Anghel | C24: Sales | D24: Sales Business Analyst | E24: Sales Operations | F24: Specialist | G24: https://ro.linkedin.com/company/cramele-recas
A25: Cramele Recaș | B25: Eduard Raznic | C25: Sales | D25: Regional Manager | E25: Regional / Area Sales | F25: Manager | G25: https://ro.linkedin.com/in/eduard-raznic-940b3232
A26: Jidvei | B26: Cristian Fuga | C26: Marketing | D26: Marketing Director | E26: Marketing Leadership | F26: Leadership | G26: https://ro.linkedin.com/in/cristian-fuga-53773948
A27: Jidvei | B27: Ana Necșulescu | C27: Marketing | D27: Communications Director | E27: PR / Communications | F27: Leadership | G27: https://ro.linkedin.com/in/ananecsulescu
A28: Jidvei | B28: Mihai Bălănescu | C28: Sales | D28: Sales Director | E28: Commercial Leadership | F28: Leadership | G28: https://ro.linkedin.com/in/mihai-balanescu-88044724
A29: Jidvei | B29: Marius Stancu | C29: Sales | D29: Export Director | E29: Export / International | F29: Leadership | G29: https://ro.linkedin.com/in/marius-stancu-72184650
... A101: Fautor | B101: Ruxanda Lipcan | C101: Sales | D101: Sales & Marketing Director | E101: Commercial Leadership | F101: Leadership | G101: https://wineofmoldova.com/en/fautor-winery/

Sheet Commercial Type Split
A1: Winery | B1: Marketing | J1: Sales | V1: Total People
B2: Marketing Leadership | C2: Brand / Product | D2: Trade Marketing | E2: Digital / Social | F2: PR / Communications | G2: Content / Creative | H2: International Marketing | I2: Total Marketing | J2: Commercial Leadership | K2: National Sales | L2: Regional / Area Sales | M2: Key Accounts / Modern Trade | N2: HoReCa / On-Trade | O2: Export / International | P2: Distribution / Traditional Trade | Q2: E-commerce / DTC | R2: Business Development | S2: Sales Management | T2: Sales Operations | U2: Total Sales
A3: Purcari Wineries | B3: =COUNTIFS('Commercial People'!$A$2:$A$101,"Purcari Wineries",'Commercial People'!$C$2:$C$101,"Marketing",'Commercial People'!$E$2:$E$101,B$2)+COUNTIFS('Commercial People'!$A$2:$A$101,"Purcari Wineries / Crama Ceptura",'Commercial People'!$C$2:$C$101,"Marketing",'Commercial People'!$E$2:$E$101,B$2) -> 2 | C3: =COUNTIFS('Commercial People'!$A$2:$A$101,"Purcari Wineries",'Commercial People'!$C$2:$C$101,"Marketing",'Commercial People'!$E$2:$E$101,C$2)+COUNTIFS('Commercial People'!$A$2:$A$101,"Purcari Wineries / Crama Ceptura",'Commercial People'!$C$2:$C$101,"Marketing",'Commercial People'!$E$2:$E$101,C$2) -> 2 | D3: =COUNTIFS('Commercial People'!$A$2:$A$101,"Purcari Wineries",'Commercial People'!$C$2:$C$101,"Marketing",'Commercial People'!$E$2:$E$101,D$2)+COUNTIFS('Commercial People'!$A$2:$A$101,"Purcari Wineries / Crama Ceptura",'Commercial People'!$C$2:$C$101,"Marketing",'Commercial People'!$E$2:$E$101,D$2) -> 3 | E3: =COUNTIFS('Commercial People'!$A$2:$A$101,"Purcari Wineries",'Commercial People'!$C$2:$C$101,"Marketing",'Commercial People'!$E$2:$E$101,E$2)+COUNTIFS('Commercial People'!$A$2:$A$101,"Purcari Wineries / Crama Ceptura",'Commercial People'!$C$2:$C$101,"Marketing",'Commercial People'!$E$2:$E$101,E$2) -> 2 | F3: =COUNTIFS('Commercial People'!$A$2:$A$101,"Purcari Wineries",'Commercial People'!$C$2:$C$101,"Marketing",'Commercial People'!$E$2:$E$101,F$2)+COUNTIFS('Commercial People'!$A$2:$A$101,"Purcari Wineries / Crama Ceptura",'Commercial People'!$C$2:$C$101,"Marketing",'Commercial People'!$E$2:$E$101,F$2) -> 0 | G3: =COUNTIFS('Commercial People'!$A$2:$A$101,"Purcari Wineries",'Commercial People'!$C$2:$C$101,"Marketing",'Commercial People'!$E$2:$E$101,G$2)+COUNTIFS('Commercial People'!$A$2:$A$101,"Purcari Wineries / Crama Ceptura",'Commercial People'!$C$2:$C$101,"Marketing",'Commercial People'!$E$2:$E$101,G$2) -> 0 | H3: =COUNTIFS('Commercial People'!$A$2:$A$101,"Purcari Wineries",'Commercial People'!$C$2:$C$101,"Marketing",'Commercial People'!$E$2:$E$101,H$2)+COUNTIFS('Commercial People'!$A$2:$A$101,"Purcari Wineries / Crama Ceptura",'Commercial People'!$C$2:$C$101,"Marketing",'Commercial People'!$E$2:$E$101,H$2) -> 2 | I3: =SUM(B3:H3) -> 11 | J3: =COUNTIFS('Commercial People'!$A$2:$A$101,"Purcari Wineries",'Commercial People'!$C$2:$C$101,"Sales",'Commercial People'!$E$2:$E$101,J$2)+COUNTIFS('Commercial People'!$A$2:$A$101,"Purcari Wineries / Crama Ceptura",'Commercial People'!$C$2:$C$101,"Sales",'Commercial People'!$E$2:$E$101,J$2) -> 0 | K3: =COUNTIFS('Commercial People'!$A$2:$A$101,"Purcari Wineries",'Commercial People'!$C$2:$C$101,"Sales",'Commercial People'!$E$2:$E$101,K$2)+COUNTIFS('Commercial People'!$A$2:$A$101,"Purcari Wineries / Crama Ceptura",'Commercial People'!$C$2:$C$101,"Sales",'Commercial People'!$E$2:$E$101,K$2) -> 0 | L3: =COUNTIFS('Commercial People'!$A$2:$A$101,"Purcari Wineries",'Commercial People'!$C$2:$C$101,"Sales",'Commercial People'!$E$2:$E$101,L$2)+COUNTIFS('Commercial People'!$A$2:$A$101,"Purcari Wineries / Crama Ceptura",'Commercial People'!$C$2:$C$101,"Sales",'Commercial People'!$E$2:$E$101,L$2) -> 1 | M3: =COUNTIFS('Commercial People'!$A$2:$A$101,"Purcari Wineries",'Commercial People'!$C$2:$C$101,"Sales",'Commercial People'!$E$2:$E$101,M$2)+COUNTIFS('Commercial People'!$A$2:$A$101,"Purcari Wineries / Crama Ceptura",'Commercial People'!$C$2:$C$101,"Sales",'Commercial People'!$E$2:$E$101,M$2) -> 0 | N3: =COUNTIFS('Commercial People'!$A$2:$A$101,"Purcari Wineries",'Commercial People'!$C$2:$C$101,"Sales",'Commercial People'!$E$2:$E$101,N$2)+COUNTIFS('Commercial People'!$A$2:$A$101,"Purcari Wineries / Crama Ceptura",'Commercial People'!$C$2:$C$101,"Sales",'Commercial People'!$E$2:$E$101,N$2) -> 0 | O3: =COUNTIFS('Commercial People'!$A$2:$A$101,"Purcari Wineries",'Commercial People'!$C$2:$C$101,"Sales",'Commercial People'!$E$2:$E$101,O$2)+COUNTIFS('Commercial People'!$A$2:$A$101,"Purcari Wineries / Crama Ceptura",'Commercial People'!$C$2:$C$101,"Sales",'Commercial People'!$E$2:$E$101,O$2) -> 2 | P3: =COUNTIFS('Commercial People'!$A$2:$A$101,"Purcari Wineries",'Commercial People'!$C$2:$C$101,"Sales",'Commercial People'!$E$2:$E$101,P$2)+COUNTIFS('Commercial People'!$A$2:$A$101,"Purcari Wineries / Crama Ceptura",'Commercial People'!$C$2:$C$101,"Sales",'Commercial People'!$E$2:$E$101,P$2) -> 0 | Q3: =COUNTIFS('Commercial People'!$A$2:$A$101,"Purcari Wineries",'Commercial People'!$C$2:$C$101,"Sales",'Commercial People'!$E$2:$E$101,Q$2)+COUNTIFS('Commercial People'!$A$2:$A$101,"Purcari Wineries / Crama Ceptura",'Commercial People'!$C$2:$C$101,"Sales",'Commercial People'!$E$2:$E$101,Q$2) -> 0 | ... T3: =COUNTIFS('Commercial People'!$A$2:$A$101,"Purcari Wineries",'Commercial People'!$C$2:$C$101,"Sales",'Commercial People'!$E$2:$E$101,T$2)+COUNTIFS('Commercial People'!$A$2:$A$101,"Purcari Wineries / Crama Ceptura",'Commercial People'!$C$2:$C$101,"Sales",'Commercial People'!$E$2:$E$101,T$2) -> 1 | U3: =SUM(J3:T3) -> 4 | V3: =I3+U3 -> 15
A4: Cramele Recaș | B4: =COUNTIFS('Commercial People'!$A$2:$A$101,"Cramele Recaș",'Commercial People'!$C$2:$C$101,"Marketing",'Commercial People'!$E$2:$E$101,B$2)+COUNTIFS('Commercial People'!$A$2:$A$101,"Cramele Recaș / Murfatlar",'Commercial People'!$C$2:$C$101,"Marketing",'Commercial People'!$E$2:$E$101,B$2) -> 1 | C4: =COUNTIFS('Commercial People'!$A$2:$A$101,"Cramele Recaș",'Commercial People'!$C$2:$C$101,"Marketing",'Commercial People'!$E$2:$E$101,C$2)+COUNTIFS('Commercial People'!$A$2:$A$101,"Cramele Recaș / Murfatlar",'Commercial People'!$C$2:$C$101,"Marketing",'Commercial People'!$E$2:$E$101,C$2) -> 1 | D4: =COUNTIFS('Commercial People'!$A$2:$A$101,"Cramele Recaș",'Commercial People'!$C$2:$C$101,"Marketing",'Commercial People'!$E$2:$E$101,D$2)+COUNTIFS('Commercial People'!$A$2:$A$101,"Cramele Recaș / Murfatlar",'Commercial People'!$C$2:$C$101,"Marketing",'Commercial People'!$E$2:$E$101,D$2) -> 0 | E4: =COUNTIFS('Commercial People'!$A$2:$A$101,"Cramele Recaș",'Commercial People'!$C$2:$C$101,"Marketing",'Commercial People'!$E$2:$E$101,E$2)+COUNTIFS('Commercial People'!$A$2:$A$101,"Cramele Recaș / Murfatlar",'Commercial People'!$C$2:$C$101,"Marketing",'Commercial People'!$E$2:$E$101,E$2) -> 0 | F4: =COUNTIFS('Commercial People'!$A$2:$A$101,"Cramele Recaș",'Commercial People'!$C$2:$C$101,"Marketing",'Commercial People'!$E$2:$E$101,F$2)+COUNTIFS('Commercial People'!$A$2:$A$101,"Cramele Recaș / Murfatlar",'Commercial People'!$C$2:$C$101,"Marketing",'Commercial People'!$E$2:$E$101,F$2) -> 0 | G4: =COUNTIFS('Commercial People'!$A$2:$A$101,"Cramele Recaș",'Commercial People'!$C$2:$C$101,"Marketing",'Commercial People'!$E$2:$E$101,G$2)+COUNTIFS('Commercial People'!$A$2:$A$101,"Cramele Recaș / Murfatlar",'Commercial People'!$C$2:$C$101,"Marketing",'Commercial People'!$E$2:$E$101,G$2) -> 0 | H4: =COUNTIFS('Commercial People'!$A$2:$A$101,"Cramele Recaș",'Commercial People'!$C$2:$C$101,"Marketing",'Commercial People'!$E$2:$E$101,H$2)+COUNTIFS('Commercial People'!$A$2:$A$101,"Cramele Recaș / Murfatlar",'Commercial People'!$C$2:$C$101,"Marketing",'Commercial People'!$E$2:$E$101,H$2) -> 0 | I4: =SUM(B4:H4) -> 2 | J4: =COUNTIFS('Commercial People'!$A$2:$A$101,"Cramele Recaș",'Commercial People'!$C$2:$C$101,"Sales",'Commercial People'!$E$2:$E$101,J$2)+COUNTIFS('Commercial People'!$A$2:$A$101,"Cramele Recaș / Murfatlar",'Commercial People'!$C$2:$C$101,"Sales",'Commercial People'!$E$2:$E$101,J$2) -> 1 | K4: =COUNTIFS('Commercial People'!$A$2:$A$101,"Cramele Recaș",'Commercial People'!$C$2:$C$101,"Sales",'Commercial People'!$E$2:$E$101,K$2)+COUNTIFS('Commercial People'!$A$2:$A$101,"Cramele Recaș / Murfatlar",'Commercial People'!$C$2:$C$101,"Sales",'Commercial People'!$E$2:$E$101,K$2) -> 2 | L4: =COUNTIFS('Commercial People'!$A$2:$A$101,"Cramele Recaș",'Commercial People'!$C$2:$C$101,"Sales",'Commercial People'!$E$2:$E$101,L$2)+COUNTIFS('Commercial People'!$A$2:$A$101,"Cramele Recaș / Murfatlar",'Commercial People'!$C$2:$C$101,"Sales",'Commercial People'!$E$2:$E$101,L$2) -> 1 | M4: =COUNTIFS('Commercial People'!$A$2:$A$101,"Cramele Recaș",'Commercial People'!$C$2:$C$101,"Sales",'Commercial People'!$E$2:$E$101,M$2)+COUNTIFS('Commercial People'!$A$2:$A$101,"Cramele Recaș / Murfatlar",'Commercial People'!$C$2:$C$101,"Sales",'Commercial People'!$E$2:$E$101,M$2) -> 1 | N4: =COUNTIFS('Commercial People'!$A$2:$A$101,"Cramele Recaș",'Commercial People'!$C$2:$C$101,"Sales",'Commercial People'!$E$2:$E$101,N$2)+COUNTIFS('Commercial People'!$A$2:$A$101,"Cramele Recaș / Murfatlar",'Commercial People'!$C$2:$C$101,"Sales",'Commercial People'!$E$2:$E$101,N$2) -> 0 | O4: =COUNTIFS('Commercial People'!$A$2:$A$101,"Cramele Recaș",'Commercial People'!$C$2:$C$101,"Sales",'Commercial People'!$E$2:$E$101,O$2)+COUNTIFS('Commercial People'!$A$2:$A$101,"Cramele Recaș / Murfatlar",'Commercial People'!$C$2:$C$101,"Sales",'Commercial People'!$E$2:$E$101,O$2) -> 0 | P4: =COUNTIFS('Commercial People'!$A$2:$A$101,"Cramele Recaș",'Commercial People'!$C$2:$C$101,"Sales",'Commercial People'!$E$2:$E$101,P$2)+COUNTIFS('Commercial People'!$A$2:$A$101,"Cramele Recaș / Murfatlar",'Commercial People'!$C$2:$C$101,"Sales",'Commercial People'!$E$2:$E$101,P$2) -> 0 | Q4: =COUNTIFS('Commercial People'!$A$2:$A$101,"Cramele Recaș",'Commercial People'!$C$2:$C$101,"Sales",'Commercial People'!$E$2:$E$101,Q$2)+COUNTIFS('Commercial People'!$A$2:$A$101,"Cramele Recaș / Murfatlar",'Commercial People'!$C$2:$C$101,"Sales",'Commercial People'!$E$2:$E$101,Q$2) -> 0 | ... T4: =COUNTIFS('Commercial People'!$A$2:$A$101,"Cramele Recaș",'Commercial People'!$C$2:$C$101,"Sales",'Commercial People'!$E$2:$E$101,T$2)+COUNTIFS('Commercial People'!$A$2:$A$101,"Cramele Recaș / Murfatlar",'Commercial People'!$C$2:$C$101,"Sales",'Commercial People'!$E$2:$E$101,T$2) -> 1 | U4: =SUM(J4:T4) -> 7 | V4: =I4+U4 -> 9
A5: Jidvei | B5: =COUNTIFS('Commercial People'!$A$2:$A$101,"Jidvei",'Commercial People'!$C$2:$C$101,"Marketing",'Commercial People'!$E$2:$E$101,B$2) -> 1 | C5: =COUNTIFS('Commercial People'!$A$2:$A$101,"Jidvei",'Commercial People'!$C$2:$C$101,"Marketing",'Commercial People'!$E$2:$E$101,C$2) -> 0 | D5: =COUNTIFS('Commercial People'!$A$2:$A$101,"Jidvei",'Commercial People'!$C$2:$C$101,"Marketing",'Commercial People'!$E$2:$E$101,D$2) -> 0 | E5: =COUNTIFS('Commercial People'!$A$2:$A$101,"Jidvei",'Commercial People'!$C$2:$C$101,"Marketing",'Commercial People'!$E$2:$E$101,E$2) -> 0 | F5: =COUNTIFS('Commercial People'!$A$2:$A$101,"Jidvei",'Commercial People'!$C$2:$C$101,"Marketing",'Commercial People'!$E$2:$E$101,F$2) -> 1 | G5: =COUNTIFS('Commercial People'!$A$2:$A$101,"Jidvei",'Commercial People'!$C$2:$C$101,"Marketing",'Commercial People'!$E$2:$E$101,G$2) -> 0 | H5: =COUNTIFS('Commercial People'!$A$2:$A$101,"Jidvei",'Commercial People'!$C$2:$C$101,"Marketing",'Commercial People'!$E$2:$E$101,H$2) -> 0 | I5: =SUM(B5:H5) -> 2 | J5: =COUNTIFS('Commercial People'!$A$2:$A$101,"Jidvei",'Commercial People'!$C$2:$C$101,"Sales",'Commercial People'!$E$2:$E$101,J$2) -> 1 | K5: =COUNTIFS('Commercial People'!$A$2:$A$101,"Jidvei",'Commercial People'!$C$2:$C$101,"Sales",'Commercial People'!$E$2:$E$101,K$2) -> 0 | L5: =COUNTIFS('Commercial People'!$A$2:$A$101,"Jidvei",'Commercial People'!$C$2:$C$101,"Sales",'Commercial People'!$E$2:$E$101,L$2) -> 2 | M5: =COUNTIFS('Commercial People'!$A$2:$A$101,"Jidvei",'Commercial People'!$C$2:$C$101,"Sales",'Commercial People'!$E$2:$E$101,M$2) -> 0 | N5: =COUNTIFS('Commercial People'!$A$2:$A$101,"Jidvei",'Commercial People'!$C$2:$C$101,"Sales",'Commercial People'!$E$2:$E$101,N$2) -> 0 | O5: =COUNTIFS('Commercial People'!$A$2:$A$101,"Jidvei",'Commercial People'!$C$2:$C$101,"Sales",'Commercial People'!$E$2:$E$101,O$2) -> 1 | P5: =COUNTIFS('Commercial People'!$A$2:$A$101,"Jidvei",'Commercial People'!$C$2:$C$101,"Sales",'Commercial People'!$E$2:$E$101,P$2) -> 0 | Q5: =COUNTIFS('Commercial People'!$A$2:$A$101,"Jidvei",'Commercial People'!$C$2:$C$101,"Sales",'Commercial People'!$E$2:$E$101,Q$2) -> 0 | ... T5: =COUNTIFS('Commercial People'!$A$2:$A$101,"Jidvei",'Commercial People'!$C$2:$C$101,"Sales",'Commercial People'!$E$2:$E$101,T$2) -> 1 | U5: =SUM(J5:T5) -> 5 | V5: =I5+U5 -> 7
A6: Cramele Cotnari | B6: =COUNTIFS('Commercial People'!$A$2:$A$101,"Cramele Cotnari",'Commercial People'!$C$2:$C$101,"Marketing",'Commercial People'!$E$2:$E$101,B$2) -> 1 | C6: =COUNTIFS('Commercial People'!$A$2:$A$101,"Cramele Cotnari",'Commercial People'!$C$2:$C$101,"Marketing",'Commercial People'!$E$2:$E$101,C$2) -> 0 | D6: =COUNTIFS('Commercial People'!$A$2:$A$101,"Cramele Cotnari",'Commercial People'!$C$2:$C$101,"Marketing",'Commercial People'!$E$2:$E$101,D$2) -> 0 | E6: =COUNTIFS('Commercial People'!$A$2:$A$101,"Cramele Cotnari",'Commercial People'!$C$2:$C$101,"Marketing",'Commercial People'!$E$2:$E$101,E$2) -> 0 | F6: =COUNTIFS('Commercial People'!$A$2:$A$101,"Cramele Cotnari",'Commercial People'!$C$2:$C$101,"Marketing",'Commercial People'!$E$2:$E$101,F$2) -> 0 | G6: =COUNTIFS('Commercial People'!$A$2:$A$101,"Cramele Cotnari",'Commercial People'!$C$2:$C$101,"Marketing",'Commercial People'!$E$2:$E$101,G$2) -> 1 | H6: =COUNTIFS('Commercial People'!$A$2:$A$101,"Cramele Cotnari",'Commercial People'!$C$2:$C$101,"Marketing",'Commercial People'!$E$2:$E$101,H$2) -> 0 | I6: =SUM(B6:H6) -> 2 | J6: =COUNTIFS('Commercial People'!$A$2:$A$101,"Cramele Cotnari",'Commercial People'!$C$2:$C$101,"Sales",'Commercial People'!$E$2:$E$101,J$2) -> 1 | K6: =COUNTIFS('Commercial People'!$A$2:$A$101,"Cramele Cotnari",'Commercial People'!$C$2:$C$101,"Sales",'Commercial People'!$E$2:$E$101,K$2) -> 0 | L6: =COUNTIFS('Commercial People'!$A$2:$A$101,"Cramele Cotnari",'Commercial People'!$C$2:$C$101,"Sales",'Commercial People'!$E$2:$E$101,L$2) -> 1 | M6: =COUNTIFS('Commercial People'!$A$2:$A$101,"Cramele Cotnari",'Commercial People'!$C$2:$C$101,"Sales",'Commercial People'!$E$2:$E$101,M$2) -> 2 | N6: =COUNTIFS('Commercial People'!$A$2:$A$101,"Cramele Cotnari",'Commercial People'!$C$2:$C$101,"Sales",'Commercial People'!$E$2:$E$101,N$2) -> 0 | O6: =COUNTIFS('Commercial People'!$A$2:$A$101,"Cramele Cotnari",'Commercial People'!$C$2:$C$101,"Sales",'Commercial People'!$E$2:$E$101,O$2) -> 1 | P6: =COUNTIFS('Commercial People'!$A$2:$A$101,"Cramele Cotnari",'Commercial People'!$C$2:$C$101,"Sales",'Commercial People'!$E$2:$E$101,P$2) -> 0 | Q6: =COUNTIFS('Commercial People'!$A$2:$A$101,"Cramele Cotnari",'Commercial People'!$C$2:$C$101,"Sales",'Commercial People'!$E$2:$E$101,Q$2) -> 0 | ... T6: =COUNTIFS('Commercial People'!$A$2:$A$101,"Cramele Cotnari",'Commercial People'!$C$2:$C$101,"Sales",'Commercial People'!$E$2:$E$101,T$2) -> 0 | U6: =SUM(J6:T6) -> 5 | V6: =I6+U6 -> 7
A7: Beciul Domnesc | B7: =COUNTIFS('Commercial People'!$A$2:$A$101,"Beciul Domnesc",'Commercial People'!$C$2:$C$101,"Marketing",'Commercial People'!$E$2:$E$101,B$2) -> 0 | C7: =COUNTIFS('Commercial People'!$A$2:$A$101,"Beciul Domnesc",'Commercial People'!$C$2:$C$101,"Marketing",'Commercial People'!$E$2:$E$101,C$2) -> 2 | D7: =COUNTIFS('Commercial People'!$A$2:$A$101,"Beciul Domnesc",'Commercial People'!$C$2:$C$101,"Marketing",'Commercial People'!$E$2:$E$101,D$2) -> 1 | E7: =COUNTIFS('Commercial People'!$A$2:$A$101,"Beciul Domnesc",'Commercial People'!$C$2:$C$101,"Marketing",'Commercial People'!$E$2:$E$101,E$2) -> 0 | F7: =COUNTIFS('Commercial People'!$A$2:$A$101,"Beciul Domnesc",'Commercial People'!$C$2:$C$101,"Marketing",'Commercial People'!$E$2:$E$101,F$2) -> 0 | G7: =COUNTIFS('Commercial People'!$A$2:$A$101,"Beciul Domnesc",'Commercial People'!$C$2:$C$101,"Marketing",'Commercial People'!$E$2:$E$101,G$2) -> 0 | H7: =COUNTIFS('Commercial People'!$A$2:$A$101,"Beciul Domnesc",'Commercial People'!$C$2:$C$101,"Marketing",'Commercial People'!$E$2:$E$101,H$2) -> 0 | I7: =SUM(B7:H7) -> 3 | J7: =COUNTIFS('Commercial People'!$A$2:$A$101,"Beciul Domnesc",'Commercial People'!$C$2:$C$101,"Sales",'Commercial People'!$E$2:$E$101,J$2) -> 1 | K7: =COUNTIFS('Commercial People'!$A$2:$A$101,"Beciul Domnesc",'Commercial People'!$C$2:$C$101,"Sales",'Commercial People'!$E$2:$E$101,K$2) -> 1 | L7: =COUNTIFS('Commercial People'!$A$2:$A$101,"Beciul Domnesc",'Commercial People'!$C$2:$C$101,"Sales",'Commercial People'!$E$2:$E$101,L$2) -> 1 | M7: =COUNTIFS('Commercial People'!$A$2:$A$101,"Beciul Domnesc",'Commercial People'!$C$2:$C$101,"Sales",'Commercial People'!$E$2:$E$101,M$2) -> 1 | N7: =COUNTIFS('Commercial People'!$A$2:$A$101,"Beciul Domnesc",'Commercial People'!$C$2:$C$101,"Sales",'Commercial People'!$E$2:$E$101,N$2) -> 0 | O7: =COUNTIFS('Commercial People'!$A$2:$A$101,"Beciul Domnesc",'Commercial People'!$C$2:$C$101,"Sales",'Commercial People'!$E$2:$E$101,O$2) -> 0 | P7: =COUNTIFS('Commercial People'!$A$2:$A$101,"Beciul Domnesc",'Commercial People'!$C$2:$C$101,"Sales",'Commercial People'!$E$2:$E$101,P$2) -> 0 | Q7: =COUNTIFS('Commercial People'!$A$2:$A$101,"Beciul Domnesc",'Commercial People'!$C$2:$C$101,"Sales",'Commercial People'!$E$2:$E$101,Q$2) -> 0 | ... T7: =COUNTIFS('Commercial People'!$A$2:$A$101,"Beciul Domnesc",'Commercial People'!$C$2:$C$101,"Sales",'Commercial People'!$E$2:$E$101,T$2) -> 1 | U7: =SUM(J7:T7) -> 5 | V7: =I7+U7 -> 8
A8: Crama Ceptura | B8: =COUNTIFS('Commercial People'!$A$2:$A$101,"Purcari Wineries / Crama Ceptura",'Commercial People'!$C$2:$C$101,"Marketing",'Commercial People'!$E$2:$E$101,B$2)+COUNTIFS('Commercial People'!$A$2:$A$101,"Crama Ceptura",'Commercial People'!$C$2:$C$101,"Marketing",'Commercial People'!$E$2:$E$101,B$2) -> 1 | C8: =COUNTIFS('Commercial People'!$A$2:$A$101,"Purcari Wineries / Crama Ceptura",'Commercial People'!$C$2:$C$101,"Marketing",'Commercial People'!$E$2:$E$101,C$2)+COUNTIFS('Commercial People'!$A$2:$A$101,"Crama Ceptura",'Commercial People'!$C$2:$C$101,"Marketing",'Commercial People'!$E$2:$E$101,C$2) -> 0 | D8: =COUNTIFS('Commercial People'!$A$2:$A$101,"Purcari Wineries / Crama Ceptura",'Commercial People'!$C$2:$C$101,"Marketing",'Commercial People'!$E$2:$E$101,D$2)+COUNTIFS('Commercial People'!$A$2:$A$101,"Crama Ceptura",'Commercial People'!$C$2:$C$101,"Marketing",'Commercial People'!$E$2:$E$101,D$2) -> 1 | E8: =COUNTIFS('Commercial People'!$A$2:$A$101,"Purcari Wineries / Crama Ceptura",'Commercial People'!$C$2:$C$101,"Marketing",'Commercial People'!$E$2:$E$101,E$2)+COUNTIFS('Commercial People'!$A$2:$A$101,"Crama Ceptura",'Commercial People'!$C$2:$C$101,"Marketing",'Commercial People'!$E$2:$E$101,E$2) -> 0 | F8: =COUNTIFS('Commercial People'!$A$2:$A$101,"Purcari Wineries / Crama Ceptura",'Commercial People'!$C$2:$C$101,"Marketing",'Commercial People'!$E$2:$E$101,F$2)+COUNTIFS('Commercial People'!$A$2:$A$101,"Crama Ceptura",'Commercial People'!$C$2:$C$101,"Marketing",'Commercial People'!$E$2:$E$101,F$2) -> 0 | G8: =COUNTIFS('Commercial People'!$A$2:$A$101,"Purcari Wineries / Crama Ceptura",'Commercial People'!$C$2:$C$101,"Marketing",'Commercial People'!$E$2:$E$101,G$2)+COUNTIFS('Commercial People'!$A$2:$A$101,"Crama Ceptura",'Commercial People'!$C$2:$C$101,"Marketing",'Commercial People'!$E$2:$E$101,G$2) -> 0 | H8: =COUNTIFS('Commercial People'!$A$2:$A$101,"Purcari Wineries / Crama Ceptura",'Commercial People'!$C$2:$C$101,"Marketing",'Commercial People'!$E$2:$E$101,H$2)+COUNTIFS('Commercial People'!$A$2:$A$101,"Crama Ceptura",'Commercial People'!$C$2:$C$101,"Marketing",'Commercial People'!$E$2:$E$101,H$2) -> 0 | I8: =SUM(B8:H8) -> 2 | J8: =COUNTIFS('Commercial People'!$A$2:$A$101,"Purcari Wineries / Crama Ceptura",'Commercial People'!$C$2:$C$101,"Sales",'Commercial People'!$E$2:$E$101,J$2)+COUNTIFS('Commercial People'!$A$2:$A$101,"Crama Ceptura",'Commercial People'!$C$2:$C$101,"Sales",'Commercial People'!$E$2:$E$101,J$2) -> 0 | K8: =COUNTIFS('Commercial People'!$A$2:$A$101,"Purcari Wineries / Crama Ceptura",'Commercial People'!$C$2:$C$101,"Sales",'Commercial People'!$E$2:$E$101,K$2)+COUNTIFS('Commercial People'!$A$2:$A$101,"Crama Ceptura",'Commercial People'!$C$2:$C$101,"Sales",'Commercial People'!$E$2:$E$101,K$2) -> 0 | L8: =COUNTIFS('Commercial People'!$A$2:$A$101,"Purcari Wineries / Crama Ceptura",'Commercial People'!$C$2:$C$101,"Sales",'Commercial People'!$E$2:$E$101,L$2)+COUNTIFS('Commercial People'!$A$2:$A$101,"Crama Ceptura",'Commercial People'!$C$2:$C$101,"Sales",'Commercial People'!$E$2:$E$101,L$2) -> 1 | M8: =COUNTIFS('Commercial People'!$A$2:$A$101,"Purcari Wineries / Crama Ceptura",'Commercial People'!$C$2:$C$101,"Sales",'Commercial People'!$E$2:$E$101,M$2)+COUNTIFS('Commercial People'!$A$2:$A$101,"Crama Ceptura",'Commercial People'!$C$2:$C$101,"Sales",'Commercial People'!$E$2:$E$101,M$2) -> 0 | N8: =COUNTIFS('Commercial People'!$A$2:$A$101,"Purcari Wineries / Crama Ceptura",'Commercial People'!$C$2:$C$101,"Sales",'Commercial People'!$E$2:$E$101,N$2)+COUNTIFS('Commercial People'!$A$2:$A$101,"Crama Ceptura",'Commercial People'!$C$2:$C$101,"Sales",'Commercial People'!$E$2:$E$101,N$2) -> 0 | O8: =COUNTIFS('Commercial People'!$A$2:$A$101,"Purcari Wineries / Crama Ceptura",'Commercial People'!$C$2:$C$101,"Sales",'Commercial People'!$E$2:$E$101,O$2)+COUNTIFS('Commercial People'!$A$2:$A$101,"Crama Ceptura",'Commercial People'!$C$2:$C$101,"Sales",'Commercial People'!$E$2:$E$101,O$2) -> 0 | P8: =COUNTIFS('Commercial People'!$A$2:$A$101,"Purcari Wineries / Crama Ceptura",'Commercial People'!$C$2:$C$101,"Sales",'Commercial People'!$E$2:$E$101,P$2)+COUNTIFS('Commercial People'!$A$2:$A$101,"Crama Ceptura",'Commercial People'!$C$2:$C$101,"Sales",'Commercial People'!$E$2:$E$101,P$2) -> 0 | Q8: =COUNTIFS('Commercial People'!$A$2:$A$101,"Purcari Wineries / Crama Ceptura",'Commercial People'!$C$2:$C$101,"Sales",'Commercial People'!$E$2:$E$101,Q$2)+COUNTIFS('Commercial People'!$A$2:$A$101,"Crama Ceptura",'Commercial People'!$C$2:$C$101,"Sales",'Commercial People'!$E$2:$E$101,Q$2) -> 0 | ... T8: =COUNTIFS('Commercial People'!$A$2:$A$101,"Purcari Wineries / Crama Ceptura",'Commercial People'!$C$2:$C$101,"Sales",'Commercial People'!$E$2:$E$101,T$2)+COUNTIFS('Commercial People'!$A$2:$A$101,"Crama Ceptura",'Commercial People'!$C$2:$C$101,"Sales",'Commercial People'!$E$2:$E$101,T$2) -> 0 | U8: =SUM(J8:T8) -> 1 | V8: =I8+U8 -> 3
A9: Domeniile Averești | B9: =COUNTIFS('Commercial People'!$A$2:$A$101,"Domeniile Averești",'Commercial People'!$C$2:$C$101,"Marketing",'Commercial People'!$E$2:$E$101,B$2) -> 1 | C9: =COUNTIFS('Commercial People'!$A$2:$A$101,"Domeniile Averești",'Commercial People'!$C$2:$C$101,"Marketing",'Commercial People'!$E$2:$E$101,C$2) -> 0 | D9: =COUNTIFS('Commercial People'!$A$2:$A$101,"Domeniile Averești",'Commercial People'!$C$2:$C$101,"Marketing",'Commercial People'!$E$2:$E$101,D$2) -> 0 | E9: =COUNTIFS('Commercial People'!$A$2:$A$101,"Domeniile Averești",'Commercial People'!$C$2:$C$101,"Marketing",'Commercial People'!$E$2:$E$101,E$2) -> 0 | F9: =COUNTIFS('Commercial People'!$A$2:$A$101,"Domeniile Averești",'Commercial People'!$C$2:$C$101,"Marketing",'Commercial People'!$E$2:$E$101,F$2) -> 0 | G9: =COUNTIFS('Commercial People'!$A$2:$A$101,"Domeniile Averești",'Commercial People'!$C$2:$C$101,"Marketing",'Commercial People'!$E$2:$E$101,G$2) -> 0 | H9: =COUNTIFS('Commercial People'!$A$2:$A$101,"Domeniile Averești",'Commercial People'!$C$2:$C$101,"Marketing",'Commercial People'!$E$2:$E$101,H$2) -> 0 | I9: =SUM(B9:H9) -> 1 | J9: =COUNTIFS('Commercial People'!$A$2:$A$101,"Domeniile Averești",'Commercial People'!$C$2:$C$101,"Sales",'Commercial People'!$E$2:$E$101,J$2) -> 0 | K9: =COUNTIFS('Commercial People'!$A$2:$A$101,"Domeniile Averești",'Commercial People'!$C$2:$C$101,"Sales",'Commercial People'!$E$2:$E$101,K$2) -> 0 | L9: =COUNTIFS('Commercial People'!$A$2:$A$101,"Domeniile Averești",'Commercial People'!$C$2:$C$101,"Sales",'Commercial People'!$E$2:$E$101,L$2) -> 2 | M9: =COUNTIFS('Commercial People'!$A$2:$A$101,"Domeniile Averești",'Commercial People'!$C$2:$C$101,"Sales",'Commercial People'!$E$2:$E$101,M$2) -> 1 | N9: =COUNTIFS('Commercial People'!$A$2:$A$101,"Domeniile Averești",'Commercial People'!$C$2:$C$101,"Sales",'Commercial People'!$E$2:$E$101,N$2) -> 0 | O9: =COUNTIFS('Commercial People'!$A$2:$A$101,"Domeniile Averești",'Commercial People'!$C$2:$C$101,"Sales",'Commercial People'!$E$2:$E$101,O$2) -> 0 | P9: =COUNTIFS('Commercial People'!$A$2:$A$101,"Domeniile Averești",'Commercial People'!$C$2:$C$101,"Sales",'Commercial People'!$E$2:$E$101,P$2) -> 0 | Q9: =COUNTIFS('Commercial People'!$A$2:$A$101,"Domeniile Averești",'Commercial People'!$C$2:$C$101,"Sales",'Commercial People'!$E$2:$E$101,Q$2) -> 0 | ... T9: =COUNTIFS('Commercial People'!$A$2:$A$101,"Domeniile Averești",'Commercial People'!$C$2:$C$101,"Sales",'Commercial People'!$E$2:$E$101,T$2) -> 0 | U9: =SUM(J9:T9) -> 3 | V9: =I9+U9 -> 4
A10: Budureasca | B10: =COUNTIFS('Commercial People'!$A$2:$A$101,"Budureasca",'Commercial People'!$C$2:$C$101,"Marketing",'Commercial People'!$E$2:$E$101,B$2) -> 1 | C10: =COUNTIFS('Commercial People'!$A$2:$A$101,"Budureasca",'Commercial People'!$C$2:$C$101,"Marketing",'Commercial People'!$E$2:$E$101,C$2) -> 0 | D10: =COUNTIFS('Commercial People'!$A$2:$A$101,"Budureasca",'Commercial People'!$C$2:$C$101,"Marketing",'Commercial People'!$E$2:$E$101,D$2) -> 0 | E10: =COUNTIFS('Commercial People'!$A$2:$A$101,"Budureasca",'Commercial People'!$C$2:$C$101,"Marketing",'Commercial People'!$E$2:$E$101,E$2) -> 0 | F10: =COUNTIFS('Commercial People'!$A$2:$A$101,"Budureasca",'Commercial People'!$C$2:$C$101,"Marketing",'Commercial People'!$E$2:$E$101,F$2) -> 0 | G10: =COUNTIFS('Commercial People'!$A$2:$A$101,"Budureasca",'Commercial People'!$C$2:$C$101,"Marketing",'Commercial People'!$E$2:$E$101,G$2) -> 0 | H10: =COUNTIFS('Commercial People'!$A$2:$A$101,"Budureasca",'Commercial People'!$C$2:$C$101,"Marketing",'Commercial People'!$E$2:$E$101,H$2) -> 0 | I10: =SUM(B10:H10) -> 1 | J10: =COUNTIFS('Commercial People'!$A$2:$A$101,"Budureasca",'Commercial People'!$C$2:$C$101,"Sales",'Commercial People'!$E$2:$E$101,J$2) -> 0 | K10: =COUNTIFS('Commercial People'!$A$2:$A$101,"Budureasca",'Commercial People'!$C$2:$C$101,"Sales",'Commercial People'!$E$2:$E$101,K$2) -> 1 | L10: =COUNTIFS('Commercial People'!$A$2:$A$101,"Budureasca",'Commercial People'!$C$2:$C$101,"Sales",'Commercial People'!$E$2:$E$101,L$2) -> 1 | M10: =COUNTIFS('Commercial People'!$A$2:$A$101,"Budureasca",'Commercial People'!$C$2:$C$101,"Sales",'Commercial People'!$E$2:$E$101,M$2) -> 1 | N10: =COUNTIFS('Commercial People'!$A$2:$A$101,"Budureasca",'Commercial People'!$C$2:$C$101,"Sales",'Commercial People'!$E$2:$E$101,N$2) -> 0 | O10: =COUNTIFS('Commercial People'!$A$2:$A$101,"Budureasca",'Commercial People'!$C$2:$C$101,"Sales",'Commercial People'!$E$2:$E$101,O$2) -> 0 | P10: =COUNTIFS('Commercial People'!$A$2:$A$101,"Budureasca",'Commercial People'!$C$2:$C$101,"Sales",'Commercial People'!$E$2:$E$101,P$2) -> 0 | Q10: =COUNTIFS('Commercial People'!$A$2:$A$101,"Budureasca",'Commercial People'!$C$2:$C$101,"Sales",'Commercial People'!$E$2:$E$101,Q$2) -> 1 | ... T10: =COUNTIFS('Commercial People'!$A$2:$A$101,"Budureasca",'Commercial People'!$C$2:$C$101,"Sales",'Commercial People'!$E$2:$E$101,T$2) -> 0 | U10: =SUM(J10:T10) -> 4 | V10: =I10+U10 -> 5
A11: Tohani România | B11: =COUNTIFS('Commercial People'!$A$2:$A$101,"Tohani România",'Commercial People'!$C$2:$C$101,"Marketing",'Commercial People'!$E$2:$E$101,B$2) -> 1 | C11: =COUNTIFS('Commercial People'!$A$2:$A$101,"Tohani România",'Commercial People'!$C$2:$C$101,"Marketing",'Commercial People'!$E$2:$E$101,C$2) -> 0 | D11: =COUNTIFS('Commercial People'!$A$2:$A$101,"Tohani România",'Commercial People'!$C$2:$C$101,"Marketing",'Commercial People'!$E$2:$E$101,D$2) -> 0 | E11: =COUNTIFS('Commercial People'!$A$2:$A$101,"Tohani România",'Commercial People'!$C$2:$C$101,"Marketing",'Commercial People'!$E$2:$E$101,E$2) -> 0 | F11: =COUNTIFS('Commercial People'!$A$2:$A$101,"Tohani România",'Commercial People'!$C$2:$C$101,"Marketing",'Commercial People'!$E$2:$E$101,F$2) -> 0 | G11: =COUNTIFS('Commercial People'!$A$2:$A$101,"Tohani România",'Commercial People'!$C$2:$C$101,"Marketing",'Commercial People'!$E$2:$E$101,G$2) -> 0 | H11: =COUNTIFS('Commercial People'!$A$2:$A$101,"Tohani România",'Commercial People'!$C$2:$C$101,"Marketing",'Commercial People'!$E$2:$E$101,H$2) -> 0 | I11: =SUM(B11:H11) -> 1 | J11: =COUNTIFS('Commercial People'!$A$2:$A$101,"Tohani România",'Commercial People'!$C$2:$C$101,"Sales",'Commercial People'!$E$2:$E$101,J$2) -> 0 | K11: =COUNTIFS('Commercial People'!$A$2:$A$101,"Tohani România",'Commercial People'!$C$2:$C$101,"Sales",'Commercial People'!$E$2:$E$101,K$2) -> 0 | L11: =COUNTIFS('Commercial People'!$A$2:$A$101,"Tohani România",'Commercial People'!$C$2:$C$101,"Sales",'Commercial People'!$E$2:$E$101,L$2) -> 0 | M11: =COUNTIFS('Commercial People'!$A$2:$A$101,"Tohani România",'Commercial People'!$C$2:$C$101,"Sales",'Commercial People'!$E$2:$E$101,M$2) -> 0 | N11: =COUNTIFS('Commercial People'!$A$2:$A$101,"Tohani România",'Commercial People'!$C$2:$C$101,"Sales",'Commercial People'!$E$2:$E$101,N$2) -> 0 | O11: =COUNTIFS('Commercial People'!$A$2:$A$101,"Tohani România",'Commercial People'!$C$2:$C$101,"Sales",'Commercial People'!$E$2:$E$101,O$2) -> 0 | P11: =COUNTIFS('Commercial People'!$A$2:$A$101,"Tohani România",'Commercial People'!$C$2:$C$101,"Sales",'Commercial People'!$E$2:$E$101,P$2) -> 1 | Q11: =COUNTIFS('Commercial People'!$A$2:$A$101,"Tohani România",'Commercial People'!$C$2:$C$101,"Sales",'Commercial People'!$E$2:$E$101,Q$2) -> 1 | ... T11: =COUNTIFS('Commercial People'!$A$2:$A$101,"Tohani România",'Commercial People'!$C$2:$C$101,"Sales",'Commercial People'!$E$2:$E$101,T$2) -> 0 | U11: =SUM(J11:T11) -> 2 | V11: =I11+U11 -> 3
A12: Murfatlar | B12: =COUNTIFS('Commercial People'!$A$2:$A$101,"Murfatlar",'Commercial People'!$C$2:$C$101,"Marketing",'Commercial People'!$E$2:$E$101,B$2)+COUNTIFS('Commercial People'!$A$2:$A$101,"Cramele Recaș / Murfatlar",'Commercial People'!$C$2:$C$101,"Marketing",'Commercial People'!$E$2:$E$101,B$2) -> 1 | C12: =COUNTIFS('Commercial People'!$A$2:$A$101,"Murfatlar",'Commercial People'!$C$2:$C$101,"Marketing",'Commercial People'!$E$2:$E$101,C$2)+COUNTIFS('Commercial People'!$A$2:$A$101,"Cramele Recaș / Murfatlar",'Commercial People'!$C$2:$C$101,"Marketing",'Commercial People'!$E$2:$E$101,C$2) -> 1 | D12: =COUNTIFS('Commercial People'!$A$2:$A$101,"Murfatlar",'Commercial People'!$C$2:$C$101,"Marketing",'Commercial People'!$E$2:$E$101,D$2)+COUNTIFS('Commercial People'!$A$2:$A$101,"Cramele Recaș / Murfatlar",'Commercial People'!$C$2:$C$101,"Marketing",'Commercial People'!$E$2:$E$101,D$2) -> 0 | E12: =COUNTIFS('Commercial People'!$A$2:$A$101,"Murfatlar",'Commercial People'!$C$2:$C$101,"Marketing",'Commercial People'!$E$2:$E$101,E$2)+COUNTIFS('Commercial People'!$A$2:$A$101,"Cramele Recaș / Murfatlar",'Commercial People'!$C$2:$C$101,"Marketing",'Commercial People'!$E$2:$E$101,E$2) -> 0 | F12: =COUNTIFS('Commercial People'!$A$2:$A$101,"Murfatlar",'Commercial People'!$C$2:$C$101,"Marketing",'Commercial People'!$E$2:$E$101,F$2)+COUNTIFS('Commercial People'!$A$2:$A$101,"Cramele Recaș / Murfatlar",'Commercial People'!$C$2:$C$101,"Marketing",'Commercial People'!$E$2:$E$101,F$2) -> 0 | G12: =COUNTIFS('Commercial People'!$A$2:$A$101,"Murfatlar",'Commercial People'!$C$2:$C$101,"Marketing",'Commercial People'!$E$2:$E$101,G$2)+COUNTIFS('Commercial People'!$A$2:$A$101,"Cramele Recaș / Murfatlar",'Commercial People'!$C$2:$C$101,"Marketing",'Commercial People'!$E$2:$E$101,G$2) -> 0 | H12: =COUNTIFS('Commercial People'!$A$2:$A$101,"Murfatlar",'Commercial People'!$C$2:$C$101,"Marketing",'Commercial People'!$E$2:$E$101,H$2)+COUNTIFS('Commercial People'!$A$2:$A$101,"Cramele Recaș / Murfatlar",'Commercial People'!$C$2:$C$101,"Marketing",'Commercial People'!$E$2:$E$101,H$2) -> 0 | I12: =SUM(B12:H12) -> 2 | J12: =COUNTIFS('Commercial People'!$A$2:$A$101,"Murfatlar",'Commercial People'!$C$2:$C$101,"Sales",'Commercial People'!$E$2:$E$101,J$2)+COUNTIFS('Commercial People'!$A$2:$A$101,"Cramele Recaș / Murfatlar",'Commercial People'!$C$2:$C$101,"Sales",'Commercial People'!$E$2:$E$101,J$2) -> 1 | K12: =COUNTIFS('Commercial People'!$A$2:$A$101,"Murfatlar",'Commercial People'!$C$2:$C$101,"Sales",'Commercial People'!$E$2:$E$101,K$2)+COUNTIFS('Commercial People'!$A$2:$A$101,"Cramele Recaș / Murfatlar",'Commercial People'!$C$2:$C$101,"Sales",'Commercial People'!$E$2:$E$101,K$2) -> 2 | L12: =COUNTIFS('Commercial People'!$A$2:$A$101,"Murfatlar",'Commercial People'!$C$2:$C$101,"Sales",'Commercial People'!$E$2:$E$101,L$2)+COUNTIFS('Commercial People'!$A$2:$A$101,"Cramele Recaș / Murfatlar",'Commercial People'!$C$2:$C$101,"Sales",'Commercial People'!$E$2:$E$101,L$2) -> 2 | M12: =COUNTIFS('Commercial People'!$A$2:$A$101,"Murfatlar",'Commercial People'!$C$2:$C$101,"Sales",'Commercial People'!$E$2:$E$101,M$2)+COUNTIFS('Commercial People'!$A$2:$A$101,"Cramele Recaș / Murfatlar",'Commercial People'!$C$2:$C$101,"Sales",'Commercial People'!$E$2:$E$101,M$2) -> 0 | N12: =COUNTIFS('Commercial People'!$A$2:$A$101,"Murfatlar",'Commercial People'!$C$2:$C$101,"Sales",'Commercial People'!$E$2:$E$101,N$2)+COUNTIFS('Commercial People'!$A$2:$A$101,"Cramele Recaș / Murfatlar",'Commercial People'!$C$2:$C$101,"Sales",'Commercial People'!$E$2:$E$101,N$2) -> 1 | O12: =COUNTIFS('Commercial People'!$A$2:$A$101,"Murfatlar",'Commercial People'!$C$2:$C$101,"Sales",'Commercial People'!$E$2:$E$101,O$2)+COUNTIFS('Commercial People'!$A$2:$A$101,"Cramele Recaș / Murfatlar",'Commercial People'!$C$2:$C$101,"Sales",'Commercial People'!$E$2:$E$101,O$2) -> 0 | P12: =COUNTIFS('Commercial People'!$A$2:$A$101,"Murfatlar",'Commercial People'!$C$2:$C$101,"Sales",'Commercial People'!$E$2:$E$101,P$2)+COUNTIFS('Commercial People'!$A$2:$A$101,"Cramele Recaș / Murfatlar",'Commercial People'!$C$2:$C$101,"Sales",'Commercial People'!$E$2:$E$101,P$2) -> 0 | Q12: =COUNTIFS('Commercial People'!$A$2:$A$101,"Murfatlar",'Commercial People'!$C$2:$C$101,"Sales",'Commercial People'!$E$2:$E$101,Q$2)+COUNTIFS('Commercial People'!$A$2:$A$101,"Cramele Recaș / Murfatlar",'Commercial People'!$C$2:$C$101,"Sales",'Commercial People'!$E$2:$E$101,Q$2) -> 0 | ... T12: =COUNTIFS('Commercial People'!$A$2:$A$101,"Murfatlar",'Commercial People'!$C$2:$C$101,"Sales",'Commercial People'!$E$2:$E$101,T$2)+COUNTIFS('Commercial People'!$A$2:$A$101,"Cramele Recaș / Murfatlar",'Commercial People'!$C$2:$C$101,"Sales",'Commercial People'!$E$2:$E$101,T$2) -> 0 | U12: =SUM(J12:T12) -> 6 | V12: =I12+U12 -> 8
A13: Davino Winery | B13: =COUNTIFS('Commercial People'!$A$2:$A$101,"Davino Winery",'Commercial People'!$C$2:$C$101,"Marketing",'Commercial People'!$E$2:$E$101,B$2) -> 0 | C13: =COUNTIFS('Commercial People'!$A$2:$A$101,"Davino Winery",'Commercial People'!$C$2:$C$101,"Marketing",'Commercial People'!$E$2:$E$101,C$2) -> 0 | D13: =COUNTIFS('Commercial People'!$A$2:$A$101,"Davino Winery",'Commercial People'!$C$2:$C$101,"Marketing",'Commercial People'!$E$2:$E$101,D$2) -> 0 | E13: =COUNTIFS('Commercial People'!$A$2:$A$101,"Davino Winery",'Commercial People'!$C$2:$C$101,"Marketing",'Commercial People'!$E$2:$E$101,E$2) -> 0 | F13: =COUNTIFS('Commercial People'!$A$2:$A$101,"Davino Winery",'Commercial People'!$C$2:$C$101,"Marketing",'Commercial People'!$E$2:$E$101,F$2) -> 0 | G13: =COUNTIFS('Commercial People'!$A$2:$A$101,"Davino Winery",'Commercial People'!$C$2:$C$101,"Marketing",'Commercial People'!$E$2:$E$101,G$2) -> 1 | H13: =COUNTIFS('Commercial People'!$A$2:$A$101,"Davino Winery",'Commercial People'!$C$2:$C$101,"Marketing",'Commercial People'!$E$2:$E$101,H$2) -> 0 | I13: =SUM(B13:H13) -> 1 | J13: =COUNTIFS('Commercial People'!$A$2:$A$101,"Davino Winery",'Commercial People'!$C$2:$C$101,"Sales",'Commercial People'!$E$2:$E$101,J$2) -> 1 | K13: =COUNTIFS('Commercial People'!$A$2:$A$101,"Davino Winery",'Commercial People'!$C$2:$C$101,"Sales",'Commercial People'!$E$2:$E$101,K$2) -> 0 | L13: =COUNTIFS('Commercial People'!$A$2:$A$101,"Davino Winery",'Commercial People'!$C$2:$C$101,"Sales",'Commercial People'!$E$2:$E$101,L$2) -> 2 | M13: =COUNTIFS('Commercial People'!$A$2:$A$101,"Davino Winery",'Commercial People'!$C$2:$C$101,"Sales",'Commercial People'!$E$2:$E$101,M$2) -> 0 | N13: =COUNTIFS('Commercial People'!$A$2:$A$101,"Davino Winery",'Commercial People'!$C$2:$C$101,"Sales",'Commercial People'!$E$2:$E$101,N$2) -> 0 | O13: =COUNTIFS('Commercial People'!$A$2:$A$101,"Davino Winery",'Commercial People'!$C$2:$C$101,"Sales",'Commercial People'!$E$2:$E$101,O$2) -> 0 | P13: =COUNTIFS('Commercial People'!$A$2:$A$101,"Davino Winery",'Commercial People'!$C$2:$C$101,"Sales",'Commercial People'!$E$2:$E$101,P$2) -> 0 | Q13: =COUNTIFS('Commercial People'!$A$2:$A$101,"Davino Winery",'Commercial People'!$C$2:$C$101,"Sales",'Commercial People'!$E$2:$E$101,Q$2) -> 0 | ... T13: =COUNTIFS('Commercial People'!$A$2:$A$101,"Davino Winery",'Commercial People'!$C$2:$C$101,"Sales",'Commercial People'!$E$2:$E$101,T$2) -> 0 | U13: =SUM(J13:T13) -> 4 | V13: =I13+U13 -> 5
A14: Domeniile Ostrov | B14: =COUNTIFS('Commercial People'!$A$2:$A$101,"Domeniile Ostrov",'Commercial People'!$C$2:$C$101,"Marketing",'Commercial People'!$E$2:$E$101,B$2) -> 0 | C14: =COUNTIFS('Commercial People'!$A$2:$A$101,"Domeniile Ostrov",'Commercial People'!$C$2:$C$101,"Marketing",'Commercial People'!$E$2:$E$101,C$2) -> 1 | D14: =COUNTIFS('Commercial People'!$A$2:$A$101,"Domeniile Ostrov",'Commercial People'!$C$2:$C$101,"Marketing",'Commercial People'!$E$2:$E$101,D$2) -> 0 | E14: =COUNTIFS('Commercial People'!$A$2:$A$101,"Domeniile Ostrov",'Commercial People'!$C$2:$C$101,"Marketing",'Commercial People'!$E$2:$E$101,E$2) -> 0 | F14: =COUNTIFS('Commercial People'!$A$2:$A$101,"Domeniile Ostrov",'Commercial People'!$C$2:$C$101,"Marketing",'Commercial People'!$E$2:$E$101,F$2) -> 0 | G14: =COUNTIFS('Commercial People'!$A$2:$A$101,"Domeniile Ostrov",'Commercial People'!$C$2:$C$101,"Marketing",'Commercial People'!$E$2:$E$101,G$2) -> 0 | H14: =COUNTIFS('Commercial People'!$A$2:$A$101,"Domeniile Ostrov",'Commercial People'!$C$2:$C$101,"Marketing",'Commercial People'!$E$2:$E$101,H$2) -> 0 | I14: =SUM(B14:H14) -> 1 | J14: =COUNTIFS('Commercial People'!$A$2:$A$101,"Domeniile Ostrov",'Commercial People'!$C$2:$C$101,"Sales",'Commercial People'!$E$2:$E$101,J$2) -> 1 | K14: =COUNTIFS('Commercial People'!$A$2:$A$101,"Domeniile Ostrov",'Commercial People'!$C$2:$C$101,"Sales",'Commercial People'!$E$2:$E$101,K$2) -> 0 | L14: =COUNTIFS('Commercial People'!$A$2:$A$101,"Domeniile Ostrov",'Commercial People'!$C$2:$C$101,"Sales",'Commercial People'!$E$2:$E$101,L$2) -> 1 | M14: =COUNTIFS('Commercial People'!$A$2:$A$101,"Domeniile Ostrov",'Commercial People'!$C$2:$C$101,"Sales",'Commercial People'!$E$2:$E$101,M$2) -> 0 | N14: =COUNTIFS('Commercial People'!$A$2:$A$101,"Domeniile Ostrov",'Commercial People'!$C$2:$C$101,"Sales",'Commercial People'!$E$2:$E$101,N$2) -> 0 | O14: =COUNTIFS('Commercial People'!$A$2:$A$101,"Domeniile Ostrov",'Commercial People'!$C$2:$C$101,"Sales",'Commercial People'!$E$2:$E$101,O$2) -> 0 | P14: =COUNTIFS('Commercial People'!$A$2:$A$101,"Domeniile Ostrov",'Commercial People'!$C$2:$C$101,"Sales",'Commercial People'!$E$2:$E$101,P$2) -> 0 | Q14: =COUNTIFS('Commercial People'!$A$2:$A$101,"Domeniile Ostrov",'Commercial People'!$C$2:$C$101,"Sales",'Commercial People'!$E$2:$E$101,Q$2) -> 0 | ... T14: =COUNTIFS('Commercial People'!$A$2:$A$101,"Domeniile Ostrov",'Commercial People'!$C$2:$C$101,"Sales",'Commercial People'!$E$2:$E$101,T$2) -> 0 | U14: =SUM(J14:T14) -> 2 | V14: =I14+U14 -> 3
A15: Casa de Vinuri Cotnari | B15: =COUNTIFS('Commercial People'!$A$2:$A$101,"Casa de Vinuri Cotnari",'Commercial People'!$C$2:$C$101,"Marketing",'Commercial People'!$E$2:$E$101,B$2) -> 0 | C15: =COUNTIFS('Commercial People'!$A$2:$A$101,"Casa de Vinuri Cotnari",'Commercial People'!$C$2:$C$101,"Marketing",'Commercial People'!$E$2:$E$101,C$2) -> 0 | D15: =COUNTIFS('Commercial People'!$A$2:$A$101,"Casa de Vinuri Cotnari",'Commercial People'!$C$2:$C$101,"Marketing",'Commercial People'!$E$2:$E$101,D$2) -> 0 | E15: =COUNTIFS('Commercial People'!$A$2:$A$101,"Casa de Vinuri Cotnari",'Commercial People'!$C$2:$C$101,"Marketing",'Commercial People'!$E$2:$E$101,E$2) -> 0 | F15: =COUNTIFS('Commercial People'!$A$2:$A$101,"Casa de Vinuri Cotnari",'Commercial People'!$C$2:$C$101,"Marketing",'Commercial People'!$E$2:$E$101,F$2) -> 0 | G15: =COUNTIFS('Commercial People'!$A$2:$A$101,"Casa de Vinuri Cotnari",'Commercial People'!$C$2:$C$101,"Marketing",'Commercial People'!$E$2:$E$101,G$2) -> 0 | H15: =COUNTIFS('Commercial People'!$A$2:$A$101,"Casa de Vinuri Cotnari",'Commercial People'!$C$2:$C$101,"Marketing",'Commercial People'!$E$2:$E$101,H$2) -> 0 | I15: =SUM(B15:H15) -> 0 | J15: =COUNTIFS('Commercial People'!$A$2:$A$101,"Casa de Vinuri Cotnari",'Commercial People'!$C$2:$C$101,"Sales",'Commercial People'!$E$2:$E$101,J$2) -> 0 | K15: =COUNTIFS('Commercial People'!$A$2:$A$101,"Casa de Vinuri Cotnari",'Commercial People'!$C$2:$C$101,"Sales",'Commercial People'!$E$2:$E$101,K$2) -> 0 | L15: =COUNTIFS('Commercial People'!$A$2:$A$101,"Casa de Vinuri Cotnari",'Commercial People'!$C$2:$C$101,"Sales",'Commercial People'!$E$2:$E$101,L$2) -> 1 | M15: =COUNTIFS('Commercial People'!$A$2:$A$101,"Casa de Vinuri Cotnari",'Commercial People'!$C$2:$C$101,"Sales",'Commercial People'!$E$2:$E$101,M$2) -> 0 | N15: =COUNTIFS('Commercial People'!$A$2:$A$101,"Casa de Vinuri Cotnari",'Commercial People'!$C$2:$C$101,"Sales",'Commercial People'!$E$2:$E$101,N$2) -> 1 | O15: =COUNTIFS('Commercial People'!$A$2:$A$101,"Casa de Vinuri Cotnari",'Commercial People'!$C$2:$C$101,"Sales",'Commercial People'!$E$2:$E$101,O$2) -> 0 | P15: =COUNTIFS('Commercial People'!$A$2:$A$101,"Casa de Vinuri Cotnari",'Commercial People'!$C$2:$C$101,"Sales",'Commercial People'!$E$2:$E$101,P$2) -> 0 | Q15: =COUNTIFS('Commercial People'!$A$2:$A$101,"Casa de Vinuri Cotnari",'Commercial People'!$C$2:$C$101,"Sales",'Commercial People'!$E$2:$E$101,Q$2) -> 0 | ... T15: =COUNTIFS('Commercial People'!$A$2:$A$101,"Casa de Vinuri Cotnari",'Commercial People'!$C$2:$C$101,"Sales",'Commercial People'!$E$2:$E$101,T$2) -> 0 | U15: =SUM(J15:T15) -> 2 | V15: =I15+U15 -> 2
A16: Zarea | B16: =COUNTIFS('Commercial People'!$A$2:$A$101,"Zarea",'Commercial People'!$C$2:$C$101,"Marketing",'Commercial People'!$E$2:$E$101,B$2) -> 1 | C16: =COUNTIFS('Commercial People'!$A$2:$A$101,"Zarea",'Commercial People'!$C$2:$C$101,"Marketing",'Commercial People'!$E$2:$E$101,C$2) -> 0 | D16: =COUNTIFS('Commercial People'!$A$2:$A$101,"Zarea",'Commercial People'!$C$2:$C$101,"Marketing",'Commercial People'!$E$2:$E$101,D$2) -> 1 | E16: =COUNTIFS('Commercial People'!$A$2:$A$101,"Zarea",'Commercial People'!$C$2:$C$101,"Marketing",'Commercial People'!$E$2:$E$101,E$2) -> 0 | F16: =COUNTIFS('Commercial People'!$A$2:$A$101,"Zarea",'Commercial People'!$C$2:$C$101,"Marketing",'Commercial People'!$E$2:$E$101,F$2) -> 0 | G16: =COUNTIFS('Commercial People'!$A$2:$A$101,"Zarea",'Commercial People'!$C$2:$C$101,"Marketing",'Commercial People'!$E$2:$E$101,G$2) -> 0 | H16: =COUNTIFS('Commercial People'!$A$2:$A$101,"Zarea",'Commercial People'!$C$2:$C$101,"Marketing",'Commercial People'!$E$2:$E$101,H$2) -> 0 | I16: =SUM(B16:H16) -> 2 | J16: =COUNTIFS('Commercial People'!$A$2:$A$101,"Zarea",'Commercial People'!$C$2:$C$101,"Sales",'Commercial People'!$E$2:$E$101,J$2) -> 1 | K16: =COUNTIFS('Commercial People'!$A$2:$A$101,"Zarea",'Commercial People'!$C$2:$C$101,"Sales",'Commercial People'!$E$2:$E$101,K$2) -> 0 | L16: =COUNTIFS('Commercial People'!$A$2:$A$101,"Zarea",'Commercial People'!$C$2:$C$101,"Sales",'Commercial People'!$E$2:$E$101,L$2) -> 1 | M16: =COUNTIFS('Commercial People'!$A$2:$A$101,"Zarea",'Commercial People'!$C$2:$C$101,"Sales",'Commercial People'!$E$2:$E$101,M$2) -> 0 | N16: =COUNTIFS('Commercial People'!$A$2:$A$101,"Zarea",'Commercial People'!$C$2:$C$101,"Sales",'Commercial People'!$E$2:$E$101,N$2) -> 0 | O16: =COUNTIFS('Commercial People'!$A$2:$A$101,"Zarea",'Commercial People'!$C$2:$C$101,"Sales",'Commercial People'!$E$2:$E$101,O$2) -> 0 | P16: =COUNTIFS('Commercial People'!$A$2:$A$101,"Zarea",'Commercial People'!$C$2:$C$101,"Sales",'Commercial People'!$E$2:$E$101,P$2) -> 0 | Q16: =COUNTIFS('Commercial People'!$A$2:$A$101,"Zarea",'Commercial People'!$C$2:$C$101,"Sales",'Commercial People'!$E$2:$E$101,Q$2) -> 0 | ... T16: =COUNTIFS('Commercial People'!$A$2:$A$101,"Zarea",'Commercial People'!$C$2:$C$101,"Sales",'Commercial People'!$E$2:$E$101,T$2) -> 0 | U16: =SUM(J16:T16) -> 2 | V16: =I16+U16 -> 4
A17: Via Viticola | B17: =COUNTIFS('Commercial People'!$A$2:$A$101,"Via Viticola",'Commercial People'!$C$2:$C$101,"Marketing",'Commercial People'!$E$2:$E$101,B$2)+COUNTIFS('Commercial People'!$A$2:$A$101,"Via Viticola / Vintruvian Estates",'Commercial People'!$C$2:$C$101,"Marketing",'Commercial People'!$E$2:$E$101,B$2) -> 1 | C17: =COUNTIFS('Commercial People'!$A$2:$A$101,"Via Viticola",'Commercial People'!$C$2:$C$101,"Marketing",'Commercial People'!$E$2:$E$101,C$2)+COUNTIFS('Commercial People'!$A$2:$A$101,"Via Viticola / Vintruvian Estates",'Commercial People'!$C$2:$C$101,"Marketing",'Commercial People'!$E$2:$E$101,C$2) -> 2 | D17: =COUNTIFS('Commercial People'!$A$2:$A$101,"Via Viticola",'Commercial People'!$C$2:$C$101,"Marketing",'Commercial People'!$E$2:$E$101,D$2)+COUNTIFS('Commercial People'!$A$2:$A$101,"Via Viticola / Vintruvian Estates",'Commercial People'!$C$2:$C$101,"Marketing",'Commercial People'!$E$2:$E$101,D$2) -> 0 | E17: =COUNTIFS('Commercial People'!$A$2:$A$101,"Via Viticola",'Commercial People'!$C$2:$C$101,"Marketing",'Commercial People'!$E$2:$E$101,E$2)+COUNTIFS('Commercial People'!$A$2:$A$101,"Via Viticola / Vintruvian Estates",'Commercial People'!$C$2:$C$101,"Marketing",'Commercial People'!$E$2:$E$101,E$2) -> 0 | F17: =COUNTIFS('Commercial People'!$A$2:$A$101,"Via Viticola",'Commercial People'!$C$2:$C$101,"Marketing",'Commercial People'!$E$2:$E$101,F$2)+COUNTIFS('Commercial People'!$A$2:$A$101,"Via Viticola / Vintruvian Estates",'Commercial People'!$C$2:$C$101,"Marketing",'Commercial People'!$E$2:$E$101,F$2) -> 0 | G17: =COUNTIFS('Commercial People'!$A$2:$A$101,"Via Viticola",'Commercial People'!$C$2:$C$101,"Marketing",'Commercial People'!$E$2:$E$101,G$2)+COUNTIFS('Commercial People'!$A$2:$A$101,"Via Viticola / Vintruvian Estates",'Commercial People'!$C$2:$C$101,"Marketing",'Commercial People'!$E$2:$E$101,G$2) -> 0 | H17: =COUNTIFS('Commercial People'!$A$2:$A$101,"Via Viticola",'Commercial People'!$C$2:$C$101,"Marketing",'Commercial People'!$E$2:$E$101,H$2)+COUNTIFS('Commercial People'!$A$2:$A$101,"Via Viticola / Vintruvian Estates",'Commercial People'!$C$2:$C$101,"Marketing",'Commercial People'!$E$2:$E$101,H$2) -> 0 | I17: =SUM(B17:H17) -> 3 | J17: =COUNTIFS('Commercial People'!$A$2:$A$101,"Via Viticola",'Commercial People'!$C$2:$C$101,"Sales",'Commercial People'!$E$2:$E$101,J$2)+COUNTIFS('Commercial People'!$A$2:$A$101,"Via Viticola / Vintruvian Estates",'Commercial People'!$C$2:$C$101,"Sales",'Commercial People'!$E$2:$E$101,J$2) -> 0 | K17: =COUNTIFS('Commercial People'!$A$2:$A$101,"Via Viticola",'Commercial People'!$C$2:$C$101,"Sales",'Commercial People'!$E$2:$E$101,K$2)+COUNTIFS('Commercial People'!$A$2:$A$101,"Via Viticola / Vintruvian Estates",'Commercial People'!$C$2:$C$101,"Sales",'Commercial People'!$E$2:$E$101,K$2) -> 0 | L17: =COUNTIFS('Commercial People'!$A$2:$A$101,"Via Viticola",'Commercial People'!$C$2:$C$101,"Sales",'Commercial People'!$E$2:$E$101,L$2)+COUNTIFS('Commercial People'!$A$2:$A$101,"Via Viticola / Vintruvian Estates",'Commercial People'!$C$2:$C$101,"Sales",'Commercial People'!$E$2:$E$101,L$2) -> 1 | M17: =COUNTIFS('Commercial People'!$A$2:$A$101,"Via Viticola",'Commercial People'!$C$2:$C$101,"Sales",'Commercial People'!$E$2:$E$101,M$2)+COUNTIFS('Commercial People'!$A$2:$A$101,"Via Viticola / Vintruvian Estates",'Commercial People'!$C$2:$C$101,"Sales",'Commercial People'!$E$2:$E$101,M$2) -> 1 | N17: =COUNTIFS('Commercial People'!$A$2:$A$101,"Via Viticola",'Commercial People'!$C$2:$C$101,"Sales",'Commercial People'!$E$2:$E$101,N$2)+COUNTIFS('Commercial People'!$A$2:$A$101,"Via Viticola / Vintruvian Estates",'Commercial People'!$C$2:$C$101,"Sales",'Commercial People'!$E$2:$E$101,N$2) -> 1 | O17: =COUNTIFS('Commercial People'!$A$2:$A$101,"Via Viticola",'Commercial People'!$C$2:$C$101,"Sales",'Commercial People'!$E$2:$E$101,O$2)+COUNTIFS('Commercial People'!$A$2:$A$101,"Via Viticola / Vintruvian Estates",'Commercial People'!$C$2:$C$101,"Sales",'Commercial People'!$E$2:$E$101,O$2) -> 1 | P17: =COUNTIFS('Commercial People'!$A$2:$A$101,"Via Viticola",'Commercial People'!$C$2:$C$101,"Sales",'Commercial People'!$E$2:$E$101,P$2)+COUNTIFS('Commercial People'!$A$2:$A$101,"Via Viticola / Vintruvian Estates",'Commercial People'!$C$2:$C$101,"Sales",'Commercial People'!$E$2:$E$101,P$2) -> 0 | Q17: =COUNTIFS('Commercial People'!$A$2:$A$101,"Via Viticola",'Commercial People'!$C$2:$C$101,"Sales",'Commercial People'!$E$2:$E$101,Q$2)+COUNTIFS('Commercial People'!$A$2:$A$101,"Via Viticola / Vintruvian Estates",'Commercial People'!$C$2:$C$101,"Sales",'Commercial People'!$E$2:$E$101,Q$2) -> 0 | ... T17: =COUNTIFS('Commercial People'!$A$2:$A$101,"Via Viticola",'Commercial People'!$C$2:$C$101,"Sales",'Commercial People'!$E$2:$E$101,T$2)+COUNTIFS('Commercial People'!$A$2:$A$101,"Via Viticola / Vintruvian Estates",'Commercial People'!$C$2:$C$101,"Sales",'Commercial People'!$E$2:$E$101,T$2) -> 0 | U17: =SUM(J17:T17) -> 4 | V17: =I17+U17 -> 7
A18: Crama Gîrboiu | B18: =COUNTIFS('Commercial People'!$A$2:$A$101,"Crama Gîrboiu",'Commercial People'!$C$2:$C$101,"Marketing",'Commercial People'!$E$2:$E$101,B$2) -> 0 | C18: =COUNTIFS('Commercial People'!$A$2:$A$101,"Crama Gîrboiu",'Commercial People'!$C$2:$C$101,"Marketing",'Commercial People'!$E$2:$E$101,C$2) -> 0 | D18: =COUNTIFS('Commercial People'!$A$2:$A$101,"Crama Gîrboiu",'Commercial People'!$C$2:$C$101,"Marketing",'Commercial People'!$E$2:$E$101,D$2) -> 0 | E18: =COUNTIFS('Commercial People'!$A$2:$A$101,"Crama Gîrboiu",'Commercial People'!$C$2:$C$101,"Marketing",'Commercial People'!$E$2:$E$101,E$2) -> 0 | F18: =COUNTIFS('Commercial People'!$A$2:$A$101,"Crama Gîrboiu",'Commercial People'!$C$2:$C$101,"Marketing",'Commercial People'!$E$2:$E$101,F$2) -> 0 | G18: =COUNTIFS('Commercial People'!$A$2:$A$101,"Crama Gîrboiu",'Commercial People'!$C$2:$C$101,"Marketing",'Commercial People'!$E$2:$E$101,G$2) -> 0 | H18: =COUNTIFS('Commercial People'!$A$2:$A$101,"Crama Gîrboiu",'Commercial People'!$C$2:$C$101,"Marketing",'Commercial People'!$E$2:$E$101,H$2) -> 0 | I18: =SUM(B18:H18) -> 0 | J18: =COUNTIFS('Commercial People'!$A$2:$A$101,"Crama Gîrboiu",'Commercial People'!$C$2:$C$101,"Sales",'Commercial People'!$E$2:$E$101,J$2) -> 0 | K18: =COUNTIFS('Commercial People'!$A$2:$A$101,"Crama Gîrboiu",'Commercial People'!$C$2:$C$101,"Sales",'Commercial People'!$E$2:$E$101,K$2) -> 0 | L18: =COUNTIFS('Commercial People'!$A$2:$A$101,"Crama Gîrboiu",'Commercial People'!$C$2:$C$101,"Sales",'Commercial People'!$E$2:$E$101,L$2) -> 0 | M18: =COUNTIFS('Commercial People'!$A$2:$A$101,"Crama Gîrboiu",'Commercial People'!$C$2:$C$101,"Sales",'Commercial People'!$E$2:$E$101,M$2) -> 0 | N18: =COUNTIFS('Commercial People'!$A$2:$A$101,"Crama Gîrboiu",'Commercial People'!$C$2:$C$101,"Sales",'Commercial People'!$E$2:$E$101,N$2) -> 0 | O18: =COUNTIFS('Commercial People'!$A$2:$A$101,"Crama Gîrboiu",'Commercial People'!$C$2:$C$101,"Sales",'Commercial People'!$E$2:$E$101,O$2) -> 0 | P18: =COUNTIFS('Commercial People'!$A$2:$A$101,"Crama Gîrboiu",'Commercial People'!$C$2:$C$101,"Sales",'Commercial People'!$E$2:$E$101,P$2) -> 0 | Q18: =COUNTIFS('Commercial People'!$A$2:$A$101,"Crama Gîrboiu",'Commercial People'!$C$2:$C$101,"Sales",'Commercial People'!$E$2:$E$101,Q$2) -> 0 | ... T18: =COUNTIFS('Commercial People'!$A$2:$A$101,"Crama Gîrboiu",'Commercial People'!$C$2:$C$101,"Sales",'Commercial People'!$E$2:$E$101,T$2) -> 0 | U18: =SUM(J18:T18) -> 0 | V18: =I18+U18 -> 0
A19: Domeniile Vânju Mare | B19: =COUNTIFS('Commercial People'!$A$2:$A$101,"Domeniile Vânju Mare",'Commercial People'!$C$2:$C$101,"Marketing",'Commercial People'!$E$2:$E$101,B$2) -> 0 | C19: =COUNTIFS('Commercial People'!$A$2:$A$101,"Domeniile Vânju Mare",'Commercial People'!$C$2:$C$101,"Marketing",'Commercial People'!$E$2:$E$101,C$2) -> 0 | D19: =COUNTIFS('Commercial People'!$A$2:$A$101,"Domeniile Vânju Mare",'Commercial People'!$C$2:$C$101,"Marketing",'Commercial People'!$E$2:$E$101,D$2) -> 0 | E19: =COUNTIFS('Commercial People'!$A$2:$A$101,"Domeniile Vânju Mare",'Commercial People'!$C$2:$C$101,"Marketing",'Commercial People'!$E$2:$E$101,E$2) -> 0 | F19: =COUNTIFS('Commercial People'!$A$2:$A$101,"Domeniile Vânju Mare",'Commercial People'!$C$2:$C$101,"Marketing",'Commercial People'!$E$2:$E$101,F$2) -> 0 | G19: =COUNTIFS('Commercial People'!$A$2:$A$101,"Domeniile Vânju Mare",'Commercial People'!$C$2:$C$101,"Marketing",'Commercial People'!$E$2:$E$101,G$2) -> 0 | H19: =COUNTIFS('Commercial People'!$A$2:$A$101,"Domeniile Vânju Mare",'Commercial People'!$C$2:$C$101,"Marketing",'Commercial People'!$E$2:$E$101,H$2) -> 0 | I19: =SUM(B19:H19) -> 0 | J19: =COUNTIFS('Commercial People'!$A$2:$A$101,"Domeniile Vânju Mare",'Commercial People'!$C$2:$C$101,"Sales",'Commercial People'!$E$2:$E$101,J$2) -> 0 | K19: =COUNTIFS('Commercial People'!$A$2:$A$101,"Domeniile Vânju Mare",'Commercial People'!$C$2:$C$101,"Sales",'Commercial People'!$E$2:$E$101,K$2) -> 0 | L19: =COUNTIFS('Commercial People'!$A$2:$A$101,"Domeniile Vânju Mare",'Commercial People'!$C$2:$C$101,"Sales",'Commercial People'!$E$2:$E$101,L$2) -> 0 | M19: =COUNTIFS('Commercial People'!$A$2:$A$101,"Domeniile Vânju Mare",'Commercial People'!$C$2:$C$101,"Sales",'Commercial People'!$E$2:$E$101,M$2) -> 0 | N19: =COUNTIFS('Commercial People'!$A$2:$A$101,"Domeniile Vânju Mare",'Commercial People'!$C$2:$C$101,"Sales",'Commercial People'!$E$2:$E$101,N$2) -> 0 | O19: =COUNTIFS('Commercial People'!$A$2:$A$101,"Domeniile Vânju Mare",'Commercial People'!$C$2:$C$101,"Sales",'Commercial People'!$E$2:$E$101,O$2) -> 0 | P19: =COUNTIFS('Commercial People'!$A$2:$A$101,"Domeniile Vânju Mare",'Commercial People'!$C$2:$C$101,"Sales",'Commercial People'!$E$2:$E$101,P$2) -> 0 | Q19: =COUNTIFS('Commercial People'!$A$2:$A$101,"Domeniile Vânju Mare",'Commercial People'!$C$2:$C$101,"Sales",'Commercial People'!$E$2:$E$101,Q$2) -> 0 | ... T19: =COUNTIFS('Commercial People'!$A$2:$A$101,"Domeniile Vânju Mare",'Commercial People'!$C$2:$C$101,"Sales",'Commercial People'!$E$2:$E$101,T$2) -> 0 | U19: =SUM(J19:T19) -> 0 | V19: =I19+U19 -> 0
A20: Licorna WineHouse | B20: =COUNTIFS('Commercial People'!$A$2:$A$101,"Licorna WineHouse",'Commercial People'!$C$2:$C$101,"Marketing",'Commercial People'!$E$2:$E$101,B$2) -> 0 | C20: =COUNTIFS('Commercial People'!$A$2:$A$101,"Licorna WineHouse",'Commercial People'!$C$2:$C$101,"Marketing",'Commercial People'!$E$2:$E$101,C$2) -> 0 | D20: =COUNTIFS('Commercial People'!$A$2:$A$101,"Licorna WineHouse",'Commercial People'!$C$2:$C$101,"Marketing",'Commercial People'!$E$2:$E$101,D$2) -> 0 | E20: =COUNTIFS('Commercial People'!$A$2:$A$101,"Licorna WineHouse",'Commercial People'!$C$2:$C$101,"Marketing",'Commercial People'!$E$2:$E$101,E$2) -> 0 | F20: =COUNTIFS('Commercial People'!$A$2:$A$101,"Licorna WineHouse",'Commercial People'!$C$2:$C$101,"Marketing",'Commercial People'!$E$2:$E$101,F$2) -> 0 | G20: =COUNTIFS('Commercial People'!$A$2:$A$101,"Licorna WineHouse",'Commercial People'!$C$2:$C$101,"Marketing",'Commercial People'!$E$2:$E$101,G$2) -> 0 | H20: =COUNTIFS('Commercial People'!$A$2:$A$101,"Licorna WineHouse",'Commercial People'!$C$2:$C$101,"Marketing",'Commercial People'!$E$2:$E$101,H$2) -> 0 | I20: =SUM(B20:H20) -> 0 | J20: =COUNTIFS('Commercial People'!$A$2:$A$101,"Licorna WineHouse",'Commercial People'!$C$2:$C$101,"Sales",'Commercial People'!$E$2:$E$101,J$2) -> 0 | K20: =COUNTIFS('Commercial People'!$A$2:$A$101,"Licorna WineHouse",'Commercial People'!$C$2:$C$101,"Sales",'Commercial People'!$E$2:$E$101,K$2) -> 0 | L20: =COUNTIFS('Commercial People'!$A$2:$A$101,"Licorna WineHouse",'Commercial People'!$C$2:$C$101,"Sales",'Commercial People'!$E$2:$E$101,L$2) -> 0 | M20: =COUNTIFS('Commercial People'!$A$2:$A$101,"Licorna WineHouse",'Commercial People'!$C$2:$C$101,"Sales",'Commercial People'!$E$2:$E$101,M$2) -> 0 | N20: =COUNTIFS('Commercial People'!$A$2:$A$101,"Licorna WineHouse",'Commercial People'!$C$2:$C$101,"Sales",'Commercial People'!$E$2:$E$101,N$2) -> 0 | O20: =COUNTIFS('Commercial People'!$A$2:$A$101,"Licorna WineHouse",'Commercial People'!$C$2:$C$101,"Sales",'Commercial People'!$E$2:$E$101,O$2) -> 0 | P20: =COUNTIFS('Commercial People'!$A$2:$A$101,"Licorna WineHouse",'Commercial People'!$C$2:$C$101,"Sales",'Commercial People'!$E$2:$E$101,P$2) -> 0 | Q20: =COUNTIFS('Commercial People'!$A$2:$A$101,"Licorna WineHouse",'Commercial People'!$C$2:$C$101,"Sales",'Commercial People'!$E$2:$E$101,Q$2) -> 0 | ... T20: =COUNTIFS('Commercial People'!$A$2:$A$101,"Licorna WineHouse",'Commercial People'!$C$2:$C$101,"Sales",'Commercial People'!$E$2:$E$101,T$2) -> 0 | U20: =SUM(J20:T20) -> 0 | V20: =I20+U20 -> 0
A21: Gitana Winery | B21: =COUNTIFS('Commercial People'!$A$2:$A$101,"Gitana Winery",'Commercial People'!$C$2:$C$101,"Marketing",'Commercial People'!$E$2:$E$101,B$2) -> 1 | C21: =COUNTIFS('Commercial People'!$A$2:$A$101,"Gitana Winery",'Commercial People'!$C$2:$C$101,"Marketing",'Commercial People'!$E$2:$E$101,C$2) -> 0 | D21: =COUNTIFS('Commercial People'!$A$2:$A$101,"Gitana Winery",'Commercial People'!$C$2:$C$101,"Marketing",'Commercial People'!$E$2:$E$101,D$2) -> 0 | E21: =COUNTIFS('Commercial People'!$A$2:$A$101,"Gitana Winery",'Commercial People'!$C$2:$C$101,"Marketing",'Commercial People'!$E$2:$E$101,E$2) -> 0 | F21: =COUNTIFS('Commercial People'!$A$2:$A$101,"Gitana Winery",'Commercial People'!$C$2:$C$101,"Marketing",'Commercial People'!$E$2:$E$101,F$2) -> 0 | G21: =COUNTIFS('Commercial People'!$A$2:$A$101,"Gitana Winery",'Commercial People'!$C$2:$C$101,"Marketing",'Commercial People'!$E$2:$E$101,G$2) -> 0 | H21: =COUNTIFS('Commercial People'!$A$2:$A$101,"Gitana Winery",'Commercial People'!$C$2:$C$101,"Marketing",'Commercial People'!$E$2:$E$101,H$2) -> 0 | I21: =SUM(B21:H21) -> 1 | J21: =COUNTIFS('Commercial People'!$A$2:$A$101,"Gitana Winery",'Commercial People'!$C$2:$C$101,"Sales",'Commercial People'!$E$2:$E$101,J$2) -> 0 | K21: =COUNTIFS('Commercial People'!$A$2:$A$101,"Gitana Winery",'Commercial People'!$C$2:$C$101,"Sales",'Commercial People'!$E$2:$E$101,K$2) -> 0 | L21: =COUNTIFS('Commercial People'!$A$2:$A$101,"Gitana Winery",'Commercial People'!$C$2:$C$101,"Sales",'Commercial People'!$E$2:$E$101,L$2) -> 1 | M21: =COUNTIFS('Commercial People'!$A$2:$A$101,"Gitana Winery",'Commercial People'!$C$2:$C$101,"Sales",'Commercial People'!$E$2:$E$101,M$2) -> 0 | N21: =COUNTIFS('Commercial People'!$A$2:$A$101,"Gitana Winery",'Commercial People'!$C$2:$C$101,"Sales",'Commercial People'!$E$2:$E$101,N$2) -> 0 | O21: =COUNTIFS('Commercial People'!$A$2:$A$101,"Gitana Winery",'Commercial People'!$C$2:$C$101,"Sales",'Commercial People'!$E$2:$E$101,O$2) -> 0 | P21: =COUNTIFS('Commercial People'!$A$2:$A$101,"Gitana Winery",'Commercial People'!$C$2:$C$101,"Sales",'Commercial People'!$E$2:$E$101,P$2) -> 0 | Q21: =COUNTIFS('Commercial People'!$A$2:$A$101,"Gitana Winery",'Commercial People'!$C$2:$C$101,"Sales",'Commercial People'!$E$2:$E$101,Q$2) -> 0 | ... T21: =COUNTIFS('Commercial People'!$A$2:$A$101,"Gitana Winery",'Commercial People'!$C$2:$C$101,"Sales",'Commercial People'!$E$2:$E$101,T$2) -> 0 | U21: =SUM(J21:T21) -> 1 | V21: =I21+U21 -> 2
A22: Domeniile Sâmburești | B22: =COUNTIFS('Commercial People'!$A$2:$A$101,"Domeniile Sâmburești",'Commercial People'!$C$2:$C$101,"Marketing",'Commercial People'!$E$2:$E$101,B$2) -> 0 | C22: =COUNTIFS('Commercial People'!$A$2:$A$101,"Domeniile Sâmburești",'Commercial People'!$C$2:$C$101,"Marketing",'Commercial People'!$E$2:$E$101,C$2) -> 0 | D22: =COUNTIFS('Commercial People'!$A$2:$A$101,"Domeniile Sâmburești",'Commercial People'!$C$2:$C$101,"Marketing",'Commercial People'!$E$2:$E$101,D$2) -> 0 | E22: =COUNTIFS('Commercial People'!$A$2:$A$101,"Domeniile Sâmburești",'Commercial People'!$C$2:$C$101,"Marketing",'Commercial People'!$E$2:$E$101,E$2) -> 0 | F22: =COUNTIFS('Commercial People'!$A$2:$A$101,"Domeniile Sâmburești",'Commercial People'!$C$2:$C$101,"Marketing",'Commercial People'!$E$2:$E$101,F$2) -> 0 | G22: =COUNTIFS('Commercial People'!$A$2:$A$101,"Domeniile Sâmburești",'Commercial People'!$C$2:$C$101,"Marketing",'Commercial People'!$E$2:$E$101,G$2) -> 0 | H22: =COUNTIFS('Commercial People'!$A$2:$A$101,"Domeniile Sâmburești",'Commercial People'!$C$2:$C$101,"Marketing",'Commercial People'!$E$2:$E$101,H$2) -> 0 | I22: =SUM(B22:H22) -> 0 | J22: =COUNTIFS('Commercial People'!$A$2:$A$101,"Domeniile Sâmburești",'Commercial People'!$C$2:$C$101,"Sales",'Commercial People'!$E$2:$E$101,J$2) -> 0 | K22: =COUNTIFS('Commercial People'!$A$2:$A$101,"Domeniile Sâmburești",'Commercial People'!$C$2:$C$101,"Sales",'Commercial People'!$E$2:$E$101,K$2) -> 0 | L22: =COUNTIFS('Commercial People'!$A$2:$A$101,"Domeniile Sâmburești",'Commercial People'!$C$2:$C$101,"Sales",'Commercial People'!$E$2:$E$101,L$2) -> 0 | M22: =COUNTIFS('Commercial People'!$A$2:$A$101,"Domeniile Sâmburești",'Commercial People'!$C$2:$C$101,"Sales",'Commercial People'!$E$2:$E$101,M$2) -> 0 | N22: =COUNTIFS('Commercial People'!$A$2:$A$101,"Domeniile Sâmburești",'Commercial People'!$C$2:$C$101,"Sales",'Commercial People'!$E$2:$E$101,N$2) -> 0 | O22: =COUNTIFS('Commercial People'!$A$2:$A$101,"Domeniile Sâmburești",'Commercial People'!$C$2:$C$101,"Sales",'Commercial People'!$E$2:$E$101,O$2) -> 0 | P22: =COUNTIFS('Commercial People'!$A$2:$A$101,"Domeniile Sâmburești",'Commercial People'!$C$2:$C$101,"Sales",'Commercial People'!$E$2:$E$101,P$2) -> 0 | Q22: =COUNTIFS('Commercial People'!$A$2:$A$101,"Domeniile Sâmburești",'Commercial People'!$C$2:$C$101,"Sales",'Commercial People'!$E$2:$E$101,Q$2) -> 0 | ... T22: =COUNTIFS('Commercial People'!$A$2:$A$101,"Domeniile Sâmburești",'Commercial People'!$C$2:$C$101,"Sales",'Commercial People'!$E$2:$E$101,T$2) -> 0 | U22: =SUM(J22:T22) -> 0 | V22: =I22+U22 -> 0
A23: Crama Rasova | B23: =COUNTIFS('Commercial People'!$A$2:$A$101,"Crama Rasova",'Commercial People'!$C$2:$C$101,"Marketing",'Commercial People'!$E$2:$E$101,B$2) -> 0 | C23: =COUNTIFS('Commercial People'!$A$2:$A$101,"Crama Rasova",'Commercial People'!$C$2:$C$101,"Marketing",'Commercial People'!$E$2:$E$101,C$2) -> 0 | D23: =COUNTIFS('Commercial People'!$A$2:$A$101,"Crama Rasova",'Commercial People'!$C$2:$C$101,"Marketing",'Commercial People'!$E$2:$E$101,D$2) -> 0 | E23: =COUNTIFS('Commercial People'!$A$2:$A$101,"Crama Rasova",'Commercial People'!$C$2:$C$101,"Marketing",'Commercial People'!$E$2:$E$101,E$2) -> 0 | F23: =COUNTIFS('Commercial People'!$A$2:$A$101,"Crama Rasova",'Commercial People'!$C$2:$C$101,"Marketing",'Commercial People'!$E$2:$E$101,F$2) -> 0 | G23: =COUNTIFS('Commercial People'!$A$2:$A$101,"Crama Rasova",'Commercial People'!$C$2:$C$101,"Marketing",'Commercial People'!$E$2:$E$101,G$2) -> 0 | H23: =COUNTIFS('Commercial People'!$A$2:$A$101,"Crama Rasova",'Commercial People'!$C$2:$C$101,"Marketing",'Commercial People'!$E$2:$E$101,H$2) -> 0 | I23: =SUM(B23:H23) -> 0 | J23: =COUNTIFS('Commercial People'!$A$2:$A$101,"Crama Rasova",'Commercial People'!$C$2:$C$101,"Sales",'Commercial People'!$E$2:$E$101,J$2) -> 0 | K23: =COUNTIFS('Commercial People'!$A$2:$A$101,"Crama Rasova",'Commercial People'!$C$2:$C$101,"Sales",'Commercial People'!$E$2:$E$101,K$2) -> 0 | L23: =COUNTIFS('Commercial People'!$A$2:$A$101,"Crama Rasova",'Commercial People'!$C$2:$C$101,"Sales",'Commercial People'!$E$2:$E$101,L$2) -> 0 | M23: =COUNTIFS('Commercial People'!$A$2:$A$101,"Crama Rasova",'Commercial People'!$C$2:$C$101,"Sales",'Commercial People'!$E$2:$E$101,M$2) -> 0 | N23: =COUNTIFS('Commercial People'!$A$2:$A$101,"Crama Rasova",'Commercial People'!$C$2:$C$101,"Sales",'Commercial People'!$E$2:$E$101,N$2) -> 0 | O23: =COUNTIFS('Commercial People'!$A$2:$A$101,"Crama Rasova",'Commercial People'!$C$2:$C$101,"Sales",'Commercial People'!$E$2:$E$101,O$2) -> 0 | P23: =COUNTIFS('Commercial People'!$A$2:$A$101,"Crama Rasova",'Commercial People'!$C$2:$C$101,"Sales",'Commercial People'!$E$2:$E$101,P$2) -> 0 | Q23: =COUNTIFS('Commercial People'!$A$2:$A$101,"Crama Rasova",'Commercial People'!$C$2:$C$101,"Sales",'Commercial People'!$E$2:$E$101,Q$2) -> 0 | ... T23: =COUNTIFS('Commercial People'!$A$2:$A$101,"Crama Rasova",'Commercial People'!$C$2:$C$101,"Sales",'Commercial People'!$E$2:$E$101,T$2) -> 0 | U23: =SUM(J23:T23) -> 0 | V23: =I23+U23 -> 0
A24: Liliac Winery | B24: =COUNTIFS('Commercial People'!$A$2:$A$101,"Liliac Winery",'Commercial People'!$C$2:$C$101,"Marketing",'Commercial People'!$E$2:$E$101,B$2) -> 0 | C24: =COUNTIFS('Commercial People'!$A$2:$A$101,"Liliac Winery",'Commercial People'!$C$2:$C$101,"Marketing",'Commercial People'!$E$2:$E$101,C$2) -> 0 | D24: =COUNTIFS('Commercial People'!$A$2:$A$101,"Liliac Winery",'Commercial People'!$C$2:$C$101,"Marketing",'Commercial People'!$E$2:$E$101,D$2) -> 0 | E24: =COUNTIFS('Commercial People'!$A$2:$A$101,"Liliac Winery",'Commercial People'!$C$2:$C$101,"Marketing",'Commercial People'!$E$2:$E$101,E$2) -> 0 | F24: =COUNTIFS('Commercial People'!$A$2:$A$101,"Liliac Winery",'Commercial People'!$C$2:$C$101,"Marketing",'Commercial People'!$E$2:$E$101,F$2) -> 0 | G24: =COUNTIFS('Commercial People'!$A$2:$A$101,"Liliac Winery",'Commercial People'!$C$2:$C$101,"Marketing",'Commercial People'!$E$2:$E$101,G$2) -> 0 | H24: =COUNTIFS('Commercial People'!$A$2:$A$101,"Liliac Winery",'Commercial People'!$C$2:$C$101,"Marketing",'Commercial People'!$E$2:$E$101,H$2) -> 0 | I24: =SUM(B24:H24) -> 0 | J24: =COUNTIFS('Commercial People'!$A$2:$A$101,"Liliac Winery",'Commercial People'!$C$2:$C$101,"Sales",'Commercial People'!$E$2:$E$101,J$2) -> 0 | K24: =COUNTIFS('Commercial People'!$A$2:$A$101,"Liliac Winery",'Commercial People'!$C$2:$C$101,"Sales",'Commercial People'!$E$2:$E$101,K$2) -> 0 | L24: =COUNTIFS('Commercial People'!$A$2:$A$101,"Liliac Winery",'Commercial People'!$C$2:$C$101,"Sales",'Commercial People'!$E$2:$E$101,L$2) -> 0 | M24: =COUNTIFS('Commercial People'!$A$2:$A$101,"Liliac Winery",'Commercial People'!$C$2:$C$101,"Sales",'Commercial People'!$E$2:$E$101,M$2) -> 0 | N24: =COUNTIFS('Commercial People'!$A$2:$A$101,"Liliac Winery",'Commercial People'!$C$2:$C$101,"Sales",'Commercial People'!$E$2:$E$101,N$2) -> 0 | O24: =COUNTIFS('Commercial People'!$A$2:$A$101,"Liliac Winery",'Commercial People'!$C$2:$C$101,"Sales",'Commercial People'!$E$2:$E$101,O$2) -> 0 | P24: =COUNTIFS('Commercial People'!$A$2:$A$101,"Liliac Winery",'Commercial People'!$C$2:$C$101,"Sales",'Commercial People'!$E$2:$E$101,P$2) -> 0 | Q24: =COUNTIFS('Commercial People'!$A$2:$A$101,"Liliac Winery",'Commercial People'!$C$2:$C$101,"Sales",'Commercial People'!$E$2:$E$101,Q$2) -> 0 | ... T24: =COUNTIFS('Commercial People'!$A$2:$A$101,"Liliac Winery",'Commercial People'!$C$2:$C$101,"Sales",'Commercial People'!$E$2:$E$101,T$2) -> 0 | U24: =SUM(J24:T24) -> 0 | V24: =I24+U24 -> 0
A25: Crama Oprișor | B25: =COUNTIFS('Commercial People'!$A$2:$A$101,"Crama Oprișor",'Commercial People'!$C$2:$C$101,"Marketing",'Commercial People'!$E$2:$E$101,B$2) -> 0 | C25: =COUNTIFS('Commercial People'!$A$2:$A$101,"Crama Oprișor",'Commercial People'!$C$2:$C$101,"Marketing",'Commercial People'!$E$2:$E$101,C$2) -> 0 | D25: =COUNTIFS('Commercial People'!$A$2:$A$101,"Crama Oprișor",'Commercial People'!$C$2:$C$101,"Marketing",'Commercial People'!$E$2:$E$101,D$2) -> 0 | E25: =COUNTIFS('Commercial People'!$A$2:$A$101,"Crama Oprișor",'Commercial People'!$C$2:$C$101,"Marketing",'Commercial People'!$E$2:$E$101,E$2) -> 0 | F25: =COUNTIFS('Commercial People'!$A$2:$A$101,"Crama Oprișor",'Commercial People'!$C$2:$C$101,"Marketing",'Commercial People'!$E$2:$E$101,F$2) -> 0 | G25: =COUNTIFS('Commercial People'!$A$2:$A$101,"Crama Oprișor",'Commercial People'!$C$2:$C$101,"Marketing",'Commercial People'!$E$2:$E$101,G$2) -> 0 | H25: =COUNTIFS('Commercial People'!$A$2:$A$101,"Crama Oprișor",'Commercial People'!$C$2:$C$101,"Marketing",'Commercial People'!$E$2:$E$101,H$2) -> 0 | I25: =SUM(B25:H25) -> 0 | J25: =COUNTIFS('Commercial People'!$A$2:$A$101,"Crama Oprișor",'Commercial People'!$C$2:$C$101,"Sales",'Commercial People'!$E$2:$E$101,J$2) -> 0 | K25: =COUNTIFS('Commercial People'!$A$2:$A$101,"Crama Oprișor",'Commercial People'!$C$2:$C$101,"Sales",'Commercial People'!$E$2:$E$101,K$2) -> 1 | L25: =COUNTIFS('Commercial People'!$A$2:$A$101,"Crama Oprișor",'Commercial People'!$C$2:$C$101,"Sales",'Commercial People'!$E$2:$E$101,L$2) -> 6 | M25: =COUNTIFS('Commercial People'!$A$2:$A$101,"Crama Oprișor",'Commercial People'!$C$2:$C$101,"Sales",'Commercial People'!$E$2:$E$101,M$2) -> 0 | N25: =COUNTIFS('Commercial People'!$A$2:$A$101,"Crama Oprișor",'Commercial People'!$C$2:$C$101,"Sales",'Commercial People'!$E$2:$E$101,N$2) -> 1 | O25: =COUNTIFS('Commercial People'!$A$2:$A$101,"Crama Oprișor",'Commercial People'!$C$2:$C$101,"Sales",'Commercial People'!$E$2:$E$101,O$2) -> 0 | P25: =COUNTIFS('Commercial People'!$A$2:$A$101,"Crama Oprișor",'Commercial People'!$C$2:$C$101,"Sales",'Commercial People'!$E$2:$E$101,P$2) -> 0 | Q25: =COUNTIFS('Commercial People'!$A$2:$A$101,"Crama Oprișor",'Commercial People'!$C$2:$C$101,"Sales",'Commercial People'!$E$2:$E$101,Q$2) -> 0 | ... T25: =COUNTIFS('Commercial People'!$A$2:$A$101,"Crama Oprișor",'Commercial People'!$C$2:$C$101,"Sales",'Commercial People'!$E$2:$E$101,T$2) -> 0 | U25: =SUM(J25:T25) -> 8 | V25: =I25+U25 -> 8
A26: Domeniile Săhăteni | B26: =COUNTIFS('Commercial People'!$A$2:$A$101,"Domeniile Săhăteni",'Commercial People'!$C$2:$C$101,"Marketing",'Commercial People'!$E$2:$E$101,B$2) -> 0 | C26: =COUNTIFS('Commercial People'!$A$2:$A$101,"Domeniile Săhăteni",'Commercial People'!$C$2:$C$101,"Marketing",'Commercial People'!$E$2:$E$101,C$2) -> 0 | D26: =COUNTIFS('Commercial People'!$A$2:$A$101,"Domeniile Săhăteni",'Commercial People'!$C$2:$C$101,"Marketing",'Commercial People'!$E$2:$E$101,D$2) -> 0 | E26: =COUNTIFS('Commercial People'!$A$2:$A$101,"Domeniile Săhăteni",'Commercial People'!$C$2:$C$101,"Marketing",'Commercial People'!$E$2:$E$101,E$2) -> 0 | F26: =COUNTIFS('Commercial People'!$A$2:$A$101,"Domeniile Săhăteni",'Commercial People'!$C$2:$C$101,"Marketing",'Commercial People'!$E$2:$E$101,F$2) -> 0 | G26: =COUNTIFS('Commercial People'!$A$2:$A$101,"Domeniile Săhăteni",'Commercial People'!$C$2:$C$101,"Marketing",'Commercial People'!$E$2:$E$101,G$2) -> 0 | H26: =COUNTIFS('Commercial People'!$A$2:$A$101,"Domeniile Săhăteni",'Commercial People'!$C$2:$C$101,"Marketing",'Commercial People'!$E$2:$E$101,H$2) -> 0 | I26: =SUM(B26:H26) -> 0 | J26: =COUNTIFS('Commercial People'!$A$2:$A$101,"Domeniile Săhăteni",'Commercial People'!$C$2:$C$101,"Sales",'Commercial People'!$E$2:$E$101,J$2) -> 0 | K26: =COUNTIFS('Commercial People'!$A$2:$A$101,"Domeniile Săhăteni",'Commercial People'!$C$2:$C$101,"Sales",'Commercial People'!$E$2:$E$101,K$2) -> 0 | L26: =COUNTIFS('Commercial People'!$A$2:$A$101,"Domeniile Săhăteni",'Commercial People'!$C$2:$C$101,"Sales",'Commercial People'!$E$2:$E$101,L$2) -> 0 | M26: =COUNTIFS('Commercial People'!$A$2:$A$101,"Domeniile Săhăteni",'Commercial People'!$C$2:$C$101,"Sales",'Commercial People'!$E$2:$E$101,M$2) -> 0 | N26: =COUNTIFS('Commercial People'!$A$2:$A$101,"Domeniile Săhăteni",'Commercial People'!$C$2:$C$101,"Sales",'Commercial People'!$E$2:$E$101,N$2) -> 0 | O26: =COUNTIFS('Commercial People'!$A$2:$A$101,"Domeniile Săhăteni",'Commercial People'!$C$2:$C$101,"Sales",'Commercial People'!$E$2:$E$101,O$2) -> 0 | P26: =COUNTIFS('Commercial People'!$A$2:$A$101,"Domeniile Săhăteni",'Commercial People'!$C$2:$C$101,"Sales",'Commercial People'!$E$2:$E$101,P$2) -> 0 | Q26: =COUNTIFS('Commercial People'!$A$2:$A$101,"Domeniile Săhăteni",'Commercial People'!$C$2:$C$101,"Sales",'Commercial People'!$E$2:$E$101,Q$2) -> 0 | ... T26: =COUNTIFS('Commercial People'!$A$2:$A$101,"Domeniile Săhăteni",'Commercial People'!$C$2:$C$101,"Sales",'Commercial People'!$E$2:$E$101,T$2) -> 0 | U26: =SUM(J26:T26) -> 0 | V26: =I26+U26 -> 0
A27: Crama 1000 de Chipuri | B27: =COUNTIFS('Commercial People'!$A$2:$A$101,"Crama 1000 de Chipuri",'Commercial People'!$C$2:$C$101,"Marketing",'Commercial People'!$E$2:$E$101,B$2) -> 0 | C27: =COUNTIFS('Commercial People'!$A$2:$A$101,"Crama 1000 de Chipuri",'Commercial People'!$C$2:$C$101,"Marketing",'Commercial People'!$E$2:$E$101,C$2) -> 0 | D27: =COUNTIFS('Commercial People'!$A$2:$A$101,"Crama 1000 de Chipuri",'Commercial People'!$C$2:$C$101,"Marketing",'Commercial People'!$E$2:$E$101,D$2) -> 0 | E27: =COUNTIFS('Commercial People'!$A$2:$A$101,"Crama 1000 de Chipuri",'Commercial People'!$C$2:$C$101,"Marketing",'Commercial People'!$E$2:$E$101,E$2) -> 0 | F27: =COUNTIFS('Commercial People'!$A$2:$A$101,"Crama 1000 de Chipuri",'Commercial People'!$C$2:$C$101,"Marketing",'Commercial People'!$E$2:$E$101,F$2) -> 0 | G27: =COUNTIFS('Commercial People'!$A$2:$A$101,"Crama 1000 de Chipuri",'Commercial People'!$C$2:$C$101,"Marketing",'Commercial People'!$E$2:$E$101,G$2) -> 0 | H27: =COUNTIFS('Commercial People'!$A$2:$A$101,"Crama 1000 de Chipuri",'Commercial People'!$C$2:$C$101,"Marketing",'Commercial People'!$E$2:$E$101,H$2) -> 0 | I27: =SUM(B27:H27) -> 0 | J27: =COUNTIFS('Commercial People'!$A$2:$A$101,"Crama 1000 de Chipuri",'Commercial People'!$C$2:$C$101,"Sales",'Commercial People'!$E$2:$E$101,J$2) -> 0 | K27: =COUNTIFS('Commercial People'!$A$2:$A$101,"Crama 1000 de Chipuri",'Commercial People'!$C$2:$C$101,"Sales",'Commercial People'!$E$2:$E$101,K$2) -> 0 | L27: =COUNTIFS('Commercial People'!$A$2:$A$101,"Crama 1000 de Chipuri",'Commercial People'!$C$2:$C$101,"Sales",'Commercial People'!$E$2:$E$101,L$2) -> 0 | M27: =COUNTIFS('Commercial People'!$A$2:$A$101,"Crama 1000 de Chipuri",'Commercial People'!$C$2:$C$101,"Sales",'Commercial People'!$E$2:$E$101,M$2) -> 0 | N27: =COUNTIFS('Commercial People'!$A$2:$A$101,"Crama 1000 de Chipuri",'Commercial People'!$C$2:$C$101,"Sales",'Commercial People'!$E$2:$E$101,N$2) -> 0 | O27: =COUNTIFS('Commercial People'!$A$2:$A$101,"Crama 1000 de Chipuri",'Commercial People'!$C$2:$C$101,"Sales",'Commercial People'!$E$2:$E$101,O$2) -> 0 | P27: =COUNTIFS('Commercial People'!$A$2:$A$101,"Crama 1000 de Chipuri",'Commercial People'!$C$2:$C$101,"Sales",'Commercial People'!$E$2:$E$101,P$2) -> 0 | Q27: =COUNTIFS('Commercial People'!$A$2:$A$101,"Crama 1000 de Chipuri",'Commercial People'!$C$2:$C$101,"Sales",'Commercial People'!$E$2:$E$101,Q$2) -> 0 | ... T27: =COUNTIFS('Commercial People'!$A$2:$A$101,"Crama 1000 de Chipuri",'Commercial People'!$C$2:$C$101,"Sales",'Commercial People'!$E$2:$E$101,T$2) -> 0 | U27: =SUM(J27:T27) -> 0 | V27: =I27+U27 -> 0
A28: Casa de Vinuri Negrini | B28: =COUNTIFS('Commercial People'!$A$2:$A$101,"Casa de Vinuri Negrini",'Commercial People'!$C$2:$C$101,"Marketing",'Commercial People'!$E$2:$E$101,B$2) -> 0 | C28: =COUNTIFS('Commercial People'!$A$2:$A$101,"Casa de Vinuri Negrini",'Commercial People'!$C$2:$C$101,"Marketing",'Commercial People'!$E$2:$E$101,C$2) -> 0 | D28: =COUNTIFS('Commercial People'!$A$2:$A$101,"Casa de Vinuri Negrini",'Commercial People'!$C$2:$C$101,"Marketing",'Commercial People'!$E$2:$E$101,D$2) -> 0 | E28: =COUNTIFS('Commercial People'!$A$2:$A$101,"Casa de Vinuri Negrini",'Commercial People'!$C$2:$C$101,"Marketing",'Commercial People'!$E$2:$E$101,E$2) -> 0 | F28: =COUNTIFS('Commercial People'!$A$2:$A$101,"Casa de Vinuri Negrini",'Commercial People'!$C$2:$C$101,"Marketing",'Commercial People'!$E$2:$E$101,F$2) -> 0 | G28: =COUNTIFS('Commercial People'!$A$2:$A$101,"Casa de Vinuri Negrini",'Commercial People'!$C$2:$C$101,"Marketing",'Commercial People'!$E$2:$E$101,G$2) -> 0 | H28: =COUNTIFS('Commercial People'!$A$2:$A$101,"Casa de Vinuri Negrini",'Commercial People'!$C$2:$C$101,"Marketing",'Commercial People'!$E$2:$E$101,H$2) -> 0 | I28: =SUM(B28:H28) -> 0 | J28: =COUNTIFS('Commercial People'!$A$2:$A$101,"Casa de Vinuri Negrini",'Commercial People'!$C$2:$C$101,"Sales",'Commercial People'!$E$2:$E$101,J$2) -> 0 | K28: =COUNTIFS('Commercial People'!$A$2:$A$101,"Casa de Vinuri Negrini",'Commercial People'!$C$2:$C$101,"Sales",'Commercial People'!$E$2:$E$101,K$2) -> 0 | L28: =COUNTIFS('Commercial People'!$A$2:$A$101,"Casa de Vinuri Negrini",'Commercial People'!$C$2:$C$101,"Sales",'Commercial People'!$E$2:$E$101,L$2) -> 0 | M28: =COUNTIFS('Commercial People'!$A$2:$A$101,"Casa de Vinuri Negrini",'Commercial People'!$C$2:$C$101,"Sales",'Commercial People'!$E$2:$E$101,M$2) -> 0 | N28: =COUNTIFS('Commercial People'!$A$2:$A$101,"Casa de Vinuri Negrini",'Commercial People'!$C$2:$C$101,"Sales",'Commercial People'!$E$2:$E$101,N$2) -> 0 | O28: =COUNTIFS('Commercial People'!$A$2:$A$101,"Casa de Vinuri Negrini",'Commercial People'!$C$2:$C$101,"Sales",'Commercial People'!$E$2:$E$101,O$2) -> 0 | P28: =COUNTIFS('Commercial People'!$A$2:$A$101,"Casa de Vinuri Negrini",'Commercial People'!$C$2:$C$101,"Sales",'Commercial People'!$E$2:$E$101,P$2) -> 0 | Q28: =COUNTIFS('Commercial People'!$A$2:$A$101,"Casa de Vinuri Negrini",'Commercial People'!$C$2:$C$101,"Sales",'Commercial People'!$E$2:$E$101,Q$2) -> 0 | ... T28: =COUNTIFS('Commercial People'!$A$2:$A$101,"Casa de Vinuri Negrini",'Commercial People'!$C$2:$C$101,"Sales",'Commercial People'!$E$2:$E$101,T$2) -> 0 | U28: =SUM(J28:T28) -> 0 | V28: =I28+U28 -> 0
A29: Petro Vaselo | B29: =COUNTIFS('Commercial People'!$A$2:$A$101,"Petro Vaselo",'Commercial People'!$C$2:$C$101,"Marketing",'Commercial People'!$E$2:$E$101,B$2) -> 0 | C29: =COUNTIFS('Commercial People'!$A$2:$A$101,"Petro Vaselo",'Commercial People'!$C$2:$C$101,"Marketing",'Commercial People'!$E$2:$E$101,C$2) -> 0 | D29: =COUNTIFS('Commercial People'!$A$2:$A$101,"Petro Vaselo",'Commercial People'!$C$2:$C$101,"Marketing",'Commercial People'!$E$2:$E$101,D$2) -> 0 | E29: =COUNTIFS('Commercial People'!$A$2:$A$101,"Petro Vaselo",'Commercial People'!$C$2:$C$101,"Marketing",'Commercial People'!$E$2:$E$101,E$2) -> 0 | F29: =COUNTIFS('Commercial People'!$A$2:$A$101,"Petro Vaselo",'Commercial People'!$C$2:$C$101,"Marketing",'Commercial People'!$E$2:$E$101,F$2) -> 0 | G29: =COUNTIFS('Commercial People'!$A$2:$A$101,"Petro Vaselo",'Commercial People'!$C$2:$C$101,"Marketing",'Commercial People'!$E$2:$E$101,G$2) -> 0 | H29: =COUNTIFS('Commercial People'!$A$2:$A$101,"Petro Vaselo",'Commercial People'!$C$2:$C$101,"Marketing",'Commercial People'!$E$2:$E$101,H$2) -> 0 | I29: =SUM(B29:H29) -> 0 | J29: =COUNTIFS('Commercial People'!$A$2:$A$101,"Petro Vaselo",'Commercial People'!$C$2:$C$101,"Sales",'Commercial People'!$E$2:$E$101,J$2) -> 0 | K29: =COUNTIFS('Commercial People'!$A$2:$A$101,"Petro Vaselo",'Commercial People'!$C$2:$C$101,"Sales",'Commercial People'!$E$2:$E$101,K$2) -> 0 | L29: =COUNTIFS('Commercial People'!$A$2:$A$101,"Petro Vaselo",'Commercial People'!$C$2:$C$101,"Sales",'Commercial People'!$E$2:$E$101,L$2) -> 0 | M29: =COUNTIFS('Commercial People'!$A$2:$A$101,"Petro Vaselo",'Commercial People'!$C$2:$C$101,"Sales",'Commercial People'!$E$2:$E$101,M$2) -> 0 | N29: =COUNTIFS('Commercial People'!$A$2:$A$101,"Petro Vaselo",'Commercial People'!$C$2:$C$101,"Sales",'Commercial People'!$E$2:$E$101,N$2) -> 0 | O29: =COUNTIFS('Commercial People'!$A$2:$A$101,"Petro Vaselo",'Commercial People'!$C$2:$C$101,"Sales",'Commercial People'!$E$2:$E$101,O$2) -> 0 | P29: =COUNTIFS('Commercial People'!$A$2:$A$101,"Petro Vaselo",'Commercial People'!$C$2:$C$101,"Sales",'Commercial People'!$E$2:$E$101,P$2) -> 0 | Q29: =COUNTIFS('Commercial People'!$A$2:$A$101,"Petro Vaselo",'Commercial People'!$C$2:$C$101,"Sales",'Commercial People'!$E$2:$E$101,Q$2) -> 0 | ... T29: =COUNTIFS('Commercial People'!$A$2:$A$101,"Petro Vaselo",'Commercial People'!$C$2:$C$101,"Sales",'Commercial People'!$E$2:$E$101,T$2) -> 0 | U29: =SUM(J29:T29) -> 0 | V29: =I29+U29 -> 0
A30: Carastelec Winery | B30: =COUNTIFS('Commercial People'!$A$2:$A$101,"Carastelec Winery",'Commercial People'!$C$2:$C$101,"Marketing",'Commercial People'!$E$2:$E$101,B$2) -> 0 | C30: =COUNTIFS('Commercial People'!$A$2:$A$101,"Carastelec Winery",'Commercial People'!$C$2:$C$101,"Marketing",'Commercial People'!$E$2:$E$101,C$2) -> 0 | D30: =COUNTIFS('Commercial People'!$A$2:$A$101,"Carastelec Winery",'Commercial People'!$C$2:$C$101,"Marketing",'Commercial People'!$E$2:$E$101,D$2) -> 0 | E30: =COUNTIFS('Commercial People'!$A$2:$A$101,"Carastelec Winery",'Commercial People'!$C$2:$C$101,"Marketing",'Commercial People'!$E$2:$E$101,E$2) -> 0 | F30: =COUNTIFS('Commercial People'!$A$2:$A$101,"Carastelec Winery",'Commercial People'!$C$2:$C$101,"Marketing",'Commercial People'!$E$2:$E$101,F$2) -> 0 | G30: =COUNTIFS('Commercial People'!$A$2:$A$101,"Carastelec Winery",'Commercial People'!$C$2:$C$101,"Marketing",'Commercial People'!$E$2:$E$101,G$2) -> 0 | H30: =COUNTIFS('Commercial People'!$A$2:$A$101,"Carastelec Winery",'Commercial People'!$C$2:$C$101,"Marketing",'Commercial People'!$E$2:$E$101,H$2) -> 0 | I30: =SUM(B30:H30) -> 0 | J30: =COUNTIFS('Commercial People'!$A$2:$A$101,"Carastelec Winery",'Commercial People'!$C$2:$C$101,"Sales",'Commercial People'!$E$2:$E$101,J$2) -> 0 | K30: =COUNTIFS('Commercial People'!$A$2:$A$101,"Carastelec Winery",'Commercial People'!$C$2:$C$101,"Sales",'Commercial People'!$E$2:$E$101,K$2) -> 0 | L30: =COUNTIFS('Commercial People'!$A$2:$A$101,"Carastelec Winery",'Commercial People'!$C$2:$C$101,"Sales",'Commercial People'!$E$2:$E$101,L$2) -> 0 | M30: =COUNTIFS('Commercial People'!$A$2:$A$101,"Carastelec Winery",'Commercial People'!$C$2:$C$101,"Sales",'Commercial People'!$E$2:$E$101,M$2) -> 0 | N30: =COUNTIFS('Commercial People'!$A$2:$A$101,"Carastelec Winery",'Commercial People'!$C$2:$C$101,"Sales",'Commercial People'!$E$2:$E$101,N$2) -> 0 | O30: =COUNTIFS('Commercial People'!$A$2:$A$101,"Carastelec Winery",'Commercial People'!$C$2:$C$101,"Sales",'Commercial People'!$E$2:$E$101,O$2) -> 0 | P30: =COUNTIFS('Commercial People'!$A$2:$A$101,"Carastelec Winery",'Commercial People'!$C$2:$C$101,"Sales",'Commercial People'!$E$2:$E$101,P$2) -> 0 | Q30: =COUNTIFS('Commercial People'!$A$2:$A$101,"Carastelec Winery",'Commercial People'!$C$2:$C$101,"Sales",'Commercial People'!$E$2:$E$101,Q$2) -> 0 | ... T30: =COUNTIFS('Commercial People'!$A$2:$A$101,"Carastelec Winery",'Commercial People'!$C$2:$C$101,"Sales",'Commercial People'!$E$2:$E$101,T$2) -> 0 | U30: =SUM(J30:T30) -> 0 | V30: =I30+U30 -> 0
A31: Domeniile Davidescu | B31: =COUNTIFS('Commercial People'!$A$2:$A$101,"Domeniile Davidescu",'Commercial People'!$C$2:$C$101,"Marketing",'Commercial People'!$E$2:$E$101,B$2) -> 0 | C31: =COUNTIFS('Commercial People'!$A$2:$A$101,"Domeniile Davidescu",'Commercial People'!$C$2:$C$101,"Marketing",'Commercial People'!$E$2:$E$101,C$2) -> 0 | D31: =COUNTIFS('Commercial People'!$A$2:$A$101,"Domeniile Davidescu",'Commercial People'!$C$2:$C$101,"Marketing",'Commercial People'!$E$2:$E$101,D$2) -> 0 | E31: =COUNTIFS('Commercial People'!$A$2:$A$101,"Domeniile Davidescu",'Commercial People'!$C$2:$C$101,"Marketing",'Commercial People'!$E$2:$E$101,E$2) -> 0 | F31: =COUNTIFS('Commercial People'!$A$2:$A$101,"Domeniile Davidescu",'Commercial People'!$C$2:$C$101,"Marketing",'Commercial People'!$E$2:$E$101,F$2) -> 0 | G31: =COUNTIFS('Commercial People'!$A$2:$A$101,"Domeniile Davidescu",'Commercial People'!$C$2:$C$101,"Marketing",'Commercial People'!$E$2:$E$101,G$2) -> 0 | H31: =COUNTIFS('Commercial People'!$A$2:$A$101,"Domeniile Davidescu",'Commercial People'!$C$2:$C$101,"Marketing",'Commercial People'!$E$2:$E$101,H$2) -> 0 | I31: =SUM(B31:H31) -> 0 | J31: =COUNTIFS('Commercial People'!$A$2:$A$101,"Domeniile Davidescu",'Commercial People'!$C$2:$C$101,"Sales",'Commercial People'!$E$2:$E$101,J$2) -> 0 | K31: =COUNTIFS('Commercial People'!$A$2:$A$101,"Domeniile Davidescu",'Commercial People'!$C$2:$C$101,"Sales",'Commercial People'!$E$2:$E$101,K$2) -> 0 | L31: =COUNTIFS('Commercial People'!$A$2:$A$101,"Domeniile Davidescu",'Commercial People'!$C$2:$C$101,"Sales",'Commercial People'!$E$2:$E$101,L$2) -> 0 | M31: =COUNTIFS('Commercial People'!$A$2:$A$101,"Domeniile Davidescu",'Commercial People'!$C$2:$C$101,"Sales",'Commercial People'!$E$2:$E$101,M$2) -> 0 | N31: =COUNTIFS('Commercial People'!$A$2:$A$101,"Domeniile Davidescu",'Commercial People'!$C$2:$C$101,"Sales",'Commercial People'!$E$2:$E$101,N$2) -> 0 | O31: =COUNTIFS('Commercial People'!$A$2:$A$101,"Domeniile Davidescu",'Commercial People'!$C$2:$C$101,"Sales",'Commercial People'!$E$2:$E$101,O$2) -> 0 | P31: =COUNTIFS('Commercial People'!$A$2:$A$101,"Domeniile Davidescu",'Commercial People'!$C$2:$C$101,"Sales",'Commercial People'!$E$2:$E$101,P$2) -> 0 | Q31: =COUNTIFS('Commercial People'!$A$2:$A$101,"Domeniile Davidescu",'Commercial People'!$C$2:$C$101,"Sales",'Commercial People'!$E$2:$E$101,Q$2) -> 0 | ... T31: =COUNTIFS('Commercial People'!$A$2:$A$101,"Domeniile Davidescu",'Commercial People'!$C$2:$C$101,"Sales",'Commercial People'!$E$2:$E$101,T$2) -> 0 | U31: =SUM(J31:T31) -> 0 | V31: =I31+U31 -> 0
A32: SERVE Ceptura | B32: =COUNTIFS('Commercial People'!$A$2:$A$101,"SERVE Ceptura",'Commercial People'!$C$2:$C$101,"Marketing",'Commercial People'!$E$2:$E$101,B$2) -> 0 | C32: =COUNTIFS('Commercial People'!$A$2:$A$101,"SERVE Ceptura",'Commercial People'!$C$2:$C$101,"Marketing",'Commercial People'!$E$2:$E$101,C$2) -> 0 | D32: =COUNTIFS('Commercial People'!$A$2:$A$101,"SERVE Ceptura",'Commercial People'!$C$2:$C$101,"Marketing",'Commercial People'!$E$2:$E$101,D$2) -> 0 | E32: =COUNTIFS('Commercial People'!$A$2:$A$101,"SERVE Ceptura",'Commercial People'!$C$2:$C$101,"Marketing",'Commercial People'!$E$2:$E$101,E$2) -> 0 | F32: =COUNTIFS('Commercial People'!$A$2:$A$101,"SERVE Ceptura",'Commercial People'!$C$2:$C$101,"Marketing",'Commercial People'!$E$2:$E$101,F$2) -> 0 | G32: =COUNTIFS('Commercial People'!$A$2:$A$101,"SERVE Ceptura",'Commercial People'!$C$2:$C$101,"Marketing",'Commercial People'!$E$2:$E$101,G$2) -> 0 | H32: =COUNTIFS('Commercial People'!$A$2:$A$101,"SERVE Ceptura",'Commercial People'!$C$2:$C$101,"Marketing",'Commercial People'!$E$2:$E$101,H$2) -> 0 | I32: =SUM(B32:H32) -> 0 | J32: =COUNTIFS('Commercial People'!$A$2:$A$101,"SERVE Ceptura",'Commercial People'!$C$2:$C$101,"Sales",'Commercial People'!$E$2:$E$101,J$2) -> 0 | K32: =COUNTIFS('Commercial People'!$A$2:$A$101,"SERVE Ceptura",'Commercial People'!$C$2:$C$101,"Sales",'Commercial People'!$E$2:$E$101,K$2) -> 0 | L32: =COUNTIFS('Commercial People'!$A$2:$A$101,"SERVE Ceptura",'Commercial People'!$C$2:$C$101,"Sales",'Commercial People'!$E$2:$E$101,L$2) -> 0 | M32: =COUNTIFS('Commercial People'!$A$2:$A$101,"SERVE Ceptura",'Commercial People'!$C$2:$C$101,"Sales",'Commercial People'!$E$2:$E$101,M$2) -> 0 | N32: =COUNTIFS('Commercial People'!$A$2:$A$101,"SERVE Ceptura",'Commercial People'!$C$2:$C$101,"Sales",'Commercial People'!$E$2:$E$101,N$2) -> 0 | O32: =COUNTIFS('Commercial People'!$A$2:$A$101,"SERVE Ceptura",'Commercial People'!$C$2:$C$101,"Sales",'Commercial People'!$E$2:$E$101,O$2) -> 0 | P32: =COUNTIFS('Commercial People'!$A$2:$A$101,"SERVE Ceptura",'Commercial People'!$C$2:$C$101,"Sales",'Commercial People'!$E$2:$E$101,P$2) -> 0 | Q32: =COUNTIFS('Commercial People'!$A$2:$A$101,"SERVE Ceptura",'Commercial People'!$C$2:$C$101,"Sales",'Commercial People'!$E$2:$E$101,Q$2) -> 0 | ... T32: =COUNTIFS('Commercial People'!$A$2:$A$101,"SERVE Ceptura",'Commercial People'!$C$2:$C$101,"Sales",'Commercial People'!$E$2:$E$101,T$2) -> 0 | U32: =SUM(J32:T32) -> 0 | V32: =I32+U32 -> 0
A33: Avincis Vinuri | B33: =COUNTIFS('Commercial People'!$A$2:$A$101,"Avincis Vinuri",'Commercial People'!$C$2:$C$101,"Marketing",'Commercial People'!$E$2:$E$101,B$2) -> 0 | C33: =COUNTIFS('Commercial People'!$A$2:$A$101,"Avincis Vinuri",'Commercial People'!$C$2:$C$101,"Marketing",'Commercial People'!$E$2:$E$101,C$2) -> 0 | D33: =COUNTIFS('Commercial People'!$A$2:$A$101,"Avincis Vinuri",'Commercial People'!$C$2:$C$101,"Marketing",'Commercial People'!$E$2:$E$101,D$2) -> 0 | E33: =COUNTIFS('Commercial People'!$A$2:$A$101,"Avincis Vinuri",'Commercial People'!$C$2:$C$101,"Marketing",'Commercial People'!$E$2:$E$101,E$2) -> 0 | F33: =COUNTIFS('Commercial People'!$A$2:$A$101,"Avincis Vinuri",'Commercial People'!$C$2:$C$101,"Marketing",'Commercial People'!$E$2:$E$101,F$2) -> 1 | G33: =COUNTIFS('Commercial People'!$A$2:$A$101,"Avincis Vinuri",'Commercial People'!$C$2:$C$101,"Marketing",'Commercial People'!$E$2:$E$101,G$2) -> 0 | H33: =COUNTIFS('Commercial People'!$A$2:$A$101,"Avincis Vinuri",'Commercial People'!$C$2:$C$101,"Marketing",'Commercial People'!$E$2:$E$101,H$2) -> 0 | I33: =SUM(B33:H33) -> 1 | J33: =COUNTIFS('Commercial People'!$A$2:$A$101,"Avincis Vinuri",'Commercial People'!$C$2:$C$101,"Sales",'Commercial People'!$E$2:$E$101,J$2) -> 0 | K33: =COUNTIFS('Commercial People'!$A$2:$A$101,"Avincis Vinuri",'Commercial People'!$C$2:$C$101,"Sales",'Commercial People'!$E$2:$E$101,K$2) -> 0 | L33: =COUNTIFS('Commercial People'!$A$2:$A$101,"Avincis Vinuri",'Commercial People'!$C$2:$C$101,"Sales",'Commercial People'!$E$2:$E$101,L$2) -> 0 | M33: =COUNTIFS('Commercial People'!$A$2:$A$101,"Avincis Vinuri",'Commercial People'!$C$2:$C$101,"Sales",'Commercial People'!$E$2:$E$101,M$2) -> 0 | N33: =COUNTIFS('Commercial People'!$A$2:$A$101,"Avincis Vinuri",'Commercial People'!$C$2:$C$101,"Sales",'Commercial People'!$E$2:$E$101,N$2) -> 0 | O33: =COUNTIFS('Commercial People'!$A$2:$A$101,"Avincis Vinuri",'Commercial People'!$C$2:$C$101,"Sales",'Commercial People'!$E$2:$E$101,O$2) -> 0 | P33: =COUNTIFS('Commercial People'!$A$2:$A$101,"Avincis Vinuri",'Commercial People'!$C$2:$C$101,"Sales",'Commercial People'!$E$2:$E$101,P$2) -> 0 | Q33: =COUNTIFS('Commercial People'!$A$2:$A$101,"Avincis Vinuri",'Commercial People'!$C$2:$C$101,"Sales",'Commercial People'!$E$2:$E$101,Q$2) -> 0 | ... T33: =COUNTIFS('Commercial People'!$A$2:$A$101,"Avincis Vinuri",'Commercial People'!$C$2:$C$101,"Sales",'Commercial People'!$E$2:$E$101,T$2) -> 0 | U33: =SUM(J33:T33) -> 0 | V33: =I33+U33 -> 1
A34: Domeniile Panciu | B34: =COUNTIFS('Commercial People'!$A$2:$A$101,"Domeniile Panciu",'Commercial People'!$C$2:$C$101,"Marketing",'Commercial People'!$E$2:$E$101,B$2) -> 0 | C34: =COUNTIFS('Commercial People'!$A$2:$A$101,"Domeniile Panciu",'Commercial People'!$C$2:$C$101,"Marketing",'Commercial People'!$E$2:$E$101,C$2) -> 0 | D34: =COUNTIFS('Commercial People'!$A$2:$A$101,"Domeniile Panciu",'Commercial People'!$C$2:$C$101,"Marketing",'Commercial People'!$E$2:$E$101,D$2) -> 0 | E34: =COUNTIFS('Commercial People'!$A$2:$A$101,"Domeniile Panciu",'Commercial People'!$C$2:$C$101,"Marketing",'Commercial People'!$E$2:$E$101,E$2) -> 0 | F34: =COUNTIFS('Commercial People'!$A$2:$A$101,"Domeniile Panciu",'Commercial People'!$C$2:$C$101,"Marketing",'Commercial People'!$E$2:$E$101,F$2) -> 0 | G34: =COUNTIFS('Commercial People'!$A$2:$A$101,"Domeniile Panciu",'Commercial People'!$C$2:$C$101,"Marketing",'Commercial People'!$E$2:$E$101,G$2) -> 0 | H34: =COUNTIFS('Commercial People'!$A$2:$A$101,"Domeniile Panciu",'Commercial People'!$C$2:$C$101,"Marketing",'Commercial People'!$E$2:$E$101,H$2) -> 0 | I34: =SUM(B34:H34) -> 0 | J34: =COUNTIFS('Commercial People'!$A$2:$A$101,"Domeniile Panciu",'Commercial People'!$C$2:$C$101,"Sales",'Commercial People'!$E$2:$E$101,J$2) -> 1 | K34: =COUNTIFS('Commercial People'!$A$2:$A$101,"Domeniile Panciu",'Commercial People'!$C$2:$C$101,"Sales",'Commercial People'!$E$2:$E$101,K$2) -> 0 | L34: =COUNTIFS('Commercial People'!$A$2:$A$101,"Domeniile Panciu",'Commercial People'!$C$2:$C$101,"Sales",'Commercial People'!$E$2:$E$101,L$2) -> 0 | M34: =COUNTIFS('Commercial People'!$A$2:$A$101,"Domeniile Panciu",'Commercial People'!$C$2:$C$101,"Sales",'Commercial People'!$E$2:$E$101,M$2) -> 0 | N34: =COUNTIFS('Commercial People'!$A$2:$A$101,"Domeniile Panciu",'Commercial People'!$C$2:$C$101,"Sales",'Commercial People'!$E$2:$E$101,N$2) -> 0 | O34: =COUNTIFS('Commercial People'!$A$2:$A$101,"Domeniile Panciu",'Commercial People'!$C$2:$C$101,"Sales",'Commercial People'!$E$2:$E$101,O$2) -> 0 | P34: =COUNTIFS('Commercial People'!$A$2:$A$101,"Domeniile Panciu",'Commercial People'!$C$2:$C$101,"Sales",'Commercial People'!$E$2:$E$101,P$2) -> 0 | Q34: =COUNTIFS('Commercial People'!$A$2:$A$101,"Domeniile Panciu",'Commercial People'!$C$2:$C$101,"Sales",'Commercial People'!$E$2:$E$101,Q$2) -> 0 | ... T34: =COUNTIFS('Commercial People'!$A$2:$A$101,"Domeniile Panciu",'Commercial People'!$C$2:$C$101,"Sales",'Commercial People'!$E$2:$E$101,T$2) -> 0 | U34: =SUM(J34:T34) -> 1 | V34: =I34+U34 -> 1
A35: Fautor | B35: =COUNTIFS('Commercial People'!$A$2:$A$101,"Fautor",'Commercial People'!$C$2:$C$101,"Marketing",'Commercial People'!$E$2:$E$101,B$2) -> 0 | C35: =COUNTIFS('Commercial People'!$A$2:$A$101,"Fautor",'Commercial People'!$C$2:$C$101,"Marketing",'Commercial People'!$E$2:$E$101,C$2) -> 0 | D35: =COUNTIFS('Commercial People'!$A$2:$A$101,"Fautor",'Commercial People'!$C$2:$C$101,"Marketing",'Commercial People'!$E$2:$E$101,D$2) -> 0 | E35: =COUNTIFS('Commercial People'!$A$2:$A$101,"Fautor",'Commercial People'!$C$2:$C$101,"Marketing",'Commercial People'!$E$2:$E$101,E$2) -> 0 | F35: =COUNTIFS('Commercial People'!$A$2:$A$101,"Fautor",'Commercial People'!$C$2:$C$101,"Marketing",'Commercial People'!$E$2:$E$101,F$2) -> 0 | G35: =COUNTIFS('Commercial People'!$A$2:$A$101,"Fautor",'Commercial People'!$C$2:$C$101,"Marketing",'Commercial People'!$E$2:$E$101,G$2) -> 0 | H35: =COUNTIFS('Commercial People'!$A$2:$A$101,"Fautor",'Commercial People'!$C$2:$C$101,"Marketing",'Commercial People'!$E$2:$E$101,H$2) -> 0 | I35: =SUM(B35:H35) -> 0 | J35: =COUNTIFS('Commercial People'!$A$2:$A$101,"Fautor",'Commercial People'!$C$2:$C$101,"Sales",'Commercial People'!$E$2:$E$101,J$2) -> 1 | K35: =COUNTIFS('Commercial People'!$A$2:$A$101,"Fautor",'Commercial People'!$C$2:$C$101,"Sales",'Commercial People'!$E$2:$E$101,K$2) -> 0 | L35: =COUNTIFS('Commercial People'!$A$2:$A$101,"Fautor",'Commercial People'!$C$2:$C$101,"Sales",'Commercial People'!$E$2:$E$101,L$2) -> 0 | M35: =COUNTIFS('Commercial People'!$A$2:$A$101,"Fautor",'Commercial People'!$C$2:$C$101,"Sales",'Commercial People'!$E$2:$E$101,M$2) -> 0 | N35: =COUNTIFS('Commercial People'!$A$2:$A$101,"Fautor",'Commercial People'!$C$2:$C$101,"Sales",'Commercial People'!$E$2:$E$101,N$2) -> 0 | O35: =COUNTIFS('Commercial People'!$A$2:$A$101,"Fautor",'Commercial People'!$C$2:$C$101,"Sales",'Commercial People'!$E$2:$E$101,O$2) -> 0 | P35: =COUNTIFS('Commercial People'!$A$2:$A$101,"Fautor",'Commercial People'!$C$2:$C$101,"Sales",'Commercial People'!$E$2:$E$101,P$2) -> 0 | Q35: =COUNTIFS('Commercial People'!$A$2:$A$101,"Fautor",'Commercial People'!$C$2:$C$101,"Sales",'Commercial People'!$E$2:$E$101,Q$2) -> 0 | ... T35: =COUNTIFS('Commercial People'!$A$2:$A$101,"Fautor",'Commercial People'!$C$2:$C$101,"Sales",'Commercial People'!$E$2:$E$101,T$2) -> 0 | U35: =SUM(J35:T35) -> 1 | V35: =I35+U35 -> 1
A36: Company total | B36: =SUM(B3:B35) -> 13 | C36: =SUM(C3:C35) -> 9 | D36: =SUM(D3:D35) -> 6 | E36: =SUM(E3:E35) -> 2 | F36: =SUM(F3:F35) -> 2 | G36: =SUM(G3:G35) -> 2 | H36: =SUM(H3:H35) -> 2 | I36: =SUM(I3:I35) -> 36 | ... V36: =SUM(V3:V35) -> 103
A38: Counts are formula-driven from the Commercial People sheet. Wineries added on 2026-08-21 are researched from public sources only — company team pages, trade press and job boards — because the LinkedIn capture behind the original rows could not be reproduced. Where no marketing or sales person is named publicly, the row reads zero: that means no public evidence was found, not that the function is unstaffed.

Sheet Takeaways_Insights
A1: Winery | B1: LinkedIn associated members | C1: Employee source / freshness | D1: Recent public roles found | E1: Hiring takeaway | F1: Campaign pattern | G1: Representative campaigns | H1: Campaign source(s) | I1: Notes / confidence
A2: Jidvei | B2: 116 | C2: Workbook LinkedIn capture: 2026-08-18 | D2: =COUNTIFS('Open Positions'!$A$2:$A$62,A2,'Open Positions'!$C$2:$C$62,"Vacancy")+COUNTIFS('Open Positions'!$A$2:$A$62,A2,'Open Positions'!$C$2:$C$62,"Paid internship / early career") -> 3 | E2: Three recent LinkedIn roles found; no dedicated vacancy page located on the official website. | F2: Romanian identity, culture, vineyard experiences and prestige partnerships | G2: Weinland Trails; Strugurele de Aur; Spirit launch; cultural diplomacy; Olympics; seasonal must | H2: https://www.jidvei.ro/ | I2: Member count is LinkedIn-associated, not payroll; campaign pattern is strongly evidenced.
A3: Beciul Domnesc | B3: 115 | C3: Workbook LinkedIn capture: 2026-08-18 | D3: =COUNTIFS('Open Positions'!$A$2:$A$62,A3,'Open Positions'!$C$2:$C$62,"Vacancy")+COUNTIFS('Open Positions'!$A$2:$A$62,A3,'Open Positions'!$C$2:$C$62,"Paid internship / early career") -> 0 | E3: No current role located on the official website or reviewed public company channels. | F3: Prize-led seasonal promotions plus always-on occasions and heritage | G3: Somelier de grătar; cabin weekend; Easter/Europa FM; Rosé Vérité; office occasions; cellar heritage | H3: https://www.linkedin.com/company/beciuldomnesc/ | I3: Official social channels supply much of the campaign evidence.
A4: Purcari Wineries | B4: 103 | C4: Workbook LinkedIn capture: 2026-08-18 | D4: =COUNTIFS('Open Positions'!$A$2:$A$62,A4,'Open Positions'!$C$2:$C$62,"Vacancy")+COUNTIFS('Open Positions'!$A$2:$A$62,A4,'Open Positions'!$C$2:$C$62,"Paid internship / early career") -> 8 | E4: Five roles appear on the official paid-internship site; three additional recent corporate postings were found. | F4: Premium launches, ESG/research, education and international reputation | G4: Parcela; Orange wine; RDW; 4SIR2; biodiversity; scholarships; masterclasses; awards; 2X by 200 | H4: https://purcariwineries.com/en/category/news-en/ | I4: Public-company and official group sources provide strong current evidence.
A5: Cramele Recas | B5: 71 | C5: Workbook LinkedIn capture: 2026-08-18 | D5: =COUNTIFS('Open Positions'!$A$2:$A$62,A5,'Open Positions'!$C$2:$C$62,"Vacancy")+COUNTIFS('Open Positions'!$A$2:$A$62,A5,'Open Positions'!$C$2:$C$62,"Paid internship / early career") -> 0 | E5: No current role or dedicated careers page located on the official website or reviewed public channels. | F5: Festivals, vineyard-season stories, arts partnerships and awards | G5: RO-Wine; Revino; Maison AMÉ; Vienna Ball; Recolta 2026; Berliner Wine Trophy; winery tourism | H5: https://ro.linkedin.com/company/cramele-recas | I5: Campaign evidence is strong; employee count remains LinkedIn-associated.
A6: Via Viticola | B6: 45 | C6: Workbook LinkedIn capture: 2026-08-18 | D6: =COUNTIFS('Open Positions'!$A$2:$A$62,A6,'Open Positions'!$C$2:$C$62,"Vacancy")+COUNTIFS('Open Positions'!$A$2:$A$62,A6,'Open Positions'!$C$2:$C$62,"Paid internship / early career") -> 0 | E6: No current role or dedicated careers page located on the official Vintruvian Estates website. | F6: Terroir-led portfolio architecture, export activity and turnaround storytelling | G6: Caii de la Letea; Prince Matei; Vintruvian house; ProWein; founder revival; recipe contest | H6: https://www.linkedin.com/company/viaviticola | I6: Via Viticola is the marketing and sales company within Vintruvian Estates.
A7: Budureasca | B7: 39 | C7: Workbook LinkedIn capture: 2026-08-18 | D7: =COUNTIFS('Open Positions'!$A$2:$A$62,A7,'Open Positions'!$C$2:$C$62,"Vacancy")+COUNTIFS('Open Positions'!$A$2:$A$62,A7,'Open Positions'!$C$2:$C$62,"Paid internship / early career") -> 0 | E7: No current role or dedicated careers page located on the official website or reviewed public channels. | F7: Wine tourism, international trade/awards and people stories | G7: Experiențe cu Vin; Cină în Vie; Saguenay; ProWein; Alimentaria; Decanter; People of Budureasca | H7: https://ro.linkedin.com/company/budureasca1 | I7: Official LinkedIn is the strongest current campaign source.
A8: Zarea | B8: 39 | C8: Workbook baseline; public page showed 58 associated members in Aug. 2026 | D8: =COUNTIFS('Open Positions'!$A$2:$A$62,A8,'Open Positions'!$C$2:$C$62,"Vacancy")+COUNTIFS('Open Positions'!$A$2:$A$62,A8,'Open Positions'!$C$2:$C$62,"Paid internship / early career") -> 1 | E8: Official careers page lists an urgent Bucharest merchandiser opening; verify before applying. | F8: Heritage modernization, ambassadors, everyday occasions and convenient formats | G8: Ilie Dumitrescu; Gustul ne aduce împreună; dinner pairing; RTDs; summer menu; Zero.0% | H8: https://zarea.ro/stiri/ | I8: Website and official careers/news pages provide direct company evidence.
A9: Cramele Cotnari | B9: 23 | C9: Workbook LinkedIn capture: 2026-08-18 | D9: =COUNTIFS('Open Positions'!$A$2:$A$62,A9,'Open Positions'!$C$2:$C$62,"Vacancy")+COUNTIFS('Open Positions'!$A$2:$A$62,A9,'Open Positions'!$C$2:$C$62,"Paid internship / early career") -> 0 | E9: No current role or dedicated careers page located on the official website; an older sales post was excluded. | F9: National prize promotions, retail mechanics, event utility and Romanian provenance | G9: Caravana; Annabella; cinema tickets; calculator; Patria vinului bine făcut; heritage education | H9: https://www.cramelecotnari.ro/concurs | I9: Kept separate from Casa de Vinuri Cotnari.
A10: Casa de Vinuri Cotnari SA | B10: 17 | C10: Workbook LinkedIn capture: 2026-08-18 | D10: =COUNTIFS('Open Positions'!$A$2:$A$62,A10,'Open Positions'!$C$2:$C$62,"Vacancy")+COUNTIFS('Open Positions'!$A$2:$A$62,A10,'Open Positions'!$C$2:$C$62,"Paid internship / early career") -> 0 | E10: No current role or dedicated careers page located on the official website or reviewed public channels. | F10: #PurRomanesc, native varieties, estate heritage and social contests | G10: #PurRomanesc; IRIS; Inedit; Castelul Vlădoianu; native-variety ranges; awards | H10: https://www.vinuricotnari.ro/ | I10: Kept separate from Cramele Cotnari; premium portfolio entity.
A11: Murfatlar | B11: 14 | C11: Workbook LinkedIn capture: 2026-08-18 | D11: =COUNTIFS('Open Positions'!$A$2:$A$62,A11,'Open Positions'!$C$2:$C$62,"Vacancy")+COUNTIFS('Open Positions'!$A$2:$A$62,A11,'Open Positions'!$C$2:$C$62,"Paid internship / early career") -> 0 | E11: No current role or dedicated careers page located on the official website or reviewed public channels. | F11: Awards-led reputation rebuilding, hero products, terroir and corporate gifting | G11: CMB cycle; 3 Hectare; Charme de la Mer; Vinalies; holiday gifting; Dobrogea portfolio | H11: https://ro.linkedin.com/company/murfatlar-vinul | I11: LinkedIn-associated count is not payroll; campaign evidence is official-channel based.
A12: Domeniile Averesti | B12: 10 | C12: Workbook LinkedIn capture: 2026-08-18 | D12: =COUNTIFS('Open Positions'!$A$2:$A$62,A12,'Open Positions'!$C$2:$C$62,"Vacancy")+COUNTIFS('Open Positions'!$A$2:$A$62,A12,'Open Positions'!$C$2:$C$62,"Paid internship / early career") -> 0 | E12: No current role or dedicated careers page located on the official website or reviewed company channels. | F12: Indigenous-variety premiumization, education, partnerships and repeated export/trade activity | G12: Zghihară sparkling; Ione Cuvée 50; #CuriozitateaAverești; ProWine Tokyo; ProWein; Povestea Alb Vișinie; TIFF | H12: https://ro.linkedin.com/company/domeniile-averesti-romania | I12: Country-manager and campaign evidence is strong; member count remains LinkedIn-associated.
A13: Tohani Romania | B13: 10 | C13: Workbook LinkedIn capture: 2026-08-18 | D13: =COUNTIFS('Open Positions'!$A$2:$A$62,A13,'Open Positions'!$C$2:$C$62,"Vacancy")+COUNTIFS('Open Positions'!$A$2:$A$62,A13,'Open Positions'!$C$2:$C$62,"Paid internship / early career") -> 0 | E13: No current role or dedicated careers page located on the official website or reviewed public channels. | F13: Wine tourism and experiential events supported by heritage, music and premium Fetească Neagră | G13: Historic winery reopening; Subcarpați; anniversary tours; Vino unde se face vinul; Apogeum; trail race | H13: https://tohaniromania.com/pages/evenimente | I13: Official site provides unusually rich recurring event evidence.
... A16: Davino Winery | B16: 9 | C16: Workbook LinkedIn capture: 2026-08-18 | D16: =COUNTIFS('Open Positions'!$A$2:$A$62,A16,'Open Positions'!$C$2:$C$62,"Vacancy")+COUNTIFS('Open Positions'!$A$2:$A$62,A16,'Open Positions'!$C$2:$C$62,"Paid internship / early career") -> 0 | E16: A recent Sales & Development Director listing is closed/filled; no current vacancy page was located. | F16: Curated premium education, cultural sponsorships, vintage storytelling and selective launches | G16: Vast/Iacob premieres; Universul Davino; Trilogia Davino; Cu Drag MT; VINARIUM awards | H16: https://ro.linkedin.com/company/davino-winery | I16: Founder-leader evidence is strong; formal CEO title and education are not recently published.
A17: Crama Gîrboiu | C17: Public sources checked 2026-08-21; no LinkedIn capture | D17: =COUNTIFS('Open Positions'!$A$2:$A$62,A17,'Open Positions'!$C$2:$C$62,"Vacancy")+COUNTIFS('Open Positions'!$A$2:$A$62,A17,'Open Positions'!$C$2:$C$62,"Paid internship / early career") -> 0 | E17: No open role found. Recruitment presence is limited to a BestJobs employer profile with 6 alumni; the official site carries no careers route. | F17: Competition-led reputation building, anchored on repeat MUNDUS VINI producer titles, plus a long consumer prize promotion and selective export fairs | G17: Roata Vinului 2025; Decanter 2025 gold and Best Value; MUNDUS VINI Spring 2026 (21 medals); WineCon Chengdu 2026; Decanter 2026 | H17: https://cramagirboiu.ro/ | I17: Awards and campaign evidence are strong and current. No commercial staff are named in public sources, so the roster and type split are empty rather than estimated.
A18: Domeniile Vânju Mare | C18: Public sources checked 2026-08-21; no LinkedIn capture | D18: =COUNTIFS('Open Positions'!$A$2:$A$62,A18,'Open Positions'!$C$2:$C$62,"Vacancy")+COUNTIFS('Open Positions'!$A$2:$A$62,A18,'Open Positions'!$C$2:$C$62,"Paid internship / early career") -> 0 | E18: No open role found. Recruitment presence is a BestJobs employer profile under the producing company; neither official site carries a careers route. | F18: Local festival heritage, princely brand naming and domestic competition awards, sold through a separate distribution identity | G18: Festivalul Viei și Vinului 2026; VINVEST and Vinul.ro awards; Prințul Vlad and Emissarius ranges; Plaiurile Drâncei terroir claim | H18: https://domeniilevinjumare.ro/ | I18: Campaign evidence is regional and largely undated. No commercial staff are named in public sources.
A19: Licorna WineHouse | C19: Public sources checked 2026-08-21; no LinkedIn capture | D19: =COUNTIFS('Open Positions'!$A$2:$A$62,A19,'Open Positions'!$C$2:$C$62,"Vacancy")+COUNTIFS('Open Positions'!$A$2:$A$62,A19,'Open Positions'!$C$2:$C$62,"Paid internship / early career") -> 0 | E19: No open role found. Recruitment presence is a BestJobs employer profile with a single alumnus; the official site carries no careers route. | F19: A single outsized Decanter result worked hard, supported by manor-house wine tourism and collective regional promotion | G19: Decanter 2018 gold for Bon Viveur; standing awards page; Nicolau manor tastings; Serafim and Anno ranges; Asociația Dealu Mare | H19: https://www.licornawinehouse.ro/premii/ | I19: Award evidence is strong but dated; recent campaign activity is thin in public sources. No commercial staff are named.
A20: Gitana Winery | C20: Public sources checked 2026-08-21 | D20: =COUNTIFS('Open Positions'!$A$2:$A$62,A20,'Open Positions'!$C$2:$C$62,"Vacancy")+COUNTIFS('Open Positions'!$A$2:$A$62,A20,'Open Positions'!$C$2:$C$62,"Paid internship / early career") -> 0 | E20: No open role found. The winery publishes a People page naming four roles but advertises no vacancy and has no careers section. | F20: A trademark-led family house selling Romania-first, with new flagships launched under one name and the Moldovan country brand behind it | G20: Gitana trademark (2009); Romania-first retail and HoReCa model; Lupi and La petite Sophie launches; Wine of Moldova programme | H20: https://www.gitanawinery.com/en/ | I20: Moldova-based producer, included because Romania is its main market — not a Romanian winery. Roles come from the winery's own People page, so confidence is high but the roster is small by construction.
A21: Domeniile Sâmburești | C21: Public sources checked 2026-08-21; no LinkedIn capture | D21: =COUNTIFS('Open Positions'!$A$2:$A$62,A21,'Open Positions'!$C$2:$C$62,"Vacancy")+COUNTIFS('Open Positions'!$A$2:$A$62,A21,'Open Positions'!$C$2:$C$62,"Paid internship / early career") -> 0 | E21: No open role found. Recruitment presence is a BestJobs employer profile with 2 alumni under the producing company. | F21: An FMCG owner's playbook: a founder-named flagship, upward line extensions and prestige placements, backed by a national producer-of-the-year title | G21: Best national producer 2024; Carpathia and ALAI launches; Carpathia at Miss România; Château Valvis; Vinalies 2026 | H21: https://samburesti.com/en/ | I21: Ownership and campaign evidence are strong. No marketing or sales staff are named in public sources, so the roster is empty rather than estimated.
A22: Crama Rasova | C22: Public sources checked 2026-08-21; no LinkedIn capture | D22: =COUNTIFS('Open Positions'!$A$2:$A$62,A22,'Open Positions'!$C$2:$C$62,"Vacancy")+COUNTIFS('Open Positions'!$A$2:$A$62,A22,'Open Positions'!$C$2:$C$62,"Paid internship / early career") -> 0 | E22: No open role found. Recruitment presence is a BestJobs employer profile with 4 alumni; the site is commerce and events only. | F22: A destination winery: ticketed concerts on the Danube, a named star winemaker, a split serious-and-playful portfolio and direct e-commerce | G22: AER / AER LIBER concert series; Acasă la vin with Unvinpezi.ro (2025); Răzvan Macici releases; Creația vs Recreația ranges; Rasova&Friends | H22: https://www.cramarasova.ro/ | I22: Campaign evidence is unusually rich and self-published. No marketing or sales staff are named in public sources.
A23: Liliac Winery | C23: Public sources checked 2026-08-21; no LinkedIn capture | D23: =COUNTIFS('Open Positions'!$A$2:$A$62,A23,'Open Positions'!$C$2:$C$62,"Vacancy")+COUNTIFS('Open Positions'!$A$2:$A$62,A23,'Open Positions'!$C$2:$C$62,"Paid internship / early career") -> 0 | E23: No open role found. Recruitment presence is a BestJobs employer profile with 15 alumni under amb Wine Company. | F23: A region-owning brand platform run by a marketing-trained CEO, worked through cross-border collaboration, tourism investment and business-press presence | G23: Tandem with Castel Mimi; 3.4 m euro expansion and lodge; guardian-of-Transylvania platform; CEO interviews; tiered labels | H23: https://www.liliac.com/ | I23: Leadership evidence including education is strong. Beyond the CEO, no marketing or sales staff are named in public sources.
A24: Crama Oprișor | C24: Public sources checked 2026-08-21; no LinkedIn capture | D24: =COUNTIFS('Open Positions'!$A$2:$A$62,A24,'Open Positions'!$C$2:$C$62,"Vacancy")+COUNTIFS('Open Positions'!$A$2:$A$62,A24,'Open Positions'!$C$2:$C$62,"Paid internship / early career") -> 0 | E24: No open role found. The winery publishes a full named team with direct contacts but no careers page; a BestJobs employer profile exists under Carl Reh Winery. | F24: Cultural patronage and thorough localisation: a museum-partnered art prize, a Romanian place name over a German parent, and folklore-derived range names | G24: Premiile Crama Oprișor pentru Desen Contemporan; 2008 rename; La Cetate flagship; folklore brand naming; published sales team | H24: https://www.crama-oprisor.com/ | I24: The strongest publicly documented commercial roster of any winery added here — eight sales roles including a dedicated HoReCa manager, all from the winery's own team page. No marketing role is published.
A25: Domeniile Săhăteni | C25: Public sources checked 2026-08-21; no LinkedIn capture | D25: =COUNTIFS('Open Positions'!$A$2:$A$62,A25,'Open Positions'!$C$2:$C$62,"Vacancy")+COUNTIFS('Open Positions'!$A$2:$A$62,A25,'Open Positions'!$C$2:$C$62,"Paid internship / early career") -> 0 | E25: No open role found. Recruitment presence is a BestJobs employer profile with 11 alumni. | F25: A winemaker-as-brand house with the portfolio split by sales channel rather than by tier, plus small-batch storytelling and regional collective promotion | G25: Aurelia Vișinescu masterbrand; Nomad / Artisan / Karakter / Anima HoReCa split; Promessa and Etika retail lines; Asociația Dealu Mare; cellar visits | H25: https://aureliavisinescu.com/ | I25: Brand architecture is well documented; dated campaign activity for 2025–2026 was not found in public sources. No marketing or sales staff are named apart from the founder.
A26: Crama 1000 de Chipuri | C26: Public sources checked 2026-08-21; no LinkedIn capture | D26: =COUNTIFS('Open Positions'!$A$2:$A$62,A26,'Open Positions'!$C$2:$C$62,"Vacancy")+COUNTIFS('Open Positions'!$A$2:$A$62,A26,'Open Positions'!$C$2:$C$62,"Paid internship / early career") -> 0 | E26: No open role found. Recruitment presence is a BestJobs employer profile with 2 alumni. | F26: A naming concept that doubles as the brand story, extended into a plot-adoption programme and defended by HoReCa-only distribution | G26: 1000 de chipuri portrait labels; Vinul tău din via ta; HoReCa-only route to market; 2 m euro winery expansion; three collections | H26: https://1000dechipuri.ro/ | I26: Founder and business evidence is strong from business-press interviews. No marketing or sales staff are named in public sources.
A27: Casa de Vinuri Negrini | C27: Public sources checked 2026-08-21; no LinkedIn capture | D27: =COUNTIFS('Open Positions'!$A$2:$A$62,A27,'Open Positions'!$C$2:$C$62,"Vacancy")+COUNTIFS('Open Positions'!$A$2:$A$62,A27,'Open Positions'!$C$2:$C$62,"Paid internship / early career") -> 0 | E27: No open role found. Recruitment presence is a BestJobs employer profile with no published alumni count. | F27: A single owned symbol and a borrowed estate history, worked through national grocery listings rather than events or awards | G27: Ballerina emblem; General Teodrini estate provenance; Negrini Premium and Hex ranges; Negru de Drăgășani | H27: https://www.negrini.ro/ | I27: The thinnest public evidence base of the wineries added here: no dated campaigns, no awards and no named staff beyond the founder were located.
A28: Petro Vaselo | C28: Public sources checked 2026-08-21; no LinkedIn capture | D28: =COUNTIFS('Open Positions'!$A$2:$A$62,A28,'Open Positions'!$C$2:$C$62,"Vacancy")+COUNTIFS('Open Positions'!$A$2:$A$62,A28,'Open Positions'!$C$2:$C$62,"Paid internship / early career") -> 0 | E28: No open role found. A BestJobs employer profile exists but carries no company detail; the official site has no careers route. | F28: Organic certification and an Italian founding story, activated through a vineyard running event and winery hospitality rather than media | G28: La Petrovaselo în vie; organic certification; Bendis sparkling range; Dal Tio family story; winery events | H28: https://petrovaselo.com/en/ | I28: Ownership and positioning are well evidenced; no dated campaign spend or awards detail was located. No commercial staff are named.
... A31: SERVE Ceptura | C31: Public sources checked 2026-08-21; no LinkedIn capture | D31: =COUNTIFS('Open Positions'!$A$2:$A$62,A31,'Open Positions'!$C$2:$C$62,"Vacancy")+COUNTIFS('Open Positions'!$A$2:$A$62,A31,'Open Positions'!$C$2:$C$62,"Paid internship / early career") -> 0 | E31: No open role found. Recruitment presence is a BestJobs employer profile with 8 alumni; recruitment may move to the Purcari group route after the May 2026 acquisition. | F31: Primacy and mission: Romania's first post-1989 private winery, built on restoring Fetească Neagră and a quantified critical record, now inside the Purcari group | G31: Fetească Neagră restoration mission; 30-year anniversary (2024); 250+ medals and first 90-plus Parker FN; Povești cu vinuri românești 2025; Purcari acquisition (May 2026) | H31: https://business-review.eu/lifestyle/food-wine/serve-winery-30-years-of-excellence-in-the-production-and-promotion-of-romanian-wine-269267 | I31: Part of Purcari Wineries since 18 May 2026 — kept as its own row because its brands, team and campaigns ran independently until then. No marketing or sales staff are named in public sources.
